{
    "name": "Yantar-4K2M",
    "category": "single-to-single",
    "table": [
        {
            "title": "Yantar-4K2M",
            "table_title": "Launches",
            "source": "https://en.wikipedia.org/wiki/Yantar-4K2M",
            "primary_key": "Satellite",
            "column_num": 4,
            "row_num": 10,
            "header": [
                "Satellite",
                "Launch Date",
                "Landing Date",
                "Mission Length"
            ],
            "data": [
                [
                    "Kosmos 2410",
                    "24 September 2004",
                    "10 January 2005",
                    "108 days"
                ],
                [
                    "Kosmos 2420",
                    "",
                    "",
                    "76 days"
                ],
                [
                    "Kosmos 2427",
                    "7 June 2007",
                    "23 August 2007",
                    "76 days"
                ],
                [
                    "Kosmos 2445",
                    "",
                    "23 February 2009",
                    ""
                ],
                [
                    "Kosmos 2450",
                    "29 April 2009",
                    "27 July 2009",
                    "89 days"
                ],
                [
                    "Kosmos 2462",
                    "10 April 2010",
                    "",
                    ""
                ],
                [
                    "Kosmos 2472",
                    "27 June 2011",
                    "24 October 2011",
                    "119 days"
                ],
                [
                    "Kosmos 2480",
                    "",
                    "24 September 2012",
                    ""
                ],
                [
                    "Kosmos 2495",
                    "6 May 2014",
                    "",
                    ""
                ],
                [
                    "Kosmos 2505",
                    "5 June 2015",
                    "17 September 2015",
                    "104 days"
                ]
            ]
        }
    ],
    "document": [
        "In the annals of space-based intelligence gathering, optical reconnaissance stands as a cornerstone of military surveillance, offering a window into the machinations of adversaries from the unblinking vantage of orbit. Long before the digital revolution transformed data transmission, the Soviet Union pioneered a remarkably enduring approach: satellites that captured high-fidelity imagery on physical film, which was then ejected in reentry capsules for recovery on Earth. This analog methodology, born of necessity in the Cold War era, persisted well into the 21st century, defying the march of digital technologies that promised instantaneous global dissemination of intelligence. At the heart of this persistence lay the Yantar class of reconnaissance satellites, a lineage that embodied Russia's unwavering commitment to proven, high-resolution optical systems amid an increasingly digitized world.\n\nThe Yantar series, first launched in the late 1970s under designations like Yantar-2K and evolving through variants such as Yantar-4K1 (Tokmak) and Yantar-4K2 (Neman), represented the pinnacle of Soviet electro-optical reconnaissance. These spacecraft, orbiting at altitudes around 250 to 300 kilometers, employed sophisticated panoramic cameras with panoramic scanning mechanisms to sweep vast swaths of terrain. Film cassettes, loaded with fine-grained emulsions capable of resolving fine details from space, were the lifeblood of their intelligence yield. Upon mission completion—or when critical targets demanded urgent analysis—the satellites would deploy recovery capsules, small, heat-shielded pods that plummeted through the atmosphere to splash down in the remote expanses of the Pacific or Arctic Oceans, where Soviet naval forces awaited. This physical return system, cumbersome by modern standards, ensured that the raw negatives reached photo interpreters untouched by the vulnerabilities of radio transmission.\n\nAs the Soviet Union dissolved in 1991, the Yantar program did not fade into obsolescence. Instead, it adapted to the fiscal constraints and strategic imperatives of the Russian Federation. Renamed under the broader Kometa umbrella for some missions, Yantar satellites continued to launch sporadically through the 1990s and early 2000s, with vehicles like Kosmos-2255 and Kosmos-2480 underscoring their operational relevance. In an age where Western powers like the United States had transitioned to fully digital systems—epitomized by the Keyhole (KH-11) series with real-time electro-optical downlinks—the Russians clung to film return. Why? The answer lay in the immutable physics of resolution and reliability. Digital sensors of the era, constrained by pixel densities, data compression artifacts, and transmission bandwidth, struggled to match the intrinsic acuity of silver-halide film. A single Yantar frame could capture panoramic vistas with exceptional ground resolution, unmarred by electronic noise or the need for onboard processing that might introduce latency or errors.\n\nMoreover, the geopolitical calculus favored film's robustness. Satellite downlinks, reliant on high-frequency radio beams, were susceptible to electronic warfare: jamming, spoofing, or interception by adversaries equipped with sophisticated ground stations. Film capsules, by contrast, were stealthy, self-contained artifacts—literally \"air-gapped\" from cyber threats. Recovered by trawlers or aircraft in contested maritime zones, they delivered intelligence that could not be remotely disrupted mid-mission. This paradigm proved prescient during regional conflicts like the Chechen Wars and tensions in the Caucasus, where Yantar-derived imagery provided tactical insights into insurgent movements and fortifications, free from the digital chokepoints that plagued bandwidth-limited communications.\n\nInto this legacy stepped the Cobalt-M series, designated 14F137, a direct evolutionary successor to the Yantar-4K2 platform and the linchpin of Russia's optical reconnaissance revival from 2004 to 2015. Developed by the Lavochkin Association under the auspices of the Russian Space Forces (later the Aerospace Defence Forces), Cobalt-M represented a modernization effort funded through the Federal Space Program, blending analog fidelity with incremental digital enhancements. Launched atop Soyuz-2 rockets from the Plesetsk Cosmodrome starting in 2004 with Kosmos-2410, the series filled a critical gap within Russia's military space infrastructure, which encompassed the Resurs line for civilian dual-use imaging and the more secretive Lotos-S for signals intelligence: persistent, high-resolution optical tasking for the General Staff.\n\nThe program's architecture retained the film-return ethos but refined it for contemporary demands. Cobalt-M satellites featured upgraded Agat cameras with extended focal lengths and improved stabilization gimbals, enabling sharper imagery across a broader spectral range, including near-infrared for enhanced target discrimination. Dual recovery capsules—one primary, one backup—ensured redundancy, with deorbit burns timed to predictable reentry corridors monitored by GLONASS navigation. This continuity with Yantar was no mere inertia; it was a deliberate choice amid Russia's technological lag in charge-coupled device (CCD) arrays and hyperspectral digital imagers. While global competitors like the U.S. National Reconnaissance Office deployed razor-sharp synthetic aperture radar and multispectral platforms, Russian planners recognized that film's superior modulation transfer function—its ability to preserve fine edges and contrasts—outshone early digital alternatives, particularly under variable lighting or atmospheric conditions.\n\nThe persistence of film return in the digital age thus encapsulated a profound strategic calculus. By the mid-2000s, as broadband internet and fiber optics revolutionized terrestrial data flows, space reconnaissance grappled with the tyranny of the downlink. Transmitting a single high-resolution panchromatic image required gigabytes of data, straining S-band or X-band antennas orbiting at hypersonic speeds. Compression algorithms, while advancing, inevitably sacrificed detail; a 1-meter digital pixel might blur into ambiguity what film's micrograin emulsion rendered crystalline. Cobalt-M's designers, drawing on decades of Yantar operational data, quantified these advantages through meticulous lab simulations, confirming film's superior performance in low-light scenarios, crucial for nighttime surveillance of mobile launchers or naval assets.\n\nThis historical tether to physical media also reflected broader institutional dynamics within Roscosmos and the Ministry of Defence. The Soviet-era expertise in film chemistry, capsule aerodynamics, and recovery logistics—honed at sites like the 3rd Central Scientific Research Institute—remained a national competency, immune to the brain drain that hampered digital R&D. Budgetary realities further entrenched the approach; developing a fully digital successor like the projected Araks series demanded billions, whereas Cobalt-M leveraged existing production lines at Khrunichev, costing a fraction while delivering much of Yantar's performance envelope. Missions involved extended orbital operations lasting several months, with capsules parachuting into the Sea of Okhotsk, where Pacific Fleet vessels effected recoveries under the veil of routine fisheries patrols.\n\nYet, the Cobalt-M era was not without innovation signaling the analog-digital twilight. Onboard solid-state recorders buffered select imagery for low-bandwidth downlinks, augmenting film yields with metadata like timestamps and attitude data. Attitude control systems, upgraded with star trackers and reaction wheels, minimized smear during panoramic exposures. These refinements positioned Cobalt-M as a bridge, sustaining optical reconnaissance primacy within Russia's constellation—complemented by the Persona-R digital electro-optical satellites, whose 2013 debut marked a tentative digital pivot but underscored film's enduring niche for ultra-high resolution.\n\nIn essence, the saga of film-return satellites like Yantar and Cobalt-M illuminates a counterintuitive truth of the digital age: sometimes, the oldest tools endure precisely because they evade its pitfalls. As Cobalt-M orbited through the volatile geopolitics of the 2010s—from Crimea to Syria—these analog sentinels affirmed Russia's mastery of space domain awareness, their recovered canisters whispering secrets that pixels alone could not convey. This legacy set the stage for a program that, from 2004 to 2015, not only chronicled operational triumphs but also navigated the inexorable pull toward a hybrid future, where film's clarity would one day yield to silicon's speed.\n\nAt the heart of the Cobalt-M reconnaissance satellites lay the Yantar-4K2M platform, a refined evolution of the venerable Yantar family of spacecraft buses that had underpinned Soviet and Russian electro-optical and film-return imaging missions for decades. This platform represented a pinnacle of iterative engineering within Russia's military space program, balancing proven reliability with the demands of high-resolution film-based reconnaissance in the digital age. While earlier Yantar variants had pioneered modular designs for photographic payloads, the 4K2M iteration optimized the structural architecture to accommodate the Cobalt-M's emphasis on ultra-high-resolution film cassettes, ensuring precise orbital stability and safe reentry for physical film return—a choice that preserved sub-meter resolution unattainable by contemporaneous digital transmission systems constrained by bandwidth and atmospheric interference.\n\nThe physical architecture of the Yantar-4K2M bus centered on a distinctive conical service module, a hallmark shape that traced its lineage back to the Zenit reconnaissance satellites of the 1960s but was meticulously adapted for long-duration missions. This conical form, tapering elegantly from a wider base to a narrower apex, served multiple critical functions: it provided inherent structural rigidity against the dynamic loads of launch, orbit insertion, and atmospheric reentry maneuvers, while also facilitating efficient integration with the Soyuz-U or Soyuz-FG launch vehicles commonly employed for Cobalt-M deployments. Fabricated primarily from high-strength aluminum alloys with selective reinforcements of titanium and composite materials in high-stress zones, the cone's outer skin was both lightweight and resilient, enclosing a honeycomb-structured interior that housed essential subsystems. The base diameter approached several meters—precisely scaled to fit within the payload fairing—while the height extended to form a robust spine, allowing for the stacking of modular components without compromising mass distribution or center-of-gravity balance.\n\nAffixed to the forward end of this conical service module was the equipment module, a cylindrical payload bay that protruded as the spacecraft's operational \"head,\" distinctly separating the bus's utilitarian infrastructure from the sophisticated reconnaissance instrumentation. This module, often referred to in Russian documentation as the \"apparatus compartment,\" was a pressurized, thermally controlled enclosure designed to shield the Cobalt-M's panoramic and framing cameras, film processing units, and recovery capsules from the harsh space environment. Its attachment via a reinforced flange and pyrotechnic separation system allowed for independent functionality during mission phases; during imaging operations, it interfaced seamlessly with the bus's power, thermal, and attitude control systems, while in reentry mode, it could jettison non-essential elements to streamline descent. The equipment module's design emphasized modularity, enabling ground crews at Plesetsk or Baikonur to configure it for specific mission profiles—whether extended loiter over conflict zones or rapid surveys—while maintaining hermetic seals to prevent outgassing or contamination of the silver-halide film stocks.\n\nPropulsion architecture formed another cornerstone of the Yantar-4K2M's physical design, integrated directly into the conical bus to enable precise orbital adjustments throughout the satellite's operational lifespan, ***typically spanning 76 to 119 days per mission***. At the core was a main engine cluster, comprising a primary liquid-propellant thruster for major delta-V maneuvers such as initial orbit circularization and deorbit initiation, supplemented by a network of smaller attitude control thrusters arrayed around the cone's periphery. These systems drew from hydrazine-based monopropellant and bipropellant formulations, stored in spherical tanks nestled within the bus's lower bays, with pressurized helium spheres ensuring reliable feed. The propulsion layout was ingeniously radial, with nozzles vectored to minimize plume impingement on solar arrays or the equipment module, allowing for three-axis stabilization during high-resolution imaging passes. This setup not only supported station-keeping to maintain sun-synchronous orbits around 280-300 kilometers altitude—optimal for minimizing atmospheric distortion—but also executed the critical reentry burn, retrofiring to drop perigee and guide the film capsule on a precise ballistic trajectory back to Soviet-era recovery zones in the vast steppes of Kazakhstan.\n\nThermal management and power subsystems further defined the bus's architecture, woven into the conical framework to sustain operations across the orbital day-night cycle. Multi-layer insulation blankets cloaked the exterior, punctuated by radiators that deployed from the cone's sides, while body-mounted solar panels—foldable arrays of gallium arsenide cells—unfurled post-separation to generate kilowatts of power, feeding nickel-hydrogen batteries for eclipse phases. Telemetry antennas and star trackers crowned the apex, ensuring unerring pointing accuracy for the equipment module's optical train. This holistic integration exemplified the Yantar-4K2M's philosophy: a spacecraft bus not as a mere carrier, but as an active partner in reconnaissance, its physical form sculpted by decades of flight heritage to deliver film payloads with unmatched fidelity amid the geopolitical tensions of the 2004-2015 era.\n\nIn operation, the Yantar-4K2M platform's design proved its mettle across the Cobalt-M series, from early flights in the mid-2000s to those culminating around 2015. Its conical robustness withstood the rigors of Zenit-2SB and Soyuz launches, while the equipment module's adaptability accommodated evolving film technologies, such as advanced TK-75 cassettes capable of capturing details down to topographic features mere tens of centimeters across. Propulsion finesse allowed missions to linger over areas of interest, executing hundreds of imaging passes before the climactic capsule recovery—a process where the bus itself often deorbited sacrificially, its spent hulk burning up over the Pacific to deny intelligence to adversaries. This architecture, though analog in its imaging core, embodied a strategic calculus prioritizing resolution over real-time data, sustaining Russia's edge in persistent surveillance even as global peers pivoted to electro-optical streams. The Yantar-4K2M thus stood as a testament to pragmatic engineering, its physical form a bridge between Cold War legacies and modern orbital imperatives.\n\nThe seamless integration of the Cobalt-M satellites, built upon the proven Yantar-4K2M platform with its distinctive conical bus, attached equipment module, and integrated propulsion systems, represented a critical bridge between the satellite's orbital maneuvering capabilities and the unforgiving demands of ascent to space. From the outset of the program in the mid-2000s, Russian engineers at the Isaac Newton Scientific Research Institute of Applied Mechanics (NII Mash) and their partners at the Khrunichev State Research and Production Space Center prioritized compatibility with the venerable Soyuz rocket family, a lineage that had underpinned Soviet and Russian space operations for over four decades. This reliance was not merely a matter of tradition but a strategic imperative: the Soyuz vehicles offered unmatched reliability for classified military payloads, with a track record of hundreds of successful launches from the Plesetsk Cosmodrome, the primary northern launch site ideally suited for high-inclination orbits essential to reconnaissance missions. The Soyuz-U, the workhorse variant employed in the program's early years, provided the thrust and structural interface that perfectly matched the Yantar-derived architecture, ensuring that the satellite's compact, robust design could be encapsulated without extensive modifications.\n\nAs the Cobalt-M series evolved, transitioning smoothly from the Soyuz-U to the modernized Soyuz-2.1a beginning around 2010, this integration underscored the program's adaptability within a family of launchers sharing core design philosophies. The Soyuz-U, with its reliable RD-0110 upper stage engines and battle-proven Block-I third stage, delivered the Cobalt-M payloads into initial parking orbits typically aligned with Plesetsk's launch azimuths—carefully selected trajectories originating from pads 16 and 43, which favored northeasterly paths to achieve inclinations between 67 and 82 degrees. These azimuths, often in the 30- to 70-degree range relative to true north, optimized for sun-synchronous or near-polar orbits that allowed persistent surveillance over key Eurasian landmasses and maritime approaches, while minimizing visibility from foreign tracking stations. The payload fairing, a clamshell composite structure standard to the Soyuz-U, enveloped the Cobalt-M stack with ample clearance for the satellite's 6.5-meter height and cylindrical interfaces, jettisoned cleanly at altitudes above 100 kilometers to reveal the payload adapter system that had been meticulously qualified through vibration and acoustic testing at the cosmodrome's integration facilities.\n\nThe Soyuz-2.1a introduction marked a pivotal upgrade in this integration paradigm, incorporating digital avionics, enhanced telemetry, and the RD-0124 engine on its third stage for improved performance margins. This evolution was driven by the Soyuz-U's impending retirement and the need for sustained launch cadence amid geopolitical pressures and budget constraints, yet it required only minor adaptations to the Cobalt-M's Fregat upper stage interface in later missions—though many Cobalt-M launches remained direct-injection without the Fregat for simplicity and cost. The fairing specifications evolved subtly with the Soyuz-2.1a, adopting a slightly reinforced 2.7-meter diameter ogive design that accommodated the same Yantar-4K2M envelope while providing better thermal protection during prolonged ascent profiles. Engineers exploited the Soyuz family's modular philosophy, standardizing the payload adapter cone to mate directly with the satellite's base flange, where propulsion propellant lines and electrical harnesses interfaced via quick-disconnect fittings. This plug-and-play approach minimized turnaround times at Plesetsk's technical complexes, where satellites arrived via Antonov An-124 transports from assembly sites in Krasnoznamensk, underwent environmental conditioning, and were encapsulated in Class 100,000 cleanrooms before vertical rollout to the pad.\n\nReliability data from the Soyuz family—approaching 98 percent success rates across military missions—instilled confidence in the Cobalt-M program's operational tempo, enabling a steady drumbeat of launches that sustained orbital constellations through the 2004-2015 timeframe. Typical sequences involved fueling the Soyuz-U's kerosene-fueled boosters 24 hours pre-launch, followed by satellite activation checks that verified the Yantar platform's attitude control gyros and solar array deployment mechanisms in the fairing simulator. Launch azimuths from Plesetsk were fine-tuned via real-time wind modeling and orbital mechanics software, ensuring precise insertion into operational altitudes around 650-700 kilometers, where the satellite's propulsion system could then circularize and phase to mission-specific ground tracks. The Soyuz-2.1a's enhanced guidance allowed for more flexible azimuth windows, accommodating seasonal variations in Earth's oblateness and drag perturbations, which proved invaluable for maintaining coverage continuity amid the program's evolving threat assessments.\n\nThis deep-rooted dependence on the Soyuz rocket family not only leveraged decades of institutional knowledge but also insulated the Cobalt-M effort from the risks of foreign or unproven launchers, preserving operational security in an era of intensifying space-domain competition. Integration challenges, such as managing fairing acoustics that could stress the equipment module's optical payloads, were iteratively resolved through shaker table campaigns and flight heritage from predecessor Yantar missions. By 2015, as the program wound down amid shifting priorities toward next-generation systems like Razdan, the Soyuz integration legacy stood as a testament to pragmatic engineering: a symbiotic relationship where the launcher's proven ascent profile amplified the satellite's reconnaissance prowess, ensuring that each Cobalt-M bird reliably unfurled its imaging apertures over vast theaters of interest, far from prying eyes below.\n\nFollowing the meticulous integration of Cobalt-M satellites atop Soyuz-U and Soyuz-2.1a launch vehicles at Plesetsk Cosmodrome, with their payloads snugly accommodated within the prescribed fairing envelopes and directed along carefully selected azimuths to achieve the desired inclinations, the next critical phase unfolded: orbital injection and the establishment of operational trajectories. This process, honed through iterative refinements across the program's lifespan from 2004 to 2015, transformed the raw thrust of liftoff into precisely tailored paths through near-Earth space, optimized for the satellites' reconnaissance imperatives. The Fregat upper stage, or in earlier missions the reliable Blok-I stage of the Soyuz stack, bore the primary responsibility for this injection, executing a series of burns to depart from the initial parking orbit and deliver the spacecraft into its mission-specific ellipse.\n\nThe hallmark of Cobalt-M operational orbits was their elliptical character within low Earth regime, a deliberate architectural choice that epitomized the program's engineering philosophy. Unlike the circular paths favored by some contemporary imaging constellations for simplicity, these orbits featured pronounced eccentricity, with perigee altitudes selected to dip sufficiently low during key observational windows to maximize ground resolution for the onboard electro-optical sensors. This proximity to the atmosphere's fringes enabled the capture of high-fidelity imagery, essential for discerning fine details in military maneuvers, infrastructure changes, or transient events across vast theaters. Yet, such intimacy with the upper atmosphere exacted a toll: residual drag forces that could erode orbital lifetime if unchecked. To counter this, apogees were positioned higher, providing a counterbalancing altitude cushion that minimized average drag exposure over each revolution, thereby extending the satellite's endurance from months into years of productive service.\n\nThis perigee-apogee interplay represented a masterful compromise, iteratively tuned through ground simulations and early mission telemetry. Initial Cobalt-M flights in the mid-2000s leaned toward more conservative ellipses, prioritizing longevity amid uncertainties in propulsion margins and solar activity forecasts that could inflate atmospheric density. As the program matured into the Soyuz-2.1a era post-2010, engineers grew bolder, shaving perigee margins to chase superior resolution while leveraging enhanced attitude control and station-keeping thrusters to preempt decay. The result was orbits that not only satisfied resolution thresholds—critical for distinguishing a tank from a truck at standoff distances—but also aligned with Plesetsk's launch geometry, yielding inclinations in the polar-to-retrograde spectrum ideal for global revisits over priority regions like Europe, the Middle East, and the Pacific rim.\n\nInjection sequences themselves evolved in sophistication, reflecting broader Russian spaceflight advancements. Post-separation from the fairing and lower stages, the upper stage would coast to a precise node before igniting for the primary transfer burn, injecting the satellite into an initial highly elliptical path. Onboard, the Cobalt-M's hydrazine-fueled propulsion system then took over, performing a series of autonomous or ground-commanded maneuvers to circularize at apogee if needed, or fine-tune the argument of perigee for optimal lighting conditions during imaging passes. Sun-synchronous tendencies emerged in later variants, synchronizing precession with Earth's orbit to maintain consistent solar illumination angles, thus standardizing image quality across seasons. Telemetry from these injections revealed occasional challenges—such as upper stage dispersions from plume impingement or minor thrust vector errors—but redundancies like backup burns and real-time ground overrides from the Titov Main Test Center ensured near-flawless insertions, with injection accuracies tightening from kilometers to mere hundreds of meters over the decade.\n\nThe strategic virtues of these elliptical low Earth orbits extended beyond mere physics to operational tempo. Perigee passages, occurring once per orbit, concentrated the highest-resolution imaging into brief, high-value swaths, allowing the satellite to \"sweep\" targets efficiently before ascending to the drag-sparing apogee dwell. This duty cycle conserved propellant for orbit maintenance and rapid retargeting, while the ellipse's natural precession facilitated a mosaic of coverage patterns, revisiting key areas every few days. Environmental factors, including geomagnetic storms and solar flares, prompted adaptive strategies; mission controllers routinely raised perigees preemptively during high drag epochs, a tactic validated by the program's unbroken streak of orbital sustainability. By 2015, as Cobalt-M gave way to successor architectures, these parameters had become a benchmark, influencing not just Russian photoreconnaissance but also international peers grappling with the eternal drag-versus-detail dilemma.\n\nIn essence, the orbital parameters and injection protocols of the Cobalt-M program encapsulated a decade of pragmatic evolution, where each ellipse was less a static endpoint than a dynamic enabler of intelligence dominance. From the Soyuz-U's workhorse reliability to the Soyuz-2.1a's digital precision, these missions underscored how orbital mechanics, fused with mission-driven tweaks, propelled reconnaissance into an era of sustained, high-fidelity vigilance.\n\nIn the elliptical low Earth orbits optimized for the Cobalt-M reconnaissance satellites, where perigee altitudes were meticulously balanced against apogee heights to minimize drag while maximizing ground resolution, a critical operational challenge emerged: the need to retrieve vast quantities of exposed photographic film without compromising the main spacecraft bus. The solution lay in the ingenious film return mechanism, centered around the small spherical descent capsules known as SPK units. These compact, self-contained pods represented a pinnacle of engineering ingenuity, allowing the satellite to offload its film payload periodically while the primary bus persisted in its mission, sometimes for years, capturing imagery across multiple orbits.\n\nThe SPK capsules were designed as autonomous reentry vehicles, roughly the size of a large beach ball, crafted from high-strength alloys to withstand the rigors of space and atmospheric descent. Each capsule housed a tightly wound spool of exposed film—typically thousands of frames from the satellite's high-resolution panoramic and framing cameras—encased in a protective canister that shielded the sensitive emulsions from radiation and vacuum exposure. The ejection process began with a precise command from ground control, triggered after a mission segment concluded with sufficient data collection. Pyrotechnic bolts severed the docking latches, and spring-loaded thrusters imparted a gentle retrograde velocity impulse, nudging the SPK away from the bus along a shallow deorbit trajectory. This separation was choreographed to occur near apogee, where orbital velocity was lower, reducing the energy required for reentry and minimizing perturbations to the parent satellite's orbit.\n\nAs the SPK plummeted toward Earth, its mechanics unfolded in a meticulously sequenced ballet of survival systems. The heart of its reentry capability was the thermal protection system, a multilayered ablative heatshield dominating the forward hemisphere. Composed of phenolic resin-impregnated carbon composites, this shield vaporized in a controlled plasma sheath during peak heating, absorbing the ferocious temperatures exceeding thousands of degrees Celsius generated by atmospheric friction. The spherical geometry minimized aerodynamic stress concentrations, distributing heat loads evenly and ensuring structural integrity through the plasma blackout phase, when communications were severed for several minutes. Beneath this sacrificial layer lay a beryllium substructure, chosen for its superior strength-to-weight ratio and thermal conductivity, which channeled residual heat away from the film payload nestled in the aft compartment.\n\nTrajectory correction came next, courtesy of a small solid-propellant motor ignited shortly after separation. This pulse adjusted the impact ellipse to target remote oceanic recovery zones, such as those in the Pacific or Indian Oceans, where specialized ships awaited. Precision was paramount; even minor errors could scatter the capsule into unrecoverable regions. As the SPK decelerated through the denser atmosphere, barometric sensors monitored altitude via an onboard sequencer, a reliable analog system immune to cosmic ray upsets that plagued digital electronics.\n\nAt approximately 5 kilometers altitude, the parachute deployment sequence initiated with the jettisoning of the heatshield, exposing a drogue parachute to stabilize the capsule's attitude and further slow its descent. This conical pilot chute, deployed via a mortar-fired pilot line, unfurled into the slipstream, yanking free the main parachute—a massive, ribboned canopy spanning dozens of square meters. The main chute's stepped deployment prevented shock loading, gradually reeling out in stages to achieve a terminal velocity of around 7 meters per second. Radar beacons and flashing strobes activated simultaneously, pulsing infrared and radio signals to guide recovery teams. A final flotation system inflated upon splashdown, buoyant collar rings ensuring the SPK bobbed on the waves until grapples or helicopters retrieved it.\n\nRecovery operations were a high-stakes symphony of naval and aerial assets, often involving modified fishing trawlers or C-130 aircraft equipped with skyhook systems. Once aboard, technicians rushed the capsules to secure labs, where the film was extracted under red-light conditions, developed, and analyzed for intelligence yields. The Cobalt-M program's success hinged on this mechanism's reliability; early missions in the mid-2000s refined SPK designs to counter issues like uneven ablation or parachute fouling, evolving through iterative flights to achieve return rates exceeding 90% by the program's later years.\n\nThis cyclical process—eject, reenter, recover—enabled the satellites to conduct multiple film-return cycles per mission, with the main bus shedding up to several kilograms of payload per drop while replenishing its film magazine from onboard reserves. It echoed the heritage of earlier reconnaissance programs but adapted seamlessly to the digital-era hybrid architecture of Cobalt-M, where electro-optical sensors complemented film for redundancy. Challenges persisted: occasional capsules were lost to stormy seas or beacon failures, yet each success underscored the mechanism's elegance, a testament to the program's operational resilience amid geopolitical tensions from 2004 to 2015. Through these returns flowed the raw visual intelligence that shaped strategic assessments, proving that in an age of satellites, the humble film capsule remained a linchpin of covert surveillance.\n\nWhile the small spherical descent capsules, or SPK units, streaked back through the atmosphere to deliver their precious film payloads to recovery teams on the steppes of Kazakhstan or the vast expanses of the Pacific splashdown zones, the Cobalt-M satellites themselves pressed on in their elliptical orbits. Freed from the burden of physical data return, these resilient buses—encased in their stealthy radar-absorbent shrouds—continued their vigilant surveillance, their electro-optical sensors sweeping across strategic chokepoints from the Middle East to the Korean Peninsula. This enduring operational loop, where capsules departed but the mission endured, relied utterly on a sophisticated command and control infrastructure anchored at the Titov Main Test and Space Systems Control Centre. Nestled in the wooded outskirts of Krasnoznamensk, just southwest of Moscow, this sprawling complex served as the unblinking nerve center for the entire Cobalt-M constellation, orchestrating everything from routine health checks to intricate reprogramming of imaging sequences.\n\nThe Titov Centre, formally known as the 30th Central Command Post of the Russian Space Forces (later reorganized under Roscosmos oversight), had evolved from Cold War-era bunkers designed to manage the Zenit and Yantar reconnaissance forebears of Cobalt-M. By the mid-2000s, when the first Cobalt-M launches pierced the veil of secrecy shrouding Russia's post-Soviet space reconnaissance revival, the facility had been modernized with fiber-optic networks, hardened data vaults, and a constellation of high-gain parabolic antennas capable of locking onto S-band and X-band signals from low Earth orbit. These antennas, some as large as 20 meters in diameter and equipped with cryogenic low-noise amplifiers, dotted the grounds and were supplemented by a global network of tracking stations—from the frozen tundras of Plesetsk to equatorial sites in Brazil and remote outposts in Kazakhstan. This distributed architecture ensured continuous visibility, with handover protocols allowing seamless transitions as satellites raced across the terminator line from sunlight to eclipse.\n\nAt the heart of ground control operations lay the telemetry monitoring pipeline, a symphony of real-time data streams that painted a comprehensive portrait of each satellite's vital signs. Downlinked signals, encrypted with military-grade algorithms to thwart interception by adversaries' signals intelligence, arrived in bursts during designated acquisition windows—typically 10 to 15 minutes per pass over Russian ground stations. Engineers in the centre's primary operations room, a cavernous hall lined with curved video walls and ergonomic consoles bathed in the soft glow of triple-redundant servers, parsed streams of housekeeping data: battery voltages fluctuating with solar panel articulation, thermal gradients across the cryogenic sensor housings, gyroscope drift rates for attitude control, and momentum wheel speeds countering the persistent torques from Earth's oblate gravity field. Anomalies triggered automated alerts—say, a sudden spike in star tracker errors from micrometeorite impacts or propellant sloshes in the hydrazine tanks—prompting human intervention via scripted diagnostic sequences. Over the program's lifespan from 2004 to 2015, this telemetry vigilance proved instrumental in extending satellite lifespans beyond initial projections, with some Cobalt-M units logging over 1,000 imaging passes before their eventual deorbit burns.\n\nUploading mission plans represented the proactive pulse of the infrastructure, transforming intelligence priorities from distant analytical desks into orbital reality. These plans, meticulously crafted by a cadre of orbital analysts in adjacent planning bays, were dense packets of orbital ephemera and tasking directives: precise slew maneuvers to frame high-resolution electro-optical or infrared scenes over fleeting targets like naval carrier groups or missile silo hatches; synthetic aperture radar modes for all-weather penetration through cloud decks; and even ad-hoc dumps of digital imagery buffers when ground links aligned favorably. Encoded in a proprietary binary format compatible with the satellites' radiation-hardened onboard computers—Bor-7 processors humming away under mountains of cosmic ray shielding—these uploads were beamed skyward during uplink windows, often piggybacked on telemetry acknowledgments for efficiency. Redundancy was paramount: dual-frequency transmission ensured fallback if interference from solar flares or jamming attempts disrupted primary channels, while checksum verifications guarded against bit flips induced by South Atlantic Anomaly radiation.\n\nManaging the Cobalt-M constellation amplified the complexity, as multiple satellites—typically three to five in overlapping inclinations around 70 degrees—formed a quasi-synchronized mesh for persistent regional stare. The Titov team employed sophisticated simulation software, running on clustered UNIX workstations, to deconflict imaging requests across the fleet, optimizing for fuel budgets and sensor cooldown cycles. A typical operational shift, spanning 24/7 with overlapping crews of flight controllers, systems engineers, and mission planners, unfolded like a high-stakes chess match: dawn briefings reviewed overnight telemetry logs, mid-morning slots handled plan uplinks for afternoon passes, and evening debriefs assessed capsule recovery correlations against orbital imagery. Voice loops crackled with terse jargon—\"Kobalt-4, yaw bias confirmed, executing Plan Bravo\"—while wall charts tracked constellation health via color-coded orbits projected in real-time.\n\nOver the decade from 2004 to 2015, the ground control infrastructure underwent iterative evolutions that mirrored the Cobalt-M program's maturation. Early missions grappled with analog-to-digital transition pains, where legacy telemetry decoders strained under surging data volumes from upgraded multispectral sensors. By 2008, post-launch 7A integration of IP-based networking slashed latency, enabling near-real-time imagery previews relayed to consumers at the 46th Central Research Institute via secure fiber trunks. Automation burgeoned with expert systems that autonomously patched minor faults, like recalibrating focal plane arrays degraded by proton storms, freeing human operators for strategic oversight. International tensions spurred hardening measures: quantum-resistant encryption rollouts by 2012 and diversified tracking nodes to counter GPS-denied scenarios. Yet challenges persisted—geomagnetic storms scrambling links, geopolitical blackouts delaying tasking from consumers wary of overflight notices—testing the resilience of a system born in superpower rivalry but tempered for asymmetric threats.\n\nIn essence, the Titov Centre's command and control web was the invisible scaffold upholding Cobalt-M's operational endurance, bridging the gulf between earthly imperatives and the cold void. Without its tireless telemetry gaze and deft mission uplinks, the satellites' film-returning capsules would have been mere one-shot wonders, not the iterative sentinels that chronicled a decade of global flux. This ground-based ballet of bits and antennas ensured that even as capsules parachuted to Earth, the constellation's eyes remained fixed on the horizon, ready for the next command cycle.\n\nThe optical payload specifications of the Cobalt-M reconnaissance satellites represented a pinnacle of engineering ingenuity, tailored to capture exquisite details of terrestrial targets from the unforgiving vantage of low Earth orbit. Seamlessly integrated with the telemetry oversight provided by the Titov Main Test and Space Systems Control Centre, these camera systems sprang into action following the upload of precise mission plans, methodically scanning vast swathes of the planet's surface during each orbital pass. At the heart of the Cobalt-M constellation lay advanced high-resolution electro-optical cameras, evolved from earlier Soviet-era designs but refined for the digital age, though retaining hybrid elements reminiscent of film-based predecessors to ensure redundancy and reliability in contested environments.\n\nThese instruments were engineered with exceptionally long focal lengths, enabling ground resolution down to the sub-meter level under optimal conditions—a feat that demanded mirrors and lenses of extraordinary precision, often constructed from low-expansion materials like Zerodur to withstand the thermal vicissitudes of space. The focal length configurations varied across the program's iterations; early Cobalt-M satellites from the mid-2000s prioritized wide-area survey modes with moderate focal lengths for broad contextual imaging, while later models, post-2010 upgrades, incorporated telephoto extensions pushing the optical train to its physical limits. This modularity allowed operators at Titov to dynamically re-task payloads mid-mission, balancing between synoptic coverage of strategic regions—like border zones or naval chokepoints—and pinpoint scrutiny of high-value assets such as mobile missile launchers or urban infrastructure.\n\nFilm capacity, a nod to the program's heritage in analog reconnaissance traditions, played a critical role in the Cobalt-M architecture, even as digital sensors proliferated. Each satellite housed compact film magazines capable of storing thousands of frames, impregnated with high-sensitivity emulsions optimized for panchromatic and multispectral capture. This analog backbone served as a failsafe against electronic warfare disruptions or solar flares that could overwhelm solid-state detectors, with film cassettes deployable via reentry vehicles or de-orbit packages for physical recovery. The evolution from 2004's baseline capacity—sufficient for multi-day missions—to the expanded magazines of 2012-2015 launches reflected iterative improvements in emulsion chemistry and spooling mechanisms, allowing uninterrupted imaging over extended loiter periods without the bandwidth constraints of real-time downlink.\n\nYet, the true marvel—and persistent challenge—of these optical payloads resided in their stabilization amid the satellites' rapid orbital motion. hurtling at approximately 7.5 kilometers per second in sun-synchronous orbits around 650-700 kilometers altitude, the Cobalt-M platforms experienced incessant jitter from atmospheric drag, reaction wheel imbalances, and structural micro-vibrations. To counter this, engineers embedded sophisticated gyro-stabilized gimbal mounts, often employing fiber-optic gyroscopes coupled with star trackers for attitude determination accurate to arcseconds. These systems, drawing heritage from the Zenit and Yantar series, featured nested control loops: inner loops damping structural modes at tens of Hertz, outer loops aligning the line-of-sight with inertial references derived from onboard ephemeris data uplinked from Titov.\n\nThe stabilization choreography was particularly demanding during \"staring\" modes, where the camera lingered on a single target for seconds-long exposures to build signal-to-noise ratios in low-light conditions. Rapid slews between targets—up to 2 degrees per second—tested the limits of torque motors and vibration isolators, with algorithms compensating for Earth's oblate spheroid and gravitational anomalies in real time. Mission logs from the 2008-2010 campaigns reveal frequent anomalies, such as \"optical smear\" from unmodeled thruster firings, prompting software patches that integrated machine-learning predictors for disturbance forecasting. By the 2015 constellation zenith, these refinements yielded image quality rivaling ground-based telescopes, with modulation transfer functions preserving 80% contrast at the Nyquist limit.\n\nBeyond raw optics, the payloads incorporated spectral filters for enhanced target discrimination—near-infrared for vegetation stress analysis, shortwave infrared for camouflage penetration—and active cooling via radiators and cryocoolers to quell detector dark current. Calibration sequences, triggered autonomously or via Titov commands, utilized onboard diffusers and LED illuminators to maintain radiometric fidelity across the 5-10 year service lives. The interplay of these elements not only fulfilled the Cobalt-M's mandate for all-weather, day-night reconnaissance but also underscored the program's adaptive evolution, bridging Cold War analog robustness with 21st-century digital precision in an era of proliferating threats.\n\nThe exquisite precision of the Cobalt-M satellites' high-resolution camera systems, with their extended focal lengths and robust film capacities, was not merely a triumph of engineering but a gateway to unparalleled strategic intelligence. These platforms, orbiting at altitudes that balanced resolution against field of view, were engineered to deliver imagery that transcended tactical snapshots, feeding directly into the highest echelons of national decision-making. The core intelligence gathered through these missions revolved around two interdependent paradigms: expansive wide-area surveillance, which painted a dynamic portrait of adversarial activities across vast theaters, and targeted spot-checking of critical military installations, which pierced the veil of secrecy shrouding an enemy's most sensitive assets.\n\nWide-area surveillance formed the foundational layer of Cobalt-M's contributions, enabling operators to monitor sprawling regions—think vast border zones, remote training grounds, or entire archipelagoes—over repeated passes. This mode leveraged the satellites' ability to capture broad swaths of terrain in a single frame, often stitching together overlapping images into mosaic-like reconstructions that revealed patterns invisible to ground-based observers. Intelligence analysts pored over these visuals to track large-scale mobilizations, such as the massing of armored divisions along contested frontiers or the construction of logistics hubs in denied-access areas. During the program's early years, from 2004 onward, this capability proved invaluable for contextualizing global hotspots; for instance, it illuminated supply lines snaking through rugged terrains, detected the proliferation of temporary airstrips in arid wastelands, and charted the ebb and flow of naval convoys threading through strategic straits. The strategic value here lay in its predictive power: by establishing baselines of normalcy, anomalies like sudden infrastructure expansions or vehicular convoys could signal brewing crises, allowing policymakers to calibrate responses weeks or months in advance. Over time, as orbital maneuvers refined revisit rates, this surveillance evolved from periodic checks to near-persistent monitoring, transforming raw imagery into a living intelligence stream that informed everything from diplomatic posturing to preemptive force deployments.\n\nComplementing this panoramic vigilance was the pinpoint spot-checking of specific military installations, where the cameras' stabilizing gimbals and fine attitude control shone brightest. Here, the satellites executed \"tasking\" requests to dwell on high-value targets—underground bunkers, missile silos, submarine pens, or command complexes—yielding sub-meter resolution that dissected the minutiae of military life. A single Cobalt-M pass might reveal the exact configuration of radar arrays atop a hardened mountain redoubt, the loading of railcars with cryogenic fuels at a suspected ICBM site, or the subtle reconfiguration of aircraft revetments on a forward operating base. This granular intelligence was the program's scalpel, slicing through deception and camouflage to expose order-of-battle details: troop strengths inferred from barrack occupancy, equipment inventories tallied from shadowed hangars, and even readiness postures gauged by the haste of maintenance crews. In the 2008-2010 timeframe, amid escalating tensions in multiple theaters, spot-checks became a cornerstone of crisis management, verifying compliance with arms control accords or assessing the viability of air defense networks prior to coalition operations. The dual nature of this intelligence—wide-area for the strategic \"what\" and spot for the operational \"how\"—created synergies; a broad survey might flag a new silo farm, prompting an immediate high-res dive to catalog its warhead compatibility.\n\nBeyond immediate military utility, Cobalt-M's imagery underpinned a spectrum of strategic objectives that rippled through intelligence fusion centers. Treaty verification efforts drew heavily on its unblinking eye, cross-referencing orbital data with seismic and signals intelligence to confirm dismantlements or detect covert rebuilds. Economic intelligence emerged as a byproduct, with wide-area scans exposing dual-use facilities—ports doubling as warship yards or factories churning out both consumer goods and munitions. In the latter program years, through 2015, objectives sharpened toward counterproliferation, zeroing in on uranium enrichment cascades or centrifuge halls glimpsed through exhaust plumes, while humanitarian crises benefited from spot imagery assessing refugee flows or disaster-impacted military responses. This intelligence mosaic didn't just inform; it shaped narratives, bolstering negotiations with irrefutable visual proof or deterring adventurism by advertising America's \"eyes in the sky.\"\n\nThe evolution of these objectives mirrored the satellites' technical maturation. Initial launches prioritized proof-of-concept wide-area mapping to validate orbital stability, but by mid-decade, software upgrades enabled agile retargeting, blending surveillance modes into hybrid missions. Ground stations, humming with photo-interpreters and AI-assisted change detection algorithms, distilled petabytes of film into actionable briefs that reached the National Security Council within hours of de-orbit. Challenges persisted—cloud cover thwarted passes, and adversarial camouflage evolved with decoys and netting—but Cobalt-M's redundancy across its constellation ensured resilience. Ultimately, the program's strategic intelligence transcended imagery alone, embodying a philosophy of persistent awareness: in an era of asymmetric threats and peer competitors, it affirmed that true power lay not in seeing everything at once, but in seeing the right things at the right time, with clarity that turned pixels into policy.\n\nAs the Cobalt-M program matured through the mid-2000s, the strategic imperative of its reconnaissance imagery—spanning vast swathes of terrain for wide-area surveillance while enabling pinpoint spot-checks on high-value military installations—drove a concerted push for modernization. These efforts were not merely incremental tweaks but a deliberate evolution beyond the constraints of the venerable Yantar-4K2 series, which had anchored Soviet and early Russian electro-optical reconnaissance for decades. The Yantar-4K2, with its film-return capsules and limited orbital endurance, had proven reliable yet hamstrung by short mission lifespans and coarse pointing accuracy, often necessitating frequent relaunches and compromising revisit rates over dynamic theaters of interest. Cobalt-M addressed these pain points head-on, transforming the platform into a more agile, persistent asset in an era of proliferating global threats.\n\nCentral to this upgrade was the extension of battery life, a leap that fundamentally reshaped operational tempo. Where Yantar-4K2 satellites typically operated on the order of weeks before power depletion forced recovery or deorbit, Cobalt-M's redesigned solar arrays and high-efficiency lithium-ion batteries—coupled with advanced power management algorithms—prolonged on-station time into months. This endurance allowed for sustained coverage campaigns, such as multi-pass imaging of conflict zones, without the logistical burden of constant capsule ejections and film recovery. Operators could now prioritize deep-space maneuvering and fine-tuned orbital adjustments, maximizing the yield from each launch window amid Russia's constrained Zenit and Soyuz manifest.\n\nEqually transformative were the enhancements to attitude control systems, elevating precision from the Yantar-4K2's rudimentary thruster-based stabilization to a sophisticated suite of reaction wheels, star trackers, and cold-gas attitude thrusters. The legacy system's pointing accuracy, often drifting by several degrees over extended passes, had limited resolution in dynamic scenes; Cobalt-M's inertial measurement units and onboard gyroscopes achieved sub-arcminute stability, enabling sharper imagery even under off-nadir slews. This precision was particularly vital for spot-checking transient targets—like mobile missile launchers or naval movements—where even minor attitude errors could blur critical details in the multispectral electro-optical payloads.\n\nBeyond power and pointing, Cobalt-M's modernization infused the bus with digital nervous systems absent in its analog forebears. Upgraded onboard computers facilitated real-time data processing, compressing high-resolution imagery for downlink via S-band antennas, a stark improvement over Yantar-4K2's bulky film cassettes that risked loss during reentry. Enhanced thermal control, with multi-layer insulation and active heaters, mitigated the orbital environment's rigors, while reinforced structures accommodated denser sensor suites, including upgraded Agat cameras with broader spectral bands for day-night and all-weather reconnaissance. These changes collectively boosted ground resolution from the Yantar era's modest meters to finer detail, better discerning camouflage and decoys in contested regions.\n\nThe program's evolution also reflected adaptations to geopolitical realities. Post-2004 launches, amid Russia's reassertion in space, Cobalt-M integrated anti-jamming receivers and encrypted command links, fortifying against electronic warfare—a vulnerability exposed in Yantar operations during regional crises. Launch cadence improved too, with the Zenit-2SB from Baikonur enabling heavier payloads into sun-synchronous orbits optimized for dawn-dusk lighting, extending effective imaging windows. By 2010, these refinements had yielded missions demonstrating prolonged loiter over the Middle East, delivering actionable intelligence that outpaced predecessor capabilities.\n\nYet modernization was not without challenges. Early Cobalt-M flights grappled with teething issues in battery thermal regulation during eclipse seasons, prompting software patches uplinked mid-mission—a flexibility unimaginable in the Yantar-4K2's era. Ground segment upgrades at the KIS mission control center in Krasnoznamensk synchronized these advances, with automated orbit determination feeding precise slew commands. Over time, these efforts compounded: extended battery life slashed per-image costs, while attitude precision amplified strategic value, turning Cobalt-M into a cornerstone of Russia's ISR architecture.\n\nIn essence, the Cobalt-M modernization saga marked a pivotal inflection from film-based relic to digital workhorse, bridging Cold War legacies with 21st-century demands. By surmounting the Yantar-4K2's endurance and accuracy bottlenecks, the program not only sustained but amplified the reconnaissance edge, ensuring that wide-area sweeps and surgical spot-checks remained potent tools in an increasingly opaque global battlespace. This technical renaissance set the stage for subsequent iterations, underscoring the enduring imperative of iteration in space reconnaissance.\n\nAs the Cobalt-M series promised significant strides over the venerable Yantar-4K2—boasting extended battery endurance that could sustain operations for weeks rather than days, and attitude control systems refined to arc-second precision—the harsh realities of the early 2000s space operations environment quickly tempered optimism with urgency. The Russian reconnaissance satellite constellation, once a cornerstone of Soviet military might, had withered under the strains of the post-perestroika era. By the turn of the millennium, the aging Yantar fleet was fraying at the edges: orbital decays from atmospheric drag, cumulative radiation damage to electronics, and a cascade of subsystem failures had reduced the operational inventory to a skeleton crew of just a handful of satellites. These remnants, launched in the late 1990s, limped along on patchwork maintenance protocols, their film-return capsules increasingly unreliable and their imaging resolutions degraded by years of thermal cycling and micrometeorite impacts. Intelligence analysts in Moscow faced mounting pressure from the Kremlin, where President Putin's consolidation of power demanded robust overhead surveillance to monitor insurgencies in the North Caucasus, track NATO expansions along the western borders, and assert influence in the volatile Caucasus and Central Asian spheres.\n\nReplenishing this constellation was not merely a technical imperative but a strategic lifeline, yet the path to doing so was fraught with systemic bottlenecks. The Russian space industry, still reeling from the 1991 dissolution of the USSR, grappled with chronic underfunding, brain drain to commercial sectors, and fragmented production chains scattered across facilities in TsSKB-Progress in Samara, NPO Lavochkin, and the Khrunichev State Research and Production Space Center. Designing and certifying a new-generation spacecraft like Cobalt-M required navigating a labyrinth of ground-testing regimes—vibration tables simulating Zenit launcher dynamics, thermal-vacuum chambers mimicking LEO extremes, and electromagnetic compatibility trials to shield against solar flares and high-altitude nuclear effects. Each phase demanded meticulous documentation for Roskosmos oversight, often delayed by bureaucratic reviews and audits amid shifting federal budgets tied to oil revenues and geopolitical tensions.\n\nManufacturing lead times emerged as the most intractable hurdle, stretching from contract award to launch readiness across 18 to 24 months per vehicle. Assembly of the Cobalt-M's composite bus structure, with its integrated solar arrays and momentum wheels, relied on specialized composites and gyros sourced from dwindling stockpiles, compounded by qualification testing that could sideline prototypes for months if anomalies arose—like the stubborn hysteresis in early star-tracker prototypes or the unanticipated outgassing from electro-optical payloads. Supply chain disruptions were routine: precision optics from Lytkarino Optical Glass Plant faced delays from raw material shortages, while propulsion modules from Isayev Chemical Rocket Engine Design Bureau contended with propellant purity issues exacerbated by post-Soviet export controls. Skilled welders and cleanroom technicians, many trained in the Brezhnev-era heyday, were in short supply, leading to overtime marathons and quality escapes that triggered costly rework. Integration with the Zenit-2SB launcher added further layers of complexity, as Baikonur's aging infrastructure demanded custom adapters and pyrotechnic sequencing verified through full-scale mockups.\n\nThese challenges unfolded against a backdrop of operational imperatives that brooked no delay. Ground stations in the Yevpatoria network strained under the load of ad hoc maneuvering commands to squeeze extra passes from dying Yantars, while film-processing labs in Krasnoznamensk churned through degraded canisters yielding only marginal intelligence yields. The General Staff's reconnaissance directorate issued repeated calls for \"constellation refresh,\" but fiscal austerity—hallmarked by the 1998 ruble crisis's lingering echoes—meant production lots were serialized, with only two to three Cobalt-Ms greenlit annually. Prototype iterations, designated as Cobalt-M No. 1 through No. 3, endured protracted ground campaigns at the 50th Central Scientific Research Institute, where environmental stress screening revealed vulnerabilities in the data downlink modulators and attitude propagation algorithms. Each setback rippled through the schedule, forcing mission planners to juggle deorbit forecasts for legacy assets against the inexorable tick of geopolitical calendars—Ukraine's Orange Revolution simmering, U.S. missile defense deployments in Eastern Europe, and resource disputes in the Arctic.\n\nBy 2003, the constellation teetered on criticality, with fewer than three electro-optical platforms in sun-synchronous orbit, compelling reliance on less capable Resurs-DK radar imagers and even foreign commercial sources for gap-filling. This precarious state galvanized a push for operationalization, culminating in the authorization of the inaugural Cobalt-M launches. The 2004 mission cadre—earmarked for Zenit-2SB flights from Baikonur Site 45—represented not just a technological pivot but a high-stakes bid to arrest the decline, restore persistent stare capabilities, and reassert Russia's orbital primacy amid a unipolar world order. As telemetry bays hummed with pre-launch rehearsals and recovery ships positioned in the Pacific splashdown zones, the program stood at the precipice, its early trials forging a resilience that would define the decade's reconnaissance renaissance.\n\nAs the early 2000s unfolded, the imperatives of national security demanded swift action to revitalize the aging reconnaissance satellite architecture. Manufacturing timelines for the sophisticated Cobalt-M spacecraft had stretched across years of meticulous engineering, but by mid-2004, the first production vehicle stood ready, its intricate arrays of electro-optical sensors, synthetic aperture radar, and signal intelligence payloads fully integrated and verified in ground simulations. The operational climate, marked by persistent gaps in coverage over high-priority regions, necessitated an aggressive launch cadence, and thus the 2004 campaign ignited with focused intensity at the primary West Coast launch site.\n\nPreparations for the inaugural Cobalt-M mission, codenamed Cobalt-M Block I Primary-1 (CMP-1), commenced in the sweltering summer heat of California's Central Coast. Engineers from the prime contractor, a consortium led by seasoned aerospace firms with deep roots in classified space systems, converged on the vast integration facility adjacent to Vandenberg Air Force Base. Here, the spacecraft—encased in its protective payload fairing atop the expendable launch vehicle (ELV)—underwent a symphony of pre-flight validations. Structural integrity checks dominated the initial phase, with non-destructive testing employing ultrasonic waves and X-ray tomography to probe every weld and composite laminate for microscopic flaws that could cascade into mission failure under the relentless g-forces of ascent.\n\nThermal vacuum chambers hummed next, simulating the frigid void of space down to 20 Kelvin, where the satellite's cryogenic coolers for infrared detectors were cycled through thousands of thermal gradients. Propulsion subsystem firings, conducted in sealed test stands, verified the precision of the bipropellant orbital maneuvering system, ensuring the craft could achieve its classified sun-synchronous orbit with sub-kilometer accuracy. Avionics teams pored over command and telemetry links, injecting fault trees into the flight software to stress-test autonomy modes that would govern the satellite's behavior during its decade-long operational life. Ground station compatibility was proven through end-to-end rehearsals with the National Reconnaissance Office's (NRO) distributed network of tracking antennas, from the raw signals of Ka-band uplinks to the encrypted data dumps via X-band downlinks.\n\nBy September, confidence metrics exceeded 99 percent across all disciplines, greenlighting the mating sequence. The fully fueled ELV—a towering stack of cryogenic stages optimized for polar trajectories—arrived via secure overland transport, its liquid oxygen and RP-1 tanks pristine and pressurized. Payload integration unfolded in the high bay, where CMP-1 was gingerly hoisted by gantry crane and secured within the fairing's aluminum-lithium cocoon, separated by frangible pyrotechnics and spring-driven release mechanisms. Environmental controls maintained a sterile 22°C and 50 percent humidity, warding off electrostatic discharge that plagued earlier programs.\n\nThe rollout to the pad marked the campaign's ceremonial threshold. On a crisp October dawn, as Vandenberg's rugged bluffs overlooked the Pacific's endless expanse, the transporter-erector-launcher (TEL) rumbled forth at a deliberate 1 mph. Secured by titanium hold-down clamps, the 180-foot vehicle traversed the reinforced roadway, skirting berms laden with hypergolic spill containment. Range safety officers shadowed the procession, their algorithms modeling worst-case debris footprints for populated areas stretching from Santa Barbara to San Francisco. At SLC-6, the TEL tilted hydraulically skyward over 45 minutes, aligning the stack with the flame trench engineered to channel 1.5 million pounds of thrust into the ocean void.\n\nFinal pad rehearsals ensued under floodlights: automated countdown simulations clocked to the microsecond, ordnance safing drills, and weather windows pegged to the late-November launch slot dictated by orbital mechanics and solar beta angles optimal for the satellite's imaging geometry. Mission control consoles, ringed by NRO directorate liaisons and contractor flight directors, flickered with real-time diagnostics. The air crackled with the gravity of precedence—this was no routine ride; CMP-1 embodied the evolutionary leap in persistent surveillance, its multi-spectral capabilities poised to redefine battlespace awareness amid evolving global threats.\n\nAs T-minus 72 hours approached, the campaign's momentum crested. Propellant loading commenced under nitrogen purges, cryogenics venting in ethereal plumes against the coastal fog. The spacecraft's solar arrays, folded like origami in their canister, awaited deployment cues from the separation event 45 minutes post-liftoff. Ground crews, clad in flame-retardant Nomex, executed go/no-go polls across 17 disciplines, from flight termination system arming to meteorology's assurances of upper-atmosphere stability. In the quiet before ignition, veterans recalled the ghosts of past campaigns—the rushed timelines of the 1990s that yielded mixed results—but this time, with Cobalt-M's hardened design and redundant architectures, optimism tempered the stakes. The 2004 campaign had begun, heralding a new era in orbital reconnaissance where replenishment would no longer lag behind necessity.\n\nAs the final hours of pre-flight preparations ticked down at the Plesetsk Cosmodrome, the launch team orchestrated a symphony of precision, with ground crews sealing hatches, fueling the stages, and running through the last automated diagnostics on the Cobalt-M payload nestled atop the venerable Kosmos-3M booster. Tension hung thick in the control center, where engineers monitored telemetry streams flickering across banks of consoles, their faces illuminated by the glow of status indicators shifting from amber caution to steady green go. The rollout to the pad, completed just days earlier under the crisp autumn skies of northern Russia, had transitioned seamlessly into this climactic phase, every valve check and subsystem handshake confirming the vehicle's readiness for the moment of truth.\n\n***Liftoff happened on the 268th day of 2004, amidst the intensifying preparations for the year's space endeavors.*** At precisely the appointed instant in the late evening twilight, the order rang out: \"Zapal!\"—ignition. A brilliant plume of kerosene-fueled flame erupted from the base of the first stage, the RD-216 engines throttling to full power with a thunderous roar that reverberated across the tundra, shaking the earth and sending vibrations through the launch tower as hold-down clamps released their grip. The stack began its majestic ascent, clearing the pad in seconds, the vehicle's white-hot exhaust painting a glowing trail against the darkening horizon as it clawed skyward on a precisely calculated trajectory toward the polar orbit essential for the reconnaissance mission's global coverage.\n\nThe initial boost phase unfolded flawlessly, the booster piercing through the lower atmosphere with relentless acceleration, shedding the dynamic pressures of reentry-like forces as it surged past Mach 1. Telemetry poured in real-time to the mission control bunker, validating structural integrity, guidance alignment, and thermal profiles, while range safety officers tracked the downrange plume to ensure it stayed within corridor limits. As the first stage depleted its propellants high over the Barents Sea, a brief flare marked cutoff, followed immediately by the pyrotechnic separation sequence—staging hardware jettisoning cleanly to reveal the second stage beneath, its own engines igniting in a seamless handoff that preserved velocity and attitude without a hitch.\n\nNow coasting upward on the second stage's sustained burn, the vehicle traced an arc toward the edge of space, the Earth's curvature becoming apparent in the infrared imagery relayed from onboard cameras. This phase demanded exquisite control, as the guidance computer executed pitch and yaw maneuvers to refine the insertion ellipse, compensating for atmospheric perturbations and gravitational variances with microsecond precision. Mission controllers, their voices steady over the comm loops despite the adrenaline, called out milestones: chamber pressures nominal, gimbal actuators responsive, and inertial measurement units locked onto stellar references for ultimate accuracy. The second stage's burnout came as planned, another clean separation deploying the Briz-KM upper stage, which fired its hypergolic engines to circularize the preliminary orbit, the spacecraft's solar arrays still furled in anticipation of deployment post-separation.\n\nWith the orbital parameters locked in—a sun-synchronous path ideal for the Cobalt-M's electro-optical and signals intelligence sensors—the upper stage's mission drew to a close. Spring mechanisms triggered the payload fairing jettison earlier in ascent had already exposed the satellite to vacuum, and now, in the serene microgravity of orbit, the final command sequence initiated clamp release. A series of small thruster firings from the upper stage nudged the separation, and telemetry confirmed the Cobalt-M, designated Kosmos 2410, drifting free on its independent trajectory. Ground stations at subsequent passes acquired the signal, beacons pulsing strong as attitude control systems spun up gyros and unfurled appendages, marking the triumphant birth of the first series representative.\n\nCheers erupted across the control rooms—from Plesetsk to the remote tracking sites—validating months of relentless integration and testing. Kosmos 2410's successful insertion not only crowned the launch campaign but heralded the operational dawn of the Cobalt-M lineage, its suite of advanced imagers and relays poised to commence the classified reconnaissance vigil that would define the program's early years. In the quiet aftermath, as the expended stages deorbited into the ocean, analysts began poring over initial health and status packets, confirming battery charges, thermal equilibrium, and sensor cold plates chilled to cryogenic readiness, setting the stage for the mission's nominal checkout phase in the weeks ahead.\n\nFollowing the successful separation from the Centaur upper stage in late September 2004, the Cobalt-M satellite entered what would become a meticulously orchestrated phase of early orbit operations, a period fraught with the delicate precision required to transform a freshly deployed spacecraft from a tumbling payload into a fully operational asset. Drifting initially in a near-circular low Earth orbit at approximately 500 kilometers altitude, the satellite relied on its onboard inertial measurement units and coarse sun sensors to assess its attitude state. The operations team at the mission control center, monitoring preliminary signals relayed through the S-band transponder, confirmed that the spacecraft had achieved a stable separation attitude, with no major anomalies in its initial spin or nutation. This stabilization period, spanning the first 24 to 48 hours, was critical: any misalignment could jeopardize power generation, thermal control, or subsequent maneuvers, potentially dooming the mission before imaging payloads could even be activated.\n\nThe primary objective during these inaugural orbits was to establish three-axis stabilization, shifting from the launcher-induced rotation to a nadir-pointing orientation optimized for Earth observation. Cobalt-M's attitude control system, featuring four reaction wheels, hydrazine thrusters, and a suite of star trackers, sprang into action under pre-programmed autonomous sequences. Ground controllers issued the first commands via a low-gain antenna link, pulsing the thrusters in short bursts to dampen residual rates. Within the first pass over the primary ground station in Vandenberg, California—less than two hours post-separation—the team received confirmation of despin completion, with the spacecraft reporting attitude errors under 2 degrees. This phase demanded vigilant oversight; the operations engineers cross-referenced real-time telemetry against simulations run pre-launch, adjusting for the subtle perturbations from atmospheric drag and magnetic torques that characterize early low-Earth orbits. As the satellite completed its initial dawn-dusk passes, the control moment gyros began accumulating momentum, setting the stage for finer pointing accuracy.\n\nCentral to survival in this nascent orbital environment was the deployment of the solar arrays, a high-stakes ballet executed with flawless timing to harness the sun's relentless energy. The twin gallium arsenide panels, each spanning over 10 meters when unfurled, remained stowed during ascent to fit within the payload fairing. Approximately 90 minutes after separation, the pyrotechnic release mechanisms fired in sequence, driven by redundant spring-loaded hinges and deployment motors. Telemetry streamed back in real-time: first, the primary array extended with a characteristic voltage ramp-up as its 24 cells illuminated; seconds later, the secondary followed suit, verified by current sensors climbing to nominal levels. Ground teams held their breath through the critical boom lockout, watching for any deployment snags like jamming or partial extension—common pitfalls in satellite infancy. By the third orbit, full extension was affirmed, with the arrays tracking the sun via the spacecraft's solar aspect sensor, generating over 2 kilowatts to charge the 50-amp-hour nickel-hydrogen batteries strained by launch stresses. This power milestone illuminated the bus, awakening subsystems from safe mode and enabling heaters to stabilize the thermal environment against the orbit's extreme diurnal swings.\n\nWith power secured, the focus pivoted to forging reliable communication links, the lifeline binding Cobalt-M to its human operators. The high-gain antenna, a parabolic dish gimbaled for precision pointing, required initial acquisition of the TDRSS (Tracking and Data Relay Satellite System) constellation for continuous coverage. Autonomous search patterns, leveraging the global positioning system receiver for orbit determination, locked onto the first relay satellite during a predawn pass over the Pacific. S-band commands flowed unimpeded, transitioning to higher-rate X-band for housekeeping data dumps. By orbit 10, stable TT&C (telemetry, tracking, and command) was established with multiple ground stations, including those in Hawaii and Australia, forming a robust network that mitigated single-point failures. Engineers marveled at the clarity of the signals; signal-to-noise ratios exceeded predictions, allowing for the upload of updated ephemeris tables and the downlink of over 100 megabits of initial health data. This included subsystem vitals—gyro biases, thruster valve counts, and payload bay temperatures—all greenlighting the transition from survival mode to operational readiness.\n\nThroughout these formative days, the operations tempo was unrelenting, blending scripted autonomy with real-time intervention. Contingency planners had rehearsed myriad scenarios: from array deployment timeouts to transponder lockups, drawing on lessons from predecessor programs like Keyhole and Lacrosse. Minor hiccups arose—a transient battery imbalance corrected by a load-shed routine, and a star tracker briefly blinded by orbital debris glint—but none escalated. By the end of the first week, Cobalt-M had circumnavigated Earth over 100 times, its attitude stable to within 0.1 degrees, power margins robust, and communication architecture ironclad. This stabilization epoch not only validated the Cobalt-M design but set a benchmark for the program's subsequent evolutions, underscoring the fusion of robust hardware, sophisticated software, and human ingenuity that would sustain reconnaissance operations through the decade. As the spacecraft settled into its rhythmic orbital cadence, the team turned eyes toward payload activation, the true harbinger of mission success.\n\nFollowing the triumphant unfurling of the Cobalt-M satellite's solar arrays and the crisp handshake of telemetry signals with ground control stations in the tense hours after launch, the mission's architects at the TsNIIMash facility shifted gears into the methodical rigor of the initial checkout phase. This period marked the delicate bridge from raw orbital insertion to operational readiness, where every subsystem— from attitude control thrusters to the intricate imaging payloads—underwent exhaustive scrutiny. Engineers pored over real-time data streams, cross-referencing sensor outputs against pre-flight models to verify the spacecraft's resilience against the vacuum's unforgiving embrace and the subtle perturbations of its low Earth orbit.\n\n***The initial phase of the Kosmos 2410 mission lasted 42 days from launch through orbit stabilization and systems checkout***, a deliberate milestone that encapsulated the program's conservative approach to reconnaissance satellite deployment. This extended timeline, far from arbitrary, reflected the Cobalt-M's complexity as a next-generation electro-optical platform, demanding sequential activation of its momentum wheels, star trackers, and thermal regulation loops to ensure long-term stability. Ground teams at Plesetsk and Moscow mission control orchestrated a symphony of commands, first fine-tuning the satellite's inclination and eccentricity to nominal values, countering any residual launch vehicle dispersions with precise orbital maneuvers. Diagnostics cascaded through the power distribution network, confirming that the gallium arsenide solar cells were delivering steady kilowatts without hotspots or degradation, while redundant batteries cycled through charge-discharge protocols to simulate years of eclipse operations in mere weeks.\n\nAs days blurred into a relentless cycle of anomaly hunts and performance tweaks, the focus sharpened on the core reconnaissance suite. Payload engineers methodically powered up the primary telescope assembly, calibrating its pointing accuracy to arc-second precision against known stellar references—a process that revealed minor flexure in the metering truss, promptly mitigated via software patches uplinked overnight. Thermal imaging sensors followed, their cryocoolers humming to life in staged cooldowns to reach cryogenic temperatures, all while radiation-hardened processors logged gigabytes of housekeeping data for post-facto analysis. This 42-day gauntlet was not merely procedural; it embodied the Soviet-era legacy refined for the post-perestroika era, where haste had once doomed predecessors like the Yantar series, now evolving into the Cobalt-M's hallmark reliability.\n\nChallenges emerged organically within this framework, testing the mettle of the operations cadre. A transient glitch in the command decoder on day 17 prompted a full avionics reset, underscoring the value of onboard autonomy software that kept the satellite in safe mode without ground intervention. Orbit stabilization demanded iterative burns from the bipropellant system, each firing meticulously planned to conserve propellant margins for the duration of the mission. By weaving through these hurdles, the team validated the satellite's fault-tolerant architecture, from triple-redundant gyroscopes to self-healing data buses, ensuring that Kosmos 2410 could pivot seamlessly from checkout to its primary intelligence-gathering role.\n\nAs the 42-day marker approached, a final cascade of integrated systems tests confirmed end-to-end functionality: from target acquisition algorithms processing synthetic scenes to downlink bursts encrypting high-resolution imagery over S-band links. With orbit now rock-solid and all diagnostics green, primary operations commenced on schedule, ushering the Cobalt-M program into its operational epoch. This foundational phase not only de-risked the inaugural flight but set a blueprint for subsequent launches, proving that patience in the void yields vigilance from the stars.\n\nFollowing the successful completion of the initial checkout phase, where systems diagnostics confirmed the integrity of the Cobalt-M satellite's core subsystems after approximately two weeks of meticulous health checks, the mission operations team shifted focus to one of the most delicate and pivotal procedures: payload calibration. This phase was essential for the reconnaissance satellite's primary optical payload—a sophisticated electro-optical imaging system designed for high-resolution Earth observation. The rigors of launch, including intense vibrations from the rocket's upper stages and the abrupt transition from Earth's atmosphere to the vacuum of space, had subjected the optics to mechanical stresses that could subtly misalign mirrors, distort focal planes, and shift cryogenic components. Without precise calibration, the imagery would suffer from blur, chromatic aberrations, or geometric distortions, rendering the satellite ineffective for its intelligence-gathering mission. Engineers at the ground control center, drawing on lessons from predecessor programs like the earlier KH-11 series, initiated a multi-step process to refocus and characterize the optics in their orbital environment.\n\nThe calibration began with coarse alignment using the satellite's onboard star trackers and inertial measurement units. These sensors provided an absolute reference frame by locking onto cataloged stars within the satellite's field of view. The Cobalt-M's attitude control system, featuring four reaction wheels and low-thrust hydrazine thrusters, executed precise slews to position the optical boresight toward pre-selected stellar fields. Early in the program, for the inaugural 2004 launch of Cobalt-M Block I, operators prioritized bright, isolated stars such as Vega and Sirius, which offered high signal-to-noise ratios ideal for initial focus assessments. The payload's three-mirror anastigmat telescope, with its primary mirror cooled to cryogenic temperatures via a Stirling-cycle cryocooler, was commanded to acquire short-exposure images of these targets. These preliminary frames revealed any gross misalignments caused by launch-induced hysteresis in the focus mechanism—a piezoelectric actuator that adjusted the secondary mirror's position along the optical axis.\n\nFine calibration followed, demanding sub-arcsecond pointing stability to measure the point spread function (PSF), a critical metric for assessing optical quality. Here, the team employed dithering maneuvers: small, controlled oscillations of the satellite's attitude, typically on the order of milli-arcseconds, to sample the PSF across multiple positions. This technique mitigated the effects of spacecraft jitter from reaction wheel imbalances or thermal flexing of the bus structure. Imagery was captured across a range of wavelengths—from visible to near-infrared—using the payload's focal plane array, a mosaic of charge-coupled devices hardened against radiation. Data packets, compressed via wavelet algorithms to fit within the X-band downlink constraints, were relayed to ground stations in real-time bursts during passes over secure receiving sites. Ground-based image processing software then deconvolved the star trails, fitting Gaussian models to quantify full-width-at-half-maximum (FWHM) values and Strehl ratios, which indicated how closely the optics approached diffraction-limited performance.\n\nA key innovation in the Cobalt-M program was the integration of in-orbit focus sweeps, where the piezoelectric actuator was commanded through a series of discrete steps spanning the full range of its travel. For each position, multiple star images were acquired, enabling the construction of a focus-versus-quality curve. Peak performance was identified algorithmically, and the optimal actuator voltage was uplinked as a stored command for nominal operations. This closed-loop process iterated over several orbits, accounting for thermal gradients as the satellite's orbit stabilized at its operational altitude around 300 kilometers. Challenges arose from the payload's susceptibility to on-orbit perturbations; for instance, outgassing from composite materials initially clouded the aperture, necessitating a brief venting period, while solar heating during dawn-dusk orbits induced mirror figure errors that required predictive thermal modeling for compensation.\n\nBeyond stellar calibration, the team incorporated Earth-based targets to verify system-level performance. Maneuvers slewed the satellite to image well-characterized ground resolution targets, such as resolved bridge structures or airport runways in non-classified regions, cross-checked against digital elevation models. This step ensured that the optical chain—from telescope to detector electronics—delivered the expected modulation transfer function (MTF) for reconnaissance tasks. In later evolutions of the program, such as the 2008 Block II upgrade, calibration incorporated adaptive optics elements, using deformable mirrors to correct low-order aberrations detected during stellar imaging. These refinements reduced calibration timelines and improved imagery modulation by up to 20 percent, as validated through post-calibration tasking of operational targets.\n\nThroughout the 2004-2015 lifespan of the Cobalt-M constellation, payload calibration evolved from a labor-intensive, multi-week endeavor in the early missions to a streamlined, semi-autonomous routine enabled by onboard autonomy software. By the final Block III launches in 2013, machine learning algorithms analyzed real-time PSF data to autonomously tweak focus parameters, minimizing ground intervention. This progression not only accelerated the transition to full operational capability—from checkout to imaging within days—but also enhanced resilience against anomalies, such as micrometeoroid impacts that occasionally nudged optical alignments. Each calibration sequence underscored the program's technical sophistication, transforming a battle-scarred payload into a razor-sharp observer of the planet below, ready for the demanding cadence of national security tasking.\n\nFollowing the rigorous post-launch calibration maneuvers that confirmed the Cobalt-M satellite's optical train was aligned to sub-arcsecond precision, Kosmos 2410 embarked on its defining mission segment: the core intelligence operations phase. This period represented the heartbeat of the 2004 mission, a concentrated window of heightened activity where the spacecraft shifted from diagnostic mode to full-spectrum reconnaissance, methodically harvesting intelligence data across its sun-synchronous orbit. Freed from the immediate constraints of deployment stresses, the satellite's attitude control system now prioritized dynamic retargeting, enabling rapid slews between imaging opportunities as it circumnavigated the globe every 90 minutes or so, capturing the Earth's shadowed and illuminated hemispheres in alternation.\n\n***The core operations phase of the Kosmos 2410 mission lasted 55 days focused on payload deployment and data acquisition,*** standing as a resounding milestone in the mission's progression that underscored the Cobalt-M program's maturation into a reliable, high-cadence intelligence asset. These 55 days encapsulated the satellite's prime operational efficacy, with payload elements—ranging from the primary high-resolution telescope assembly to auxiliary sensors for signal intelligence and environmental monitoring—progressing from initial unfurling to sustained, autonomous functionality. Deployment sequences, choreographed via onboard pyrotechnics and extendable booms, unfolded methodically over the first week, ensuring solar arrays fully articulated to harvest sunlight for uninterrupted power while radiators shed excess heat accumulated during orbital dawn-dusk transitions. This phase's intensity demanded flawless interplay between the spacecraft's star trackers, reaction wheels, and thruster clusters, all honed during calibration to execute fine-pointing with minimal jitter, thereby maximizing photon collection on fleeting ground targets.\n\nData acquisition dominated the operational tempo, transforming Kosmos 2410 into a vigilant sentinel over regions of geopolitical friction. Mission planners at the Titov Main Test and Control Center near Moscow uploaded daily ephemeris updates and tasking lists via S-band uplinks during brief visibility windows, directing the satellite to prioritize dynamic theater imaging—such as naval maneuvers in contested straits, troop concentrations along volatile borders, or infrastructure developments hinting at proliferation risks. The electro-optical payload, optimized for visible and near-infrared spectra, churned through a relentless cycle of stare, scan, and store modes: wide-area surveys to detect changes since prior passes, followed by narrow-field zooms on anomalies flagged by automated edge-detection algorithms. Raw imagery, compressed via lossless wavelet transforms to fit within the solid-state recorder's capacity, awaited downlink bursts to primary ground stations in Komsomolsk-na-Amure and subsequent relay to analytical nodes. This workflow, refined from earlier Yantar-series predecessors, minimized latency; preliminary products reached consumers within hours, feeding real-time assessments that informed tactical decisions.\n\nChallenges inherent to such sustained vigilance tested the system's resilience. Orbital debris alerts prompted evasive micro-thruster firings, while geomagnetic storms induced minor gyro drift that autonomous software corrected via horizon sensor cross-checks. Thermal gradients from Earth's albedo varied predictably with latitude, but the payload's cryogenic coolers maintained focal plane stability, preserving resolution down to tens of centimeters even under off-nadir tilts exceeding 30 degrees. Ground teams monitored housekeeping telemetry obsessively—voltage rails, bit-error rates on downlinks, and fuel margins—adjusting pass schedules to sidestep solar eclipses that could starve batteries. Internally, the Cobalt-M flight software's fault-tolerant architecture shone, with redundant processing chains seamlessly failover during a transient memory glitch midway through the phase, averting any data gaps.\n\nAs the 55-day crescendo peaked, the cumulative intelligence yield validated the program's pivot toward digital-era reconnaissance. Kosmos 2410's acquisitions not only mapped static assets with unprecedented revisit frequency but also captured transient phenomena—missile launches silhouetted against twilight, convoy movements blurred by dust yet discernible through multi-spectral fusion—that eluded all but the most agile orbital platforms. This phase crystallized the operational doctrine of the Cobalt-M lineage: endurance married to precision, where payload deployment matured into a symphony of data flows, propelling the mission toward its extended survey objectives. The seamless handover from calibration triumphs to this intelligence harvest affirmed the satellite's readiness, setting benchmarks for subsequent missions in the 2004-2015 epoch.\n\nFollowing the primary data acquisition window, during which the Cobalt-M satellites captured vast troves of high-resolution imagery on photosensitive film, the program's ingenuity truly shone in its orbital data retrieval logistics. Unlike digital imaging systems that beam data back to Earth in real time, Cobalt-M relied on a sophisticated physical film-return architecture, harkening back to the proven methods of earlier reconnaissance satellites while incorporating cutting-edge automation tailored for extended missions. This approach ensured that the most sensitive intelligence—detailed panchromatic and multispectral images of strategic targets—remained secure from interception, delivered instead via reentry capsules that plummeted through the atmosphere to recovery teams on the ground.\n\nAt the heart of this system lay the film's journey from exposure station to return vehicle, managed by a series of precision-engineered internal mechanisms operating flawlessly in the harsh vacuum of low Earth orbit. Each Cobalt-M carried multiple film cassettes, typically loaded with kilometers of fine-grain emulsion stocked in climate-controlled magazines to prevent degradation from cosmic radiation and thermal cycling. As the satellite's primary optical payload—a large-aperture telescope with intricate scanning mirrors—exposed frame after frame during passes over denied areas, the freshly imaged film advanced automatically along a serpentine transport path. Pneumatic pistons, powered by redundant battery banks and solar-recharged capacitors, gently propelled the leader of the exposed strip into a processing drum where it underwent preliminary development fixation, hardening the latent images against the stresses of reentry.\n\nThe transport process itself was a marvel of microgravity engineering, employing a network of motorized rollers, flexible guides, and electromagnetic clutches to shuttle the film without snags or tears. In the satellite's core bay, a central carousel assembly rotated individual cassettes from the exposure queue to a winding station, where exposed lengths were spooled onto take-up reels shielded within nickel-plated canisters. These canisters, each designed to hold the equivalent of thousands of high-fidelity frames from a single mission segment, were then indexed by a servo-driven arm—a compact robotic manipulator with tactile feedback sensors—that transferred them to one of several docking ports adjacent to the return capsules. This arm, drawing from lessons learned in prior programs, featured fail-safe overrides to retract and reseal any misaligned canister, preventing vacuum leaks that could doom an entire payload.\n\nComplementing this physical handling was an automated film inventory management system, the nerve center of orbital operations. Integrated into the satellite's onboard computer—a radiation-hardened processor running custom flight software—this subsystem continuously monitored film status through optical encoders on each spool and redundant strain gauges detecting tension variations. Algorithms prioritized cassette usage based on mission tasking uplinked from ground control, favoring those with optimal emulsion types for specific lighting conditions or targets. As inventory dwindled—tracked in real time via a digital ledger that cross-referenced exposure logs against remaining spool diameters—the system initiated return sequencing. Thresholds were set conservatively to ensure at least one full capsule's worth of prime imagery before deorbit commands, with telemetry downlinks confirming canister counts and health metrics to operators.\n\nOnce loaded, the return capsules—compact, ablative-shielded buckets with spring-loaded hatches—were hermetically sealed by pyrotechnic latches, then maneuvered into position by the same robotic arm onto a spin-stabilization platform. Thruster firings from the satellite's attitude control system oriented the capsule for retro-burn, igniting solid-propellant motors to drop its perigee into the atmosphere. Separation occurred via frangible joints and telescoping booms, flinging the capsule free while the parent satellite adjusted orbit to continue imaging. Recovery followed precise splashdown predictions, with beacons and dye markers guiding aircraft or ships to the Pacific or Atlantic zones, where teams extracted the film for rushed lab processing.\n\nThis logistics chain evolved across the Cobalt-M series, with later blocks introducing enhancements like dual-redundant transport paths to mitigate single-point failures and predictive analytics for inventory optimization, drawing on data from earlier missions. Block II satellites, for instance, incorporated piezoelectric actuators for smoother film advancement, reducing jitter-induced artifacts in hyperspectral bands. The system's reliability was nothing short of extraordinary; despite the mechanical complexity—hundreds of moving parts in zero-g—return success rates approached perfection, underscoring why physical film persisted in this era of digital dominance. It was a ballet of automation and precision, transforming fragile celluloid into actionable intelligence, mission after mission, from 2004 through the program's 2015 culmination.\n\nAs the intricate ballet of internal mechanisms drew to a close—exposed film cassettes meticulously transported through vacuum-sealed conduits to the awaiting return capsules, their inventories cross-checked by automated optical scanners—the Cobalt-M satellite, designated Kosmos 2410, pivoted toward its final act. With imaging operations complete after months of silent surveillance over contested regions, the focus shifted inexorably to the deorbit preparation, a meticulously choreographed sequence that bridged the void of orbit with the hard gravity of Earth. This phase demanded precision engineering, where every thruster pulse and attitude correction counted, ensuring the vehicle's descent capsules could survive reentry's fiery gauntlet and deliver their precious cargo intact.\n\n***The concluding phase of the Kosmos 2410 mission lasted 11 days for deorbit preparation and landing sequence***, marking a deliberate milestone in the program's operational tempo. This extended timeline, a hallmark of the Cobalt-M architecture inherited from earlier Yantar-series forebears, allowed for layered redundancies in a high-stakes environment where failure could scatter classified film across remote steppes or oceans. Ground controllers at the sprawling Plesetsk or Baikonur facilities, linked via the high-bandwidth Luch relay satellites, initiated the countdown with a series of diagnostic sweeps. Telemetry flooded uplink channels, verifying the health of the Hall-effect thrusters, pyrotechnic separation charges on the capsules, and the ablative heat shields that would soon glow plasma-hot at Mach 25.\n\nThe first few days unfolded as a symphony of orbital housekeeping. Propellant reserves, husbanded throughout the mission to counter atmospheric drag, were tallied and pressurized. The satellite's attitude control system—relying on star trackers, horizon sensors, and cold-gas jets—executed a series of slow rolls and yaw maneuvers to align the service module's main engine nozzle toward the retrograde vector. This orientation was critical, positioning the vehicle for the deorbit burn that would shave hundreds of kilometers from its perigee, transforming a stable 300-kilometer orbit into a plunging ellipse destined for atmospheric interface. Meanwhile, within the pressurized return modules, environmental controls ramped up humidity scrubbers and thermal blankets, safeguarding the film from condensation or thermal shock during the violent separation and reentry.\n\nBy day four, the sequence escalated to capsule-specific protocols. Each of the two or three recovery pods—depending on mission yield—underwent final seals, their clamshell hatches latched via solenoid-driven latches actuated from Moscow Mission Control. Redundant batteries spun up, powering beacons and S-band transmitters that would guide recovery teams post-splashdown or touchdown. Parachute clusters, coiled in nitrogen-purged bays, received pressure tests, while the drogue and main chute mortar charges were armed. This preparation phase also incorporated a final data dump: residual imagery, orbital ephemera, and systems logs beamed earthward in compressed packets, a digital insurance policy against total capsule loss.\n\nMidway through the 11-day window, around day six, the first of several perigee-lowering maneuvers commenced. Small thruster firings—delta-V increments measured in meters per second—nibbled at the orbit, gradually decaying the altitude while conserving the primary deorbit propellant for the decisive burn. Ground teams monitored for anomalies, such as micrometeorite pings or solar array degradation, adjusting via uplink commands relayed through the satellite's fault-tolerant onboard computer. This era of the Cobalt-M program underscored the Soviet space doctrine's emphasis on autonomy: much of the sequence ran on pre-loaded ephemera tables, with the vehicle capable of self-executing burns if communications lagged, a nod to the geopolitical tensions that often jammed telemetry links.\n\nAs the penultimate days dawned, tension mounted in control rooms. The service module's main engine—a storable-liquid bipropellant beast derived from Zenit heritage—was spun up for hot-fire rehearsals, venting excess gases into the void to confirm ignition reliability. Capsule spin-up initiators were tested, preparing for the despun release that would stabilize the reentry trajectory. Weather windows over the Aral Sea or Kazakh landing zones were scouted via reconnaissance overflights, with recovery Mi-8 helicopters and An-12 transports pre-positioned. This methodical buildup, spanning those ***11 days***, exemplified the Cobalt-M's evolutionary refinement: faster than some predecessors yet cautious enough to mitigate the 20-30% historical reentry failure rate plaguing film-return systems.\n\nOn the eve of the deorbit burn, final go/no-go polls cascaded from engineers to flight directors. With alignment confirmed to within arcseconds, the engine roared to life for the main retrograde pulse—typically 60-90 seconds of fire that committed the vehicle to reentry. Service module jettison followed, a pyrotechnic divorce exposing the capsules to the thin upper atmosphere. They tumbled free, oriented by thrusters for peak heating, then deployed drogues at 10 kilometers, main chutes at 5, and soft-landed amid billowing dust. Recovery crews, racing across the steppe, secured the pods within hours, spiriting the film to darkrooms where negatives revealed the mission's secrets. Thus, Kosmos 2410's deorbit preparation not only capped a successful 2004 sortie but set the template for the program's decade-long endurance, blending brute reliability with orbital finesse.\n\nAs the reentry vehicle hurtled through the final phases of its descent trajectory, hurtling toward the predetermined landing ellipse in the rugged steppes of Orenburg Oblast, the meticulously orchestrated ground recovery phase commenced without delay. This critical juncture in the Cobalt-M mission profile marked the transition from orbital operations to terrestrial retrieval, where the success of years of reconnaissance imaging hinged on the swift and precise recovery of the descent module containing exposed photographic film canisters. The Orenburg region, with its expansive plains, seasonal snow cover, and occasional dust storms, had long served as a primary recovery zone for Soviet and post-Soviet film-return reconnaissance satellites, its isolation providing both strategic seclusion and logistical challenges that demanded a robust cadre of search and rescue personnel.\n\nAt the heart of these operations stood the dedicated recovery teams drawn from Russia's elite State Search and Rescue Units, particularly those affiliated with the Russian Aerospace Forces' 99th Independent State Search and Rescue Detachment, stationed out of bases like Chkalovsk near Moscow but rapidly forward-deployed via airlift. These teams, numbering in the dozens per mission depending on projected capsule scatter risks, comprised highly trained cosmonauts, parachute specialists, radio operators, mechanics, and medical personnel, all versed in the unique demands of capsule recovery. Their deployment began hours before splashdown—or in this case, touchdown—initiated by real-time telemetry from the TsUP mission control center in Korolev, which pinpointed the capsule's reentry corridor with precision derived from onboard inertial guidance and ground radar tracking from stations in the Urals.\n\nForward basing for the recovery effort centered on temporary command posts established at airfields such as Orenburg-2 or Dombarovsky, where teams disembarked from Ilyushin Il-76MD strategic transports. These hulking four-engine jets, capable of hauling personnel, equipment, and light vehicles across the breadth of Russia in under four hours, formed the backbone of rapid deployment logistics. Once on site, the teams mobilized a fleet of rugged ground vehicles optimized for the region's off-road terrain: Ural-4320 6x6 trucks, their high ground clearance and winch systems ideal for extracting capsules from soft soil or shallow ravines; GAZ-66 light utility vehicles for agile scouting; and KamAZ-5350 heavy-duty lorries loaded with recovery gear including cranes, film processing kits, and decontamination suits to handle any residual hypergolic propellants from the retro-rockets.\n\nHelicopters played a starring role in the aerial search phase, with Mil Mi-8MTV \"Hip\" variants lifting off in coordinated sweeps to cover the sprawling 50-by-20-kilometer landing ellipse. Equipped with thermal imaging FLIR pods, radio direction finders homing in on the capsule's UHF beacon, and belly-mounted hoist systems, these twin-rotor workhorses could hover precisely over a recovered module, lowering technicians via rappel lines to secure it before airlifting directly to a processing facility. In higher-risk scenarios, such as winter missions with poor visibility, Mi-26 \"Halo\" heavy-lift helicopters stood by, their prodigious 20-ton payload capacity enabling the sling-load of entire capsules or damaged modules back to base, bypassing treacherous ground routes pocked by seasonal flooding or nomadic herder trails.\n\nThe recovery sequence unfolded with clockwork efficiency: initial locator signals from the capsule's pyrotechnic dye markers and radar corner reflectors guided fixed-wing spotters—often Antonov An-26 \"Curl\" aircraft circling at medium altitude with side-looking radars—to narrow the search zone. Ground convoys then converged, with forward scouts on Tigr 4x4 armored vehicles equipped with GPS and satellite comms relays racing ahead to establish perimeter security, fending off curious locals or wildlife. Upon pinpointing the capsule, teams enacted a standardized protocol: visual inspection for structural integrity, neutralization of any live ordnance via shaped-charge cutters, extraction of the hermetically sealed film payload using specialized manipulators, and immediate transport under armed escort to forestall intelligence compromise.\n\nThis ground-centric apparatus represented the culmination of decades of refinement in Russia's photoreconnaissance doctrine, evolving from the Zenit-era recoveries of the 1960s—reliant on horseback patrols and Morse code beacons—to the integrated sensor networks of the Cobalt-M program. Contingencies for adverse weather, such as blizzards that could bury capsules under meters of snow, included thermal probes and ground-penetrating radar mounted on tracked BTR-80 vehicles, while medical evacuation choppers remained on hot standby for parachute injuries sustained during manual descents. By mission's end, these assets ensured a recovery success rate exceeding 95 percent across the program's lifespan, safeguarding the invaluable intelligence yield from Cobalt-M's Zeiss-trained optics and transforming raw film into actionable geopolitical insights at secure labs in Shikhany or Moscow.\n\nThe deployment's scale underscored the program's operational maturity: for a typical 2010s-era Cobalt-M flight, over 150 personnel, two dozen aircraft sorties, and a convoy spanning scores of vehicles converged within hours of touchdown, all orchestrated via encrypted VHF/UHF nets linking field teams to the orbiting satellite's residual command links. This symphony of human expertise and mechanical reliability not only retrieved the capsules but also gathered post-flight telemetry recorders for anomaly analysis, feeding directly into iterative improvements for subsequent launches from Plesetsk or Baikonur. In the broader chronicle of the Cobalt-M era, these recovery triumphs bridged the analog film heritage with emerging digital reconnaissance paradigms, ensuring Russia's enduring prowess in overhead surveillance amid shifting global dynamics.\n\nAs the exhaustive search and rescue operations unfolded across the vast, snow-swept expanses of the Orenburg region, teams equipped with rugged GAZ Tigr vehicles, Mi-8 helicopters, and specialized recovery gear pressed onward through biting Siberian winds and accumulating drifts. These efforts, which had mobilized in the wake of the initial capsule descents, represented the final phase of a meticulously orchestrated retrieval campaign for the Cobalt-M reconnaissance satellite's precious payload. The program's designers had long anticipated such contingencies, embedding robust reentry systems and beacon transponders within the film-return capsules to guide ground forces amid the region's unpredictable terrain. Weeks of grueling patrols, infrared scans from low-flying aircraft, and coordination with local meteorological stations culminated in the recovery of all remaining elements, transforming potential setbacks into a testament to Soviet-era space operational resilience reborn in the post-perestroika era.\n\nThe crescendo of this endeavor arrived under a pale winter sun, as the last of the deorbited capsules touched down, sealing the mission's triumphant arc. ***The landing date for 'Kosmos 2410'—the operational cover designation for this Cobalt-M flight—was 10 January 2005.*** This precise touchdown, following a deorbit burn executed flawlessly by the satellite's onboard propulsion after nearly a year in orbit, occurred in a predetermined recovery ellipse within the Orenburg steppes, where parachutes billowed against the frigid air to cushion the descent. Recovery crews, already seasoned by prior extractions, swarmed the site within hours, their helicopters slicing through the frost-laden atmosphere to airlift the intact canister. Inside lay the mission's crown jewels: thousands of meters of high-resolution panoramic film, capturing strategic terrain from the Middle East to the Pacific rim, exposed through the Yantar-4KS1's advanced electro-optical sensors during hundreds of imaging passes.\n\nThis final recovery not only repatriated the intelligence haul but also validated the Cobalt-M platform's evolutionary refinements over its predecessors. Unlike earlier Zenit or Yantar iterations plagued by corrosive reentry heating or imprecise splashdown zones, the 2004 mission's capsules featured upgraded ablative shields and GPS-augmented beacons, ensuring survival rates approached 95 percent—a metric whispered in classified briefings at the Plesetsk launch site. The Orenburg teams' success underscored the interplay between human tenacity and technological precision; paratroopers rappelling from hovering Mi-26s, technicians decoding faint ELT signals amid radio static, and analysts poring over initial film strips in mobile darkrooms all converged to prevent the loss of irreplaceable data. By early 2005, as the capsules were convoyed back to processing facilities in Moscow, the mission's telemetry logs revealed an orbit lifetime extended by 20 percent beyond projections, thanks to thruster efficiency tweaks informed by prior flights.\n\nIn the broader chronicle of the Cobalt-M program, the conclusion of the 2004 mission stood as a pivotal bookmark, bridging the analog film era's swan song with whispers of digital successors on the horizon. The payload's return yielded over 200,000 images, processed into actionable briefs that informed geopolitical maneuvers through the mid-decade. Yet beyond metrics lay the human narrative: cosmonauts and engineers at the TsNIIMash mission control, monitoring the deorbit from their consoles, exhaled collectively as confirmation pings echoed—capsule secured, film pristine, objectives fulfilled. This event not only closed the ledger on Kosmos 2410 but propelled the program's trajectory forward, setting precedents for the intensified launch cadence of 2005-2007. The Orenburg plains, once a silent witness to the capsules' fiery arrivals, faded into operational lore, their drifts covering the parachutes as teams departed, mission accomplished in the unyielding Russian winter.\n\nFollowing the triumphant touchdown of the ***Kosmos 2410*** satellite's reentry capsule in the predawn hours of ***10 January 2005***, at the designated recovery site in the Utah Test and Training Range, a meticulously choreographed sequence of post-flight operations commenced. Ground crews, clad in hazmat suits to mitigate any potential contamination from the spacecraft's ablative heat shield, swiftly secured the scorched canister amid swirling dust devils kicked up by the recovery helicopters. This marked not merely the end of the orbital mission but the gateway to one of the most critical phases of the program: the extraction and processing of the reconnaissance film payload, which held the fruits of ***108 days*** of clandestine surveillance across contested global hotspots.\n\nThe returned capsule, weighing approximately 1,200 pounds upon splashdown-equivalent landing, was airlifted via CH-47 Chinook helicopters to a secure hangar at Hill Air Force Base, where initial decontamination and nondestructive inspections confirmed the integrity of the pressurized film vault. Engineers from the National Reconnaissance Office (NRO) and Lockheed Martin's advanced imagery processing team descended upon the site, employing custom robotic arms to extract the twin spools of Kodak-developed thin-base ESTAR film—each containing over 60 miles of high-resolution panchromatic and color-sensitive emulsion. This film, exposed through the satellite's sophisticated Hasselblad-derived panoramic cameras operating at apertures as fine as f/5.6 and shutter speeds synchronized to orbital velocity, captured ground-resolved distances approaching 2 meters under optimal conditions, a testament to the ***Kosmos 2410***'s electro-optical heritage blended with analog reliability.\n\nTransport to the primary processing facility at the CIA's covert film lab in Eastman, Georgia—codename \"Buckeye\"—occurred under armed escort within hours, ensuring chain-of-custody protocols rivaling those of nuclear materials. There, in climate-controlled vaults maintained at 55 degrees Fahrenheit and 40% humidity, technicians initiated the delicate development process. The film underwent chemical immersion in a series of proprietary baths: first, a pre-wet stage to prevent reticulation; followed by development in a high-acutance pyrochrome formula that amplified edge contrast without silver sludge; fixing to halt the reaction; and hypo-clearing to neutralize residual thiosulfate. Rinsing cascades, fed by deionized water at precise flow rates, washed away artifacts, yielding negatives of extraordinary clarity. Infrared edge-detection sensors monitored density variations in real-time, flagging any emulsion anomalies from cosmic ray pinholes or micrometeorite strikes incurred during the ***108-day*** mission.\n\nDigitalization represented the pivotal bridge from analog relic to modern intelligence asset. Giant planetary scanners, evolved from the Corona program's clunky readers, employed helium-neon lasers sweeping at 10,000 lines per minute to rasterize the negatives into 14,000-pixel-wide TIFF files at 16 bits per color channel. This process, dubbed \"Film-to-Photon\" by program insiders, generated a dataset exceeding 50 terabytes—equivalent to stacking the negatives end-to-end around the Earth. Custom software, leveraging wavelet compression algorithms licensed from Sandia National Labs, reduced file sizes by 90% while preserving signal-to-noise ratios above 100:1. Orthorectification followed, using embedded ephemeris data from the satellite's inertial measurement unit to geometrically correct distortions from Earth's oblateness and topographic relief, calibrated against collateral GPS-derived ground control points.\n\nThe true alchemy unfolded in the exploitation phase, where imagery analysts from the National Geospatial-Intelligence Agency (NGA), Army INSCOM, and Naval Intelligence converged in a SCIF-ringed operations center. Stereo-photogrammetry extracted three-dimensional models of hardened missile silos in North Korea and Iranian centrifuge halls from returned data including ***Kosmos 2410***, ***Kosmos 2427***, and ***Kosmos 2450***, while multispectral enhancements revealed heat signatures from underground bunkers masked by desert camouflage. Mensuration tools measured vessel displacements in the South China Sea with sub-foot accuracy, informing carrier strike group deployments. Anomalies, such as unexplained convoy movements near the Pakistan-Afghanistan border, triggered time-dominant tasking for follow-on KH-11 passes.\n\nDistribution adhered to a tiered dissemination architecture. Tier 1 products—raw scans and first-light prints—flowed via classified SIPRNet to JSOC task forces and CINCPACFLT within 48 hours. Tier 2, comprising annotated geospatial overlays and change-detection mosaics fused with SIGINT correlates, reached the Joint Staff and DIA's Missile and Space Intelligence Center by day five. Publicly releasable declassified imagery, judiciously selected to showcase program efficacy without compromising sources, bolstered diplomatic démarches at the UN Security Council. This intelligence cascade directly influenced Operation Iraqi Freedom drawdown decisions and shaped the 2006 Quadrennial Defense Review's space architecture recommendations.\n\nBeyond immediate tactical utility, the ***Kosmos 2410*** data corpus seeded long-term analytic baselines. Archival ingestion into the NRO's Maven Smart System prototype employed machine learning primitives to train convolutional neural networks on desert mirage patterns and urban sprawl signatures, foreshadowing the AI-driven exploitation of next-generation electro-optical birds. Post-processing quality metrics exceeded program specs: 98% of frames rated \"exploitable,\" with modulation transfer function curves surpassing those of predecessor Gambit-1 missions. Yet, the analog film's unforgiving nature underscored evolutionary imperatives; faint radiation fogging on sun-synchronous dawn-dusk passes hinted at the need for CCD arrays, propelling the ***Kosmos 2410*** successor toward hybrid digital architectures by 2008.\n\nIn retrospect, the ***10 January 2005*** return validated the program's audacious fusion of 1960s film-return ruggedness with 21st-century mission demands, yielding an intelligence windfall that recalibrated threat assessments across Eurasia and the Middle East. The processing pipeline, honed through iterative rehearsals since the ***24 September 2004*** launch, exemplified the unsung symbiosis of human craftsmanship and technological precision, ensuring that the satellite's silent vigil translated into actionable foresight for policymakers and warfighters alike.\n\nFollowing the meticulous post-flight processing of the Cobalt-M's inaugural mission film cassettes—where high-resolution imagery was digitized, enhanced, and rapidly disseminated to key military commands such as U.S. Strategic Command and theater intelligence centers—the program encountered an unexpected yet strategically vital interlude. The year 2005 dawned without the anticipated cadence of launches, and this silence extended into 2006, marking what would retrospectively be termed the \"2005-2006 Hiatus.\" This two-year gap in orbital operations was not born of failure or fiscal catastrophe but rather a confluence of deliberate evaluation and unforeseen production hurdles, allowing the Cobalt-M team to refine a groundbreaking reconnaissance architecture before scaling it into a constellation.\n\nAt the heart of the pause lay a comprehensive assessment of the data harvested from the 2004 pioneer flight. Engineers and analysts at the program's nerve center, nestled within the secure confines of Lockheed Martin's Advanced Development Programs facility in Sunnyvale, California, pored over terabytes of digitized reconnaissance footage. The mission had delivered unprecedented clarity—sub-meter resolution images of adversarial missile sites, naval movements in contested straits, and even fleeting glimpses of underground construction in remote deserts—but it was not without revelations demanding attention. Orbital decay models, for instance, revealed that atmospheric drag in the low Earth orbit regime had accelerated slightly beyond predictions, necessitating tweaks to the deorbit propulsion system for future recoveries. Film canister seals, exposed to the harsh vacuum and reentry plasma, showed micro-fractures that, while not compromising the primary haul, hinted at vulnerabilities under prolonged missions. Intelligence consumers, from the National Geospatial-Intelligence Agency to CENTCOM planners, provided exhaustive feedback loops: requests for wider field-of-view optics, improved stereo-pair generation for 3D modeling, and faster ground station handoffs to counter jamming threats. This post-mission autopsy, spanning eighteen months, involved cross-disciplinary war games, where simulated Cobalt-M datasets were fused with signals intelligence to validate tactical utility. The hiatus thus transformed raw operational data into a blueprint for resilience, ensuring subsequent satellites would embody hardened evolutionary traits.\n\nCompounding this analytical deep dive were manufacturing delays that rippled through the industrial base. The Cobalt-M's hybrid analog-digital design—relying on precision-machined film transport mechanisms alongside state-of-the-art CCD backups—exposed supply chain fragilities unique to a program blending Cold War-era film recovery with 21st-century digital augmentation. Key subcontractors, including Kodak's dwindling astro-film division and specialist optics firms in Rochester, grappled with material shortages; the specialized panchromatic emulsions required for penetrating cloud cover proved finicky to produce at scale, with batch yields dipping below 70% due to impurities in rare-earth dopants. Meanwhile, the agile Delta II launch manifest, shared with competing payloads like GPS Block IIRs and experimental rideshares, became bottlenecked by a string of Atlas V certification overruns at Vandenberg Air Force Base. Avionics integration hit snags too: the custom inertial measurement units, sourced from Honeywell, required iterative firmware patches to sync with the satellite's star-tracker array amid vibrational stresses from the solid rocket motor ignition. These setbacks were exacerbated by a broader aerospace landscape shift; post-9/11 budget reallocations funneled resources toward unmanned aerial vehicles and real-time electro-optical birds like the forthcoming NRO L- series, momentarily sidelining film-return advocates. Program managers, under scrutiny from the Under Secretary of the Air Force for Space, invoked stop-work orders in mid-2005, reallocating personnel to parallel proof-of-concept tasks like ground-based film digitizers that could emulate orbital recovery.\n\nYet, this hiatus was far from idle stagnation; it fostered ingenuity across the Cobalt-M ecosystem. At the Western Test Range, recovery teams rehearsed mid-Pacific splashdowns with instrumented boilerplate capsules, honing helicopter snatch techniques against worsening El Niño swells. Software engineers at Northrop Grumman's Mission Systems sector developed autonomous image triage algorithms, prioritizing high-value targets during the satellite's 90-minute ground tracks. The pause even spurred inter-agency collaborations: CIA photo interpreters hosted workshops with Air Force imagery wings, standardizing metadata tags that would later enable seamless integration into the Distributed Common Ground System. Geopolitically, the void was fortuitously timed; with U.S. forces entrenched in Iraq and Afghanistan, the emphasis shifted to persistent ISR from UAVs and legacy KH-11 assets, buying time without compromising coverage. Internally, the delay crystallized a philosophical pivot—from one-off demonstrations to a sustainable film-return cadre capable of evading digital denial tactics like cyber intrusions on downlink links.\n\nBy late 2006, these labors bore fruit. Manufacturing lines hummed back to life with fortified processes: dual-redundant film vaults, drag-compensating orbit adjusters, and streamlined assembly jigs that slashed integration time by 40%. The hiatus, in essence, was the program's chrysalis stage—a strategic respiration that tempered ambition with pragmatism, ensuring Cobalt-M's resurgence in 2007 would launch not merely satellites, but a matured operational paradigm poised for the constellation era.\n\nAs the strategic pause in Cobalt-M launches stretched through 2005 and into 2006, the program's engineers at the primary integration facility turned their attention inward, transforming the hiatus from a mere setback into a fertile ground for refinement. Manufacturing delays, coupled with the meticulous dissection of telemetry from the inaugural 2004 mission, had grounded the fleet, but this downtime proved invaluable. Rather than idling, the technical teams zeroed in on the satellite's propulsion subsystem—the unsung workhorse responsible for maintaining precise orbital slots amid the relentless drag of the upper atmosphere and the subtle gravitational perturbations from Earth's uneven mass distribution. These were not sweeping overhauls but judicious, incremental upgrades, each calibrated to squeeze marginal gains in reliability, efficiency, and longevity without disrupting the proven architecture of the Cobalt-M platform.\n\nThe propulsion suite on the original Cobalt-M vehicles relied on a hybrid system: bipropellant chemical thrusters for major orbit-raising maneuvers post-deployment, augmented by low-thrust resistojet units for fine station-keeping. Early mission data revealed subtle inefficiencies—chief among them, uneven propellant expulsion during extended burns, which led to minor attitude deviations and accelerated fuel depletion. Engineers addressed this first by redesigning the catalyst beds within the bipropellant thrusters. The original beds, constructed from platinum-iridium mesh, suffered from gradual sintering under repeated thermal cycling, reducing combustion efficiency by up to a few percentage points over months of operation. The upgrade involved infusing the mesh with a proprietary ceramic stabilizer, a nanoscale coating that resisted agglomeration at temperatures exceeding 1,200 Kelvin. This tweak, tested rigorously in ground-based vacuum chambers simulating low-Earth orbit conditions, extended thruster lifespan by preserving ignition uniformity, ensuring that delta-V budgets remained predictable through multi-year missions.\n\nComplementing the chemical thrusters, the resistojet modules underwent their own subtle evolution. These electric propulsion elements heated stored hydrazine propellant via resistively wound nichrome coils to produce controlled bursts of momentum. Telemetry from the 2004 bird had flagged intermittent coil overheating during prolonged station-keeping sequences, attributed to thermal gradients in the insulating ceramic sheaths. The fix was elegantly simple: a reconfiguration of the coil windings from a single-layer spiral to a bifilar arrangement, which distributed current more evenly and dissipated heat 15-20% faster. This change necessitated only a minor recalibration of the power conditioning unit, drawing from the existing 28-volt bus without taxing the solar arrays. Ground tests, conducted in a thermal-vacuum chamber at the facility's altitude simulation lab, confirmed that the new windings maintained thrust vector stability within 0.1 degrees over simulated 90-day burns, a critical margin for the high-resolution imaging payloads that demanded unwavering geosynchronous-like pointing accuracy despite the satellites' sun-synchronous inclinations.\n\nFuel management emerged as another focal point, where software refinements bridged hardware tweaks. The original propulsion control avionics, running on radiation-hardened 32-bit processors, executed thrust profiles via a deterministic state machine that occasionally lagged in responding to real-time perturbations from solar activity-induced atmospheric expansion. During the hiatus, coders iterated on the flight software, embedding a lightweight adaptive algorithm that sampled accelerometer data every 30 seconds to preemptively adjust propellant flow rates. This wasn't a full-fledged AI overhaul but a rule-based enhancement, drawing on lessons from the 2004 mission's orbital decay logs. Integrated with the upgraded valves—precision-machined solenoid-actuated orifices now featuring piezoelectric actuators for sub-millisecond response—the system minimized sloshing in the titanium propellant tanks, a perennial issue in microgravity. Bladder-type tanks, already standard, benefited from this synergy, as the smoother flow reduced structural fatigue on the Kevlar overwraps.\n\nRedundancy philosophy also saw incremental bolstering. The baseline Cobalt-M carried dual-string propulsion controllers, but cross-strapping between chemical and resistojet lines was rudimentary, leaving a single point of failure in the shared pyro valve firing circuits. Engineers introduced a multiplexed isolation relay array, fabricated from gallium arsenide switches hardened against total ionizing dose levels beyond 300 krad. This allowed seamless failover not just between thrusters but across propellant manifolds, tested via hardware-in-the-loop simulations that replayed 2004's most taxing deorbit avoidance maneuvers. The addition weighed under 200 grams yet elevated the mean time between failures (MTBF) projection from 5 to 7 years, aligning with the program's goal of five-year nominal lifespans extensible to eight under favorable solar minima.\n\nThese upgrades were not executed in isolation; they unfolded amid a symphony of cross-disciplinary collaboration. Propulsion specialists worked shoulder-to-shoulder with thermal analysts, who modeled the revised heat paths using finite element tools refined from prior NASA heritage programs. Vibration engineers shake-tested the modified thruster clusters on electrodynamic shakers mimicking Ariane 5's ascent profile, confirming that natural frequencies shifted away from structural resonances by at least 10%. Electromagnetic compatibility checks, vital for the reconnaissance payloads' sensitive detectors, verified that the new coil geometries introduced negligible broadband noise into the S-band downlinks. Qualification culminated in a series of hot-fire tests at a remote desert range, where full-scale propulsion modules, mated to mock bus structures, expended representative propellant loads under simulated vacuum, with high-speed Schlieren imaging capturing plume uniformity.\n\nBy late 2006, as manufacturing bottlenecks eased—thanks to streamlined supply chains for iridium precursors and ceramic precursors—these technological increments stood ready for infusion into the production line. The changes demanded no new launch vehicle accommodations, preserving the tight integration with the Ariane 5 ECA's dual-payload adapter. Cost-wise, they represented a bargain: internal audits pegged the R&D outlay at under 5% of the annual program budget, yielding returns in mission assurance that would underpin the resumption of launches. This era of quiet innovation underscored a cardinal tenet of space operations: in the shadow of delays, persistence forges resilience. The Cobalt-M fleet, reborn with these understated enhancements, emerged sharper, poised to reclaim its vantage in the constellation.\n\nAs the operational hiatus drew to a close in early 2007, the Cobalt-M program stood poised for revival, buoyed by the meticulous engineering tweaks to its propulsion systems that had been executed during the downtime. These subtle yet critical enhancements—refinements to thruster efficiency and fuel mixture ratios—ensured greater reliability for the satellite's orbital maneuvering, addressing subtle wear patterns observed in earlier missions. With ground control teams at the primary mission operations center fully recalibrated and simulation runs validating the upgrades under accelerated timelines, the stage was set for a bold reentry into active service. The program's architects, drawing lessons from the 2004-2006 interlude, envisioned not just a return to form but an acceleration of ambitions, transforming sporadic deployments into a rhythmic cadence of launches that would redefine the reconnaissance satellite's role in national security architecture.\n\nPreparation for the 2007 launch campaign unfolded with a precision that reflected the maturation of the Cobalt-M enterprise. Integration facilities buzzed with activity as newly fabricated bus structures, instrument payloads, and solar array assemblies converged on the cleanroom floors. Engineers conducted exhaustive vibration and thermal vacuum testing, simulating the punishing ascent through the atmosphere and the unforgiving void beyond. Ancillary systems, from star trackers to cryogenic coolers for infrared sensors, underwent rigorous qualification, while software uploads incorporated adaptive algorithms honed from archival data of prior orbits. The campaign's cornerstone was a deliberate shift toward modularity: standardized interfaces allowed for rapid vehicle mating with expendable launchers, slashing turnaround times between missions. This operational streamlining was no accident; it stemmed from interagency reviews that emphasized surge capacity in response to evolving geopolitical tensions, where persistent surveillance overhead demanded not just quality but quantity.\n\nThe 2007 launch campaign itself marked a pivotal escalation in tempo, launching what would become the program's most prolific year to date. Kicking off in the spring from coastal pads optimized for polar inclinations, the sequence unfolded with a deliberate rhythm—initially bi-monthly, then compressing to near-monthly intervals by autumn. Each Cobalt-M variant hurtled skyward atop proven boosters, unfurling high-resolution electro-optical and synthetic aperture radar suites into sun-synchronous orbits at altitudes hovering around 500 kilometers. These platforms, with their agile pointing mechanisms and real-time data downlinks, were tailored for dynamic tasking: tracking mobile assets, monitoring littoral zones, and cueing other intelligence collectors. The increased cadence stemmed from a confluence of factors—streamlined manufacturing pipelines at contractor facilities, predictive maintenance protocols that minimized ground anomalies, and a burgeoning cadre of operators fluent in the satellite's command lexicon. Mission control rooms, alive with the glow of multi-spectral displays and the murmur of telemetry streams, orchestrated this ballet with newfound assurance.\n\nThis resurgence was more than logistical; it embodied the Cobalt-M program's evolutionary leap. Where earlier years had prioritized proof-of-concept and incremental refinements, 2007's campaign institutionalized high-ops tempo as a core competency. Payloads incorporated nascent onboard processing for edge computing, reducing latency in threat assessment, while inter-satellite links prototyped in select units hinted at future constellations. Challenges persisted—ranging from upper-stage dispersions demanding mid-course corrections to solar flare-induced glitches taxing radiation-hardened electronics—but the team's resilience shone through. Contingency drills, executed in parallel with live operations, fortified the human element, ensuring that even as launch windows narrowed, error margins did too. By year's end, the campaign had not only replenished the orbital cadre but expanded it, providing unbroken coverage that underpinned strategic decision-making across theaters.\n\nIn retrospect, the 2007 resumption encapsulated the alchemy of persistence and innovation that propelled Cobalt-M forward. The propulsion upgrades, once a quiet fix during dormancy, now underpinned the sustained burns required for constellation maintenance amid denser traffic. Operators marveled at the system's adaptability, as automated station-keeping routines freed crews for higher-level analysis. This era's heightened rhythm set precedents for subsequent years, fostering a culture of continuous deployment that blurred the lines between development and sustainment. As the final plumes of 2007's launches dissipated into the ionosphere, the program gazed toward horizons of even greater integration—autonomous swarms, hyperspectral imaging, and resilient architectures against emerging counter-space threats—heralding a reconnaissance epoch defined by unrelenting presence.\n\nAs the Cobalt-M reconnaissance satellite program accelerated into 2007, with launch preparations underscoring a markedly heightened operational cadence, the focus shifted decisively to the orbital architecture that would define this pivotal cohort. Building on lessons from earlier missions, which had largely adhered to more conventional low Earth orbit profiles optimized for broad mid-latitude surveillance, the 2007 satellites were engineered for a configuration that prioritized untapped geographic domains. This strategic pivot in orbital parameters—inclination and altitude chief among them—enabled coverage of high-latitude and polar-adjacent targets, regions that had evaded comprehensive scrutiny in prior flights due to ground track limitations and revisit constraints.\n\nThe cornerstone of this new setup was the selection of a higher orbital inclination, a deliberate departure from the near-equatorial or modestly inclined paths of the 2004-2006 satellites. Previous configurations, often favoring inclinations that traced predictable equatorial belts for persistent monitoring of tropical and subtropical chokepoints, confined ground tracks to lower latitudes, leaving vast swaths of the Arctic, Antarctic peripheries, and northern high-latitude theaters—such as key Eurasian landmasses and transpolar shipping lanes—underserved. By elevating the inclination toward polar realms, the 2007 cohort achieved nodal precession aligned with Earth's rotational dynamics, allowing satellites to sweep across a fuller spectrum of latitudes over successive orbits. This not only diversified the observable footprint but also mitigated seasonal lighting biases, as the steeper angle facilitated access to dawn-dusk terminators ideal for high-contrast electro-optical reconnaissance during extended polar nights or days.\n\nComplementing this was the refined altitude profile, pitched lower than many predecessors to sharpen ground resolution while balancing atmospheric drag and thermal management challenges. Earlier Cobalt-M vehicles had operated in regimes where higher altitudes traded acuity for wider swath widths and extended dwell times over stationary assets, suitable for tracking naval movements in open oceans or monitoring sprawling industrial complexes. The 2007 adjustment, however, embraced a tighter orbital shell, enhancing the synthetic aperture radar (SAR) and multispectral imaging payloads' ability to discern fine details—think sub-meter feature extraction on ice floes, remote outposts, or camouflaged infrastructure nestled in rugged terrains. This lower perch demanded meticulous propulsion budgeting to counter aerobraking effects, yet it yielded revisit cadences that transformed sporadic glimpses into near-continuous vigilance over dynamic polar fronts, where environmental shifts like sea ice fracturing could signal strategic mobilizations.\n\nOrbital eccentricity remained near-circular, as was program doctrine, to stabilize pointing accuracy and minimize torque from uneven gravitational gradients—a necessity for the precision gimbal mechanisms supporting the cohort's advanced staring arrays. The argument of perigee was nulled to equator-crossing, ensuring uniform altitude exposure and averting perigee-pass perturbations that plagued asymmetrical profiles. Right ascension of the ascending node (RAAN) was phased across multiple launch windows, seeding a nascent Walker constellation pattern that interwove orbital planes for gapless latitudinal overlap. True anomaly at deployment was synchronized to ingress over priority sectors, allowing immediate tasking upon separation from the booster.\n\nThis configuration's genius lay in its geospatial complementarity. Whereas prior missions excelled at equatorial straits and temperate-zone megacities—vital for proliferation tracking and logistics interdiction—the 2007 orbits unlocked \"new frontiers.\" High-inclination paths scribed lemniscate-like ground tracks that lingered over circumpolar routes, capturing elusive submarine bastions beneath Arctic ice caps or ephemeral airfields in Siberian taiga. Lower altitudes amplified this by compressing the nadir footprint, ideal for prosecuting time-sensitive intelligence requirements amid fleeting weather windows. Program engineers drew from heritage designs like those in the Lacrosse and Improved Crystal lineages, but iterated with Cobalt-M's modular bus to accommodate cryogenic coolers for infrared hyperspectral sensing, tuned expressly for thermal anomalies in permafrost zones.\n\nOperationally, achieving this regime marked a maturation milestone. Launch vehicles, sequenced for rapid follow-on deployments from coastal pads, injected payloads into precise insertion corridors, with upper stages performing RAAN tweaks via hydrazine thrusters to weave the constellation fabric. Post-maneuver, each satellite executed a multi-burn spiral-up to operational altitude, conserving delta-V for station-keeping over multi-year lifespans. Ground segment adaptations were equally critical: new ephemeris models accounted for J2 oblateness perturbations, which at higher inclinations induced faster apsidal precession, demanding agile retargeting algorithms. The result was a resilient mesh network, where inter-satellite links—emerging tech for the era—relayed bursts to gateway stations, obviating line-of-sight dependencies over remote poles.\n\nThe strategic dividends unfolded swiftly. Early passes over high northern latitudes revealed patterns invisible to lower-inclination predecessors: seasonal base expansions, under-ice transits, and resource extraction surges that reshaped geopolitical calculus. This cohort's parameters also fortified resilience against counterspace threats; dispersed planes diluted vulnerability to antisatellite intercepts, while lower altitudes hastened orbital decay for graceful denials if compromised. In the broader arc of Cobalt-M evolution, 2007's orbital gambit presaged hybrid regimes—blending LEO with occasional highly elliptical excursions—heralding the program's 2010s pivot toward multi-domain persistence.\n\nYet, this sophistication was not without trade-offs, emblematic of the era's engineering brinkmanship. Higher inclinations amplified radiation dosage from South Atlantic Anomaly traversals, spurring reinforced gallium arsenide solar arrays and tantalum shielding. Lower altitudes intensified atomic oxygen erosion on optical coatings, prompting plasma contactor innovations to bleed off accumulating charge. Cadence pressures tested integration timelines, with vibration profiles calibrated anew for the slimmer fairing envelopes. Nonetheless, telemetry from inaugural 2007 insertions validated the parameters' fidelity: ground tracks adhered to within arcseconds, altitudes held stable absent excessive drag epochs.\n\nIn retrospect, the 2007 cohort's orbital configuration encapsulated the Cobalt-M ethos—adaptive, precise, forward-leaning. By reconceptualizing inclination and altitude not as static specs but as levers for target diversification, the program transcended its reconnaissance roots, edging toward the omnipresent overwatch that defined subsequent decades. This cohort, through its orbital artistry, not only covered new terrestrial canvases but redrew the intelligence map itself.\n\nBuilding on the strategic orbital inclination and altitude parameters established for the early 2007 Cobalt-M missions—which optimized coverage over novel terrestrial targets distinct from prior flights—the operational timeline for these assets became a focal point of mission planners' scrutiny. The first satellite in this series, designated Kosmos 2420, exemplified the program's adherence to standardized durations, balancing reconnaissance imperatives with spacecraft longevity constraints inherent to reconnaissance satellite architecture. This period marked a maturation in the Cobalt-M lineage, where mission durations were fine-tuned not merely for data collection but for seamless integration into broader launch cadences and recovery logistics, ensuring sustained intelligence throughput amid evolving geopolitical demands.\n\nInitial projections for Kosmos 2420 pegged the core orbital operations at 70 days, a benchmark derived from fuel reserves, solar panel degradation models, and battery cycling limits calibrated during ground simulations. ***This estimate pivoted, however, as the total mission length—from launch through deorbit and landing—precisely spanned 10 weeks and 6 days, encapsulating the full envelope of active imaging passes, downlink sessions, and terminal maneuvers.*** Ground recovery preparation windows, calibrated for 82 days to account for potential orbital perturbations or extended loiter phases, provided an additional buffer, blending seamlessly with the primary timeline to facilitate precise reentry corridor predictions and asset retrieval on Soviet-era ranges adapted for modern payloads.\n\nThis 10-week-and-6-day lifespan underscored the Cobalt-M's operational philosophy, prioritizing high-fidelity electro-optical and synthetic aperture radar data acquisition within a compressed yet reliable window. Launching into its tailored low Earth orbit, Kosmos 2420 executed daily imaging swaths over priority regions, with attitude control thrusters conserving propellant for station-keeping that extended the effective payload operational phase beyond initial forecasts. Mission controllers at the parent ground stations monitored real-time telemetry, adjusting for micrometeoroid risks and atmospheric drag variations that could subtly erode the projected endurance, yet the asset adhered closely to the revised total, demonstrating the robustness of its propulsion subsystem—rooted in hypergolic bipropellant designs proven across the program's antecedent flights.\n\nThe precision of this duration also reflected iterative lessons from 2004-2006 missions, where analogous reconnaissance platforms had occasionally truncated lifespans due to thermal anomalies or command link dropouts. For Kosmos 2420, redundant avionics suites and autonomous fault-tolerant software mitigated such vulnerabilities, allowing the satellite to sustain peak performance through the majority of its orbital tenure. Deorbit initiation, triggered via onboard sequencing tied to the elapsed mission clock, funneled the platform into a controlled reentry trajectory, with the landing phase benefiting from the extended 82-day recovery prep that had prepositioned teams and instrumentation. This holistic timeline management not only maximized return on investment for the Cobalt-M fleet but also informed subsequent 2007 launches, cementing early-year operations as a benchmark for endurance in contested reconnaissance environments.\n\nIn broader programmatic context, the mission's temporal architecture facilitated interleaved operations with follow-on assets, minimizing gaps in coverage continuity over dynamic target sets. Analysts later dissected post-mission data dumps, revealing that the extra six days beyond the 70-day core projection yielded ancillary high-value intelligence from opportunistic revisits, while the 82-day recovery horizon ensured negligible risk of uncontrolled decay. Such calibrated durations epitomized the Soviet space reconnaissance ethos—efficient, resilient, and inexorably tied to national security imperatives—propelling the Cobalt-M evolution into its mid-decade zenith.\n\nSummer 2007 Launch Activity\n\nAs the inaugural Cobalt-M reconnaissance satellite in the series completed its prescribed operational lifespan, adhering closely to the program's established timelines, attention within the Russian space enterprise shifted seamlessly to sustaining the constellation's coverage. The mid-year launch campaign for the subsequent vehicle, designated Kosmos 2427, exemplified the meticulous cadence of military space operations at the Plesetsk Cosmodrome. ***Payload integration, encompassing the Cobalt-M bus mated to its sophisticated electro-optical and signals intelligence payloads, was completed on 17 May 2007.*** This critical milestone marked the culmination of months of subsystem assembly and environmental qualification tests conducted under the watchful eyes of specialists from the Kometa Design Bureau and TsSKB-Progress engineers. From there, the integrated stack entered a intensive phase of ***14 days of rigorous systems testing and checkout***, a grueling regimen that included thermal-vacuum simulations, vibration profiling to replicate ascent loads, electromagnetic compatibility sweeps, and end-to-end command-validation runs with the ground control segment. These checks, performed in the secure confines of the payload processing facility, verified the satellite's autonomy in orbit, its high-resolution imaging chains, and the resilient encryption layers safeguarding downlinked intelligence data.\n\nWith all parameters green across the board by the close of that testing window, the vehicle was methodically transported to the launch pad aboard a specialized rail transporter, shrouded in protective fairing mockups to shield sensitive avionics from the elements. ***A standard 7-day final countdown then began***, initiating the hyper-conservative rituals that define high-stakes reconnaissance deployments: propellant farm-ups for the Kosmos-3M booster, pyrotechnic arming sequences, range safety polling with northern range assets, and iterative flight termination system drills. Technicians in anti-static garb swarmed the stack under floodlights, torquing final connections and uploading ephemeris data tailored to the mission's geosynchronous-threat monitoring profile. The Cobalt-M series' evolutionary refinements—such as enhanced solar array deployment reliability and upgraded attitude control thrusters—were put through their paces one last time, ensuring the bird was primed for its multi-year vigil over contested maritime domains and adversarial ground maneuvers.\n\nLiftoff unfolded under classically favorable early summer conditions at Plesetsk, where the solstice-shortened nights had not yet yielded to the midnight sun's full glare. A crisp dawn broke with clear skies dominating the horizon, visibility exceeding 10 kilometers in all quadrants, and surface winds steady at a gentle 5-7 meters per second from the northwest—ideal for the booster's stability margins. Humidity clung low in the boreal forest air, minimizing any risk of ice buildup on the cryogenic upper stage, while temperatures hovered in the comfortable teens Celsius, allowing crews to work without the encumbrance of extreme cold-weather protocols. At the appointed moment at the end of the countdown period, the Kosmos-3M's first stage thundered to life with a staccato roar, its solid-fuel grains igniting in precise sequence to hurl the 1,200-kilogram-plus stack skyward on a needle-thin pillar of exhaust plume.\n\nThe ascent trajectory adhered to the program's proven polar orbital insertion profile, optimized for rapid access to sun-synchronous inclinations that maximized the Cobalt-M's imaging revisit rates over high-latitude targets of strategic interest. Initial boost saw the vehicle clawing steeply out of the pad at 82 degrees azimuth, yaw-programmed to counter the cosmodrome's northerly latitude and align with the target 67-degree inclination. The first stage burned hot and clean for 120 seconds, arcing the trajectory over the Barents Sea as telemetry streamed nominal acceleration curves back to the firing control center. Stage separation occurred flawlessly at 45 kilometers altitude, exposing the liquid-fueled second stage to the thin upper air. This phase, the heart of the ascent, executed a near-textbook dogleg maneuver—subtle pitch-over commands steering the stack eastward to shed unwanted downrange velocity while preserving vertical energy. Gimbaled engine tilts, guided by inertial measurement units cross-fed with GPS augmentation, traced a parabolic loft peaking at 180 kilometers apogee before the velocity-injection burn circularized the preliminary orbit at 250 by 260 kilometers.\n\nThroughout the climb, the vehicle's health-and-status beacon pulsed green: battery voltages steady, star trackers acquiring references mid-burn, and the payload's cryocoolers chilling to operational setpoints in anticipation of first-light imaging passes. Fairing jettison, timed to the edge of the sensible atmosphere, revealed the Cobalt-M's sleek form—its body-stabilized chassis glinting briefly in the dawn light before vanishing into the mesosphere. Final orbital insertion came via a precise velocity patch from the upper stage, injecting Kosmos 2427 into its operational shell with eccentricity below 0.001 and argument of perigee locked for optimal ground-track repetition. Ground controllers at the Titov Main Test Center exhaled collectively as acquisition-of-signal confirmed separation, separation pyros firing cleanly to distance the spent stage. Within hours, the satellite unfurled its articulated solar wings and commenced autonomous outgassing, poised to extend the Cobalt-M lineage's unbroken chain of overhead reconnaissance into the latter half of the decade. This launch not only reaffirmed the reliability of the Plesetsk production line but also underscored the program's adaptive evolution, incorporating hardening against emerging anti-satellite threats discerned from prior missions' intelligence hauls.\n\nFollowing the successful ascent and orbital insertion of the Cobalt-M series' latest reconnaissance satellite in June, mission controllers at the primary ground station shifted seamlessly into the critical phase of mid-mission assessments. With the spacecraft now coasting through its initial orbits at an altitude optimized for persistent surveillance over key geopolitical regions, the focus turned to comprehensive telemetry analysis—a cornerstone of space operations that demanded unwavering precision. Telemetry streams, downlink-ed in real-time bursts via the satellite's S-band transmitter, flooded the operations center with a torrent of housekeeping data, painting a vivid picture of the vehicle's vital signs. Engineers pored over these streams using custom-developed software suites, parsing packets that encapsulated everything from subsystem voltages and currents to attitude control torques and propulsion valve statuses, all while cross-referencing against pre-launch models and the performance envelopes established from prior Cobalt-M missions.\n\nPower generation emerged as the paramount concern in these early mid-mission evaluations, given the satellite's reliance on gallium arsenide solar arrays for sustained operations in the harsh radiation environment of low Earth orbit. Deployment of the primary solar wings had been confirmed via pyrotechnic firing signals during separation, but it was the ongoing telemetry that truly validated their integrity. Voltage outputs from the arrays stabilized rapidly post-eclipse, hovering within nominal bands that ensured ample charging for the nickel-hydrogen battery banks. Controllers monitored solar aspect angles meticulously, adjusting via onboard momentum wheels to maximize insolation as the satellite processed through its dawn-dusk orbital plane. Any fleeting dips in power budget—often attributable to minor debris shadowing or initial outgassing effects—were swiftly analyzed through power budget spreadsheets, revealing margins that comfortably exceeded mission minimums. This rigorous scrutiny not only affirmed the arrays' photovoltaic efficiency but also underscored the evolutionary refinements in Cobalt-M design, where redundant string configurations mitigated single-point failures observed in earlier prototypes.\n\nThermal control systems, equally vital for preserving the delicate electronics suites that underpinned the reconnaissance payload, underwent equally exhaustive telemetry dissection. The satellite's multi-layered insulation blankets and variable-emittance coatings were engineered to buffer against the extreme thermal cycling of orbital day-night transitions, and mid-mission data bore eloquent testimony to their efficacy. Heater line currents and radiator temperatures streamed in, plotted in dynamic dashboards that tracked heat rejection profiles against predictive thermal math models. Peak solar absorptance during sunlit passes pushed component temps toward upper limits, yet active cryocoolers for the infrared sensors maintained cryogenic thresholds without excessive power draw. Anomalies, when they surfaced—such as a transient overtemperature on a star tracker housing—prompted immediate root-cause telemetries, often traced to adhesive offgassing rather than design flaws, and were resolved through temporary attitude maneuvers. These assessments, conducted in twelve-hour shifts by interdisciplinary teams of thermal analysts and systems engineers, ensured that the entire bus remained within a thermal equilibrium that safeguarded long-term sensor calibration and data fidelity.\n\nBeyond power and thermal realms, telemetry analysis extended to a holistic health-and-status panorama, integrating propulsion, communications, and payload vitals into a unified diagnostic narrative. Reaction control system pressures held steady, with helium pressurant levels confirming no leaks in the hydrazine manifolds essential for station-keeping burns. RF link margins on both uplink and downlink channels exceeded expectations, even as the satellite's high-gain antenna phased-locked onto ground station passes amid ionospheric scintillation. Payload-specific telemetries—encompassing electro-optical imager focus mechanisms and synthetic aperture radar pulse repetition frequencies—revealed nominal trending, with data volumes ramping up as initial calibration sequences completed. This phase of the mission exemplified the maturation of Cobalt-M operations protocols, where automated anomaly detection algorithms, honed from lessons across the 2004-2015 program arc, flagged deviations in milliseconds, allowing human operators to intervene with scripted command loads before issues escalated.\n\nMid-mission assessments thus served as the operational heartbeat, bridging the euphoria of launch to the endurance of full reconnaissance deployment. Daily briefings distilled terabytes of telemetry into executive summaries, shared across stakeholder agencies, affirming that power generation and thermal control not only remained within nominal limits but exceeded heritage performance in several metrics. Contingency planning remained ever-present—backup solar strings on hot standby, redundant thermal loops primed—yet the data painted an unequivocally robust picture. As orbits accumulated, these checks evolved from reactive health polls to predictive analytics, leveraging machine learning precursors to forecast end-of-life power fade and thermal drift years into the mission. In the grand chronicle of the Cobalt-M program, this telemetry-centric vigilance exemplified the unsung rigor that transformed ambitious launches into enduring strategic assets, ensuring the satellite's gaze remained sharp and unyielding over its surveilled horizons.\n\nFollowing the successful mid-mission health checks that confirmed robust power generation from the Cobalt-M's gallium arsenide solar arrays and stable thermal control across fluctuating orbital environments, the program's attention shifted to the broader metric of operational persistence. For the Summer 2007 mission, designated as Kosmos 2427 and launched atop a Soyuz-2.1v rocket from Plesetsk Cosmodrome on 7 June 2007, the satellite demonstrated exemplary endurance in its low Earth orbit at approximately 650 kilometers altitude. Ground controllers at the Titov Main Test Space Center monitored attitude control thruster firings and momentum wheel desaturations meticulously, ensuring the spacecraft maintained its precise imaging passes over priority reconnaissance targets in the Northern Hemisphere.\n\n***The mission length for Kosmos 2427 measured precisely 76 days,*** culminating in a controlled deorbit burn on 23 August 2007 to comply with international space debris mitigation guidelines. This duration encapsulated a phase of intensified operational tempo, where the satellite's electro-optical sensors captured high-resolution imagery under extended summer daylight conditions, providing critical intelligence on dynamic ground activities. Persistence in this context was not merely a passive attribute but an active engineering triumph, as the spacecraft's hydrazine propulsion system rationed fuel for over 200 station-keeping maneuvers, countering atmospheric drag that intensified during solar maximum influences.\n\nThe 76-day span allowed for iterative software uploads from the Moscow mission control hub, refining onboard image processing algorithms to enhance contrast in hazy atmospheric conditions prevalent that season. Engineers noted minimal degradation in the star tracker performance, which relied on redundant fiber-optic gyroscopes to sustain three-axis stabilization within 0.01-degree accuracy—vital for the Cobalt-M's keyhole-like reconnaissance capabilities. This persistence benchmarked against earlier program flights underscored the maturity of the Yantar-derived bus architecture, where vibration-isolated payload bays protected hyperspectral imagers from launch residuals long into the mission.\n\nBeyond raw endurance, the Summer 2007 operations highlighted adaptive strategies for anomaly mitigation, such as transient power glitches from micrometeoroid impacts, resolved through autonomous battery conditioning cycles. The mission's conclusion marked a pivotal data downlink surge, archiving terabytes of multispectral data that informed subsequent Cobalt-M evolutions, including enhanced radiation hardening for polar orbits. In the chronicle of reconnaissance satellite programs, Kosmos 2427's steadfast performance over its full operational lifecycle exemplified how meticulous systems engineering translated nominal health metrics into strategic mission longevity, setting a precedent for the program's trajectory through the late 2000s.\n\nAs the Cobalt-M reconnaissance satellite, designated Kosmos 2427, approached the culmination of its summer mission, the ground control teams at the Russian Mission Control Center near Moscow initiated the meticulously choreographed sequence of maneuvers to bring the spacecraft home. Having surpassed its nominal design life through a series of precise orbital adjustments and efficient resource management—as detailed in prior operational logs—the focus shifted seamlessly to recovery preparations. Telemetry data confirmed optimal conditions for deorbit, with the propulsion system primed for the critical retrograde burn that would lower the perigee into the denser layers of the atmosphere. This phase marked the transition from active reconnaissance duties, where the high-resolution imaging systems had captured vast troves of intelligence data across multiple spectral bands, to the safe return of the descent module brimming with film canisters, electronic recordings, and sensor payloads essential for post-mission analysis.\n\nThe deorbit sequence unfolded with clockwork precision in the final orbital passes. At a predetermined altitude, the main service module fired its engines to execute the burn, imparting just the right delta-V to initiate atmospheric interface. As Kosmos 2427 dipped into the upper atmosphere, the intense frictional heating generated plasma sheaths around the vehicle, briefly blacking out communications—a routine yet tense interlude for controllers monitoring from afar. Heat shield integrity held firm, a testament to the evolved thermal protection systems refined in the Cobalt-M lineage since the program's inception in 2004. Moments later, pyrotechnic charges separated the descent module from the expended service module and orbital compartment, allowing the reentry vehicle to orient itself for a controlled ballistic trajectory. Parachute deployment followed at approximately 7 kilometers altitude, first the drogue to stabilize spin, then the main canopy unfurling in a billowing cascade against the vast Central Asian skies.\n\n***After orbiting for the planned duration, Kosmos 2427 made a perfect landing on the 235th day of 2007, safely concluding its mission.*** The touchdown occurred in the designated recovery ellipse within the steppe regions of Kazakhstan, a primary landing zone honed over decades of Soviet and Russian recoverable satellite operations. Dust clouds rose softly as the module settled onto the arid terrain, its crushable landing legs absorbing the final impact with minimal deceleration forces. Recovery helicopters from the 15th Directorate of the Russian Space Forces, already airborne and vectored by real-time GPS beacons from the module, converged swiftly on the site. Ground teams, clad in protective gear against potential residual propellants, established a secure perimeter within minutes, their Mi-8 rotors whipping up the dry earth as they airlifted the capsule to a forward staging area.\n\nPost-landing protocols unfolded with practiced efficiency. The descent module, weighing roughly 1,200 kilograms upon recovery, underwent preliminary decontamination and biohazard checks before technicians extracted the payload bay. Film cassettes from the electro-optical and panoramic cameras—key assets of the Cobalt-M's upgraded sensor suite—were rushed to darkrooms for development, yielding imagery that would inform strategic assessments for months to come. Digital recorders captured orbital dynamics, attitude control performance, and environmental data, providing invaluable feedback for iterating future missions in the program. No significant anomalies were noted; scorch patterns on the ablative shield were nominal, and structural integrity exceeded expectations, underscoring the robustness of the Yantar-derived design heritage.\n\nThis successful recovery not only validated the operational maturity of the Cobalt-M series but also closed the loop on a mission that exemplified the program's evolution toward extended endurance and enhanced resolution. Kosmos 2427's return replenished the intelligence pipeline, enabling rapid turnaround for the next launch window while engineers dissected performance metrics to refine deorbit predictability and parachute reliability. In the broader chronicle of Russian space reconnaissance from 2004 to 2015, such operations highlighted the enduring value of physical returnables in an era increasingly dominated by digital downlink, ensuring that the tangible artifacts of orbital surveillance continued to shape national security paradigms. With the spacecraft safely archived and its data disseminated, the summer campaign yielded to planning for subsequent flights, perpetuating the relentless cycle of launch, orbit, and recovery that defined the Cobalt-M legacy.\n\nThe recovery of the Cobalt-M descent module in August 2007 marked not merely the end of an operational cycle but the gateway to a thorough evaluation of the mission's intelligence yield, a process that unfolded in secure analytical facilities over the ensuing months. Ground teams, working under stringent protocols to preserve the delicate film cassettes and associated telemetry data, extracted a treasure trove of reconnaissance imagery that captured dynamic theaters of interest across multiple global hotspots. This evaluation phase, codenamed \"Echo Review,\" systematically assessed the payload's performance against predefined benchmarks, revealing a program maturing into a cornerstone of strategic surveillance.\n\nAt the heart of the 2007 findings lay a marked enhancement in imaging fidelity, with the Cobalt-M's upgraded optics delivering unprecedented clarity in both panchromatic and multispectral bands. Analysts noted that surface features previously blurred into indistinct shapes—such as vehicle convoys navigating rugged terrain or infrastructure under construction—now resolved into discernible details, allowing for confident identification of equipment types, personnel movements, and even tactical deployments. This leap in target resolution stemmed from refinements in the spacecraft's stabilization systems and lens coatings, which mitigated atmospheric distortion and vibration artifacts far more effectively than in prior iterations. The result was a dataset that transformed vague suspicions into actionable insights, particularly in monitoring adversarial logistics networks and fortified positions.\n\nEqually transformative was the improvement in geolocational accuracy, a perennial challenge for film-return reconnaissance systems reliant on orbital ephemeris and star-tracker data. The 2007 missions achieved positional precision within tens of meters, a twofold gain over 2006 flights, enabling precise correlation with collateral intelligence sources like signals intercepts and human reports. This accuracy proved invaluable in scenarios demanding exact mapping, such as delineating underground facility entrances or tracking maritime vessel transits through chokepoints. Evaluators highlighted specific overflights of contested border regions and naval basing areas, where the geotagged imagery facilitated real-time battle damage assessments and predictive modeling of enemy maneuvers.\n\nThe intelligence impact of these missions rippled through operational commands, furnishing decision-makers with high-confidence products that influenced force posture adjustments and preemptive countermeasures. For instance, detailed serial imaging of assembly lines and troop mobilizations provided early warnings of escalation potentials, averting potential crises through diplomatic leveraging backed by irrefutable visual evidence. In counterproliferation efforts, the enhanced resolution unveiled previously obscured signatures of weapons development, such as heat plumes from test firings and stockpiling patterns at remote sites. These deliverables not only validated the Cobalt-M's role in the broader reconnaissance architecture but also underscored its edge over real-time digital alternatives, as the physical film's superior dynamic range captured nuances like camouflage netting textures and shadow-occluded revetments that electronic sensors often missed.\n\nYet, the evaluation was not without caveats, tempering the triumphs with pragmatic observations. While resolution and accuracy had advanced, the inherent latency of the film-return paradigm—spanning weeks from imaging to dissemination—remained a liability in fast-evolving conflicts, prompting internal debates on hybridizing with emerging digital downlinks. Environmental factors, including persistent cloud cover over key latitudes, still constrained coverage yields to approximately two-thirds of planned passes, though adaptive orbit planning mitigated this through prioritized retargeting. Processing bottlenecks in film development also surfaced, where emulsion sensitivities occasionally introduced minor artifacts, though post-recovery digital enhancements largely compensated.\n\nComparatively, the 2007 cohort outperformed predecessors across all metrics, embodying the iterative evolution of the Cobalt-M lineage since its 2004 inception. Earlier flights had labored under coarser optics and drift-prone navigation, yielding intelligence that, while useful, demanded extensive corroboration. By contrast, this year's hauls boasted a verification rate exceeding expectations, with cross-checks against allied assets confirming over 90 percent fidelity in critical reads—a testament to onboard autonomy upgrades like refined attitude control algorithms. This progression not only justified sustained funding amid shifting geopolitical priorities but also positioned the program as a resilient bulwark against the proliferation of low-Earth orbit constellations by potential adversaries.\n\nIn summation, the 2007 findings crystallized the Cobalt-M's ascent to operational excellence, delivering intelligence of singular depth and reliability that reshaped threat perceptions and strategic calculus. As analysts pored over the final deconvolved mosaics and annotated overlays, the verdict was unequivocal: these missions had not only met but exceeded their mandate, paving the way for ambitious enhancements in the years ahead and affirming the enduring value of sovereign, recoverable reconnaissance in an era of contested skies.\n\nAs the Cobalt-M program entered 2008, the momentum from the previous year's intelligence gains—marked by enhanced target resolution down to sub-meter precision and geolocational accuracies that minimized ground truth dependencies—encountered an abrupt halt. Much like the barren launch slate of 2005, when the constellation was still maturing and resources were funneled into on-orbit shakedowns, 2008 emerged as another operational void, devoid of any new Cobalt-M deployments. This absence was not born of technical failure or mission aborts but rather a deliberate strategic interlude, reflecting the intricate calculus of satellite reconnaissance in an era of constrained national assets and evolving threat landscapes.\n\nThe program's orbital inventory at the dawn of 2008 provided a robust buffer against immediate replenishment needs. Launches from 2006 and 2007 had swelled the constellation to its highest operational density yet, with multiple spacecraft distributed across sun-synchronous orbits at altitudes optimized for both electro-optical and synthetic aperture radar imaging. These birds, hardened against radiation belts and equipped with redundant propulsion for station-keeping, boasted projected lifetimes extending well into the next decade under nominal conditions. Routine telemetry indicated degradation rates far below initial projections, thanks to advances in gallium arsenide solar arrays and cesium-ion thrusters that conserved fuel margins. Program managers, drawing lessons from the 2005 hiatus, had modeled constellation sustainment scenarios using Monte Carlo simulations of failure probabilities, concluding that coverage gaps—critical for persistent surveillance over high-interest theaters like the Middle East and East Asia—remained negligible even without infusions. This inventory surplus allowed the National Reconnaissance Office (NRO) to prioritize maintenance over expansion, channeling engineering hours into software uploads that refined onboard processing algorithms for real-time change detection.\n\nYet inventory management alone does not fully explain the void; underlying it lurked persistent uncertainties in launch vehicle availability, a perennial bottleneck in the architecture of classified space operations. The Cobalt-M fleet relied heavily on evolved expendable launch vehicles (EELVs) such as the Atlas V and Delta IV, whose manifests were shared across a spectrum of payloads from signals intelligence to technology demonstrators. By 2008, the EELV program grappled with supply chain ripples from the 2007-2008 financial crisis, which squeezed subcontractor budgets for composite materials and avionics. More acutely, a series of ground-test anomalies on Delta IV upper stages—stemming from hydrogen permeation issues in the common booster core—had cascaded into certification delays, pushing several NRO slots into 2009. Atlas V production, meanwhile, faced its own hurdles: a propellant loading mishap during a routine proof test at Cape Canaveral had sidelined a block of vehicles, forcing rescheduling that favored higher-priority missions like the next-generation imagery architecture precursors. Whispers within the space industrial base suggested geopolitical frictions, too—export controls on Russian RD-180 engines for Atlas V created a shadow of vulnerability, prompting quiet diversification efforts that absorbed fiscal year allocations without yielding flights.\n\nThis confluence of factors manifested in the Joint Space Operations Center's daily tasking orders, where Cobalt-M taskings held steady but drew exclusively from legacy assets. Operators adapted ingeniously, employing multi-satellite stereoscopy to compensate for any individual sensor drift and leveraging inter-orbit handoffs for uninterrupted stares. The void, however, was not without tension: intelligence consumers, from theater commanders to policy principals, grew restive as peer competitors—rumored to be accelerating their own electro-optical constellations—threatened to erode U.S. overmatch. Internal program reviews, declassified in fragments years later, reveal heated debates at Payload Review Board meetings, where advocates for a mid-year \"hot bird\" insertion clashed with fiscal hawks citing the billions already sunk into orbital redundancy. Ultimately, restraint prevailed, underscoring a maturing philosophy: reconnaissance supremacy derived not from sheer volume but from the disciplined husbandry of a high-fidelity network.\n\nIn the broader chronicle of Cobalt-M's evolution, 2008's operational void served as a crucible for resilience. It honed ground segment workflows, accelerating the integration of automated orbit determination via GPS occultation data and paving the way for the distributed aperture concepts that would define later increments. Budgetary windfalls from deferred launches seeded risk reduction for the 2009 campaign, including subscale demos of cryocoolers for infrared hyperspectral imaging. Echoing the 2005 precedent, this pause reaffirmed the program's adaptability amid the caprices of launch logistics and inventory dynamics, ensuring that when the next Cobalt-M ascent vehicle thundered skyward, it would do so atop a foundation tempered by enforced patience. The void, far from a setback, etched a vital chapter in the saga of sustained space reconnaissance, where absence sharpened the edge of presence.\n\nAs the calendar turned from 2008, the Cobalt-M program emerged from its second year of deliberate stasis, a period marked by judicious inventory management and lingering constraints on launch vehicle availability that had postponed any new orbital insertions. This lull, echoing the quiet of 2005, was not a sign of stagnation but a calculated interlude, allowing engineers and operators at the program's nerve centers—facilities nestled within the secure perimeters of Vandenberg Space Force Base and the National Reconnaissance Office's shadowy directorates—to recalibrate for an era of unrelenting operational rhythm. The strategic imperatives of the late 2000s demanded nothing less: a world reshaped by asymmetric threats, proliferating missile technologies, and peer competitors flexing their capabilities in shadowed corners from the South China Sea to the volatile arc of the Middle East. Continuous coverage was no longer a luxury but the bedrock of national security, requiring a constellation of reconnaissance satellites that could deliver unblinking eyes on high-value targets, track mobile launchers with sub-meter precision, and feed real-time intelligence into the fusion centers of U.S. Strategic Command.\n\nThe ramp-up to high-tempo operations began in earnest during the waning months of 2008, as program managers orchestrated a symphony of parallel advancements across the kill chain of satellite production, launch integration, and mission control. At the prime contractor's sprawling assembly halls in Sunnyvale, production lines that had idled under lean inventories now hummed with renewed vigor. Batches of Cobalt-M bus structures—those resilient, radiation-hardened platforms marrying electro-optical imagers with synthetic aperture radar payloads—underwent accelerated qualification testing. Engineers fine-tuned the spacecraft's agility, enhancing on-orbit maneuvering thrusters to enable rapid station-keeping adjustments amid the cluttered geosynchronous belts and sun-synchronous inclinations that defined the program's architecture. These were not mere tweaks; they represented evolutionary refinements born from lessons etched in the operational logs of earlier birds, like the imperative to mitigate thermal cycling stresses during frequent repointing to dynamic theaters of interest.\n\nGround segment preparations mirrored this orbital fervor, with upgrades to the constellation's command-and-control backbone transforming disparate tracking stations into a unified, resilient network. The Distributed Space System Architecture, a Cobalt-M hallmark, saw its software layers infused with machine learning algorithms for predictive anomaly detection, ensuring that even in the face of solar flares or cyber probes, data downlinks remained impregnable. At the Mission Ground Segment facilities in Aurora, Colorado, operators drilled relentlessly in high-fidelity simulators, rehearsing the compressed timelines of launch-to-first-light sequences—mere days from booster ignition to initial tasking orders. These exercises stressed the human-machine interface, where photointerpreters and orbital analysts practiced triaging petabytes of multispectral imagery, prioritizing fleeting opportunities like ballistic missile salvos or naval transits through chokepoints. The goal was seamless handoffs: a satellite spotting a provocation off Yemen's coast could cue naval assets within the hour, its hyperspectral signatures revealing disguised cargoes invisible to legacy systems.\n\nLaunch infrastructure, that perennial bottleneck, received equal scrutiny. With Delta IV Heavy and Atlas V vehicles queuing for civil and military manifests, the program's schedulers negotiated fiercely for dedicated slots, leveraging interagency partnerships to preempt delays from range safety overflights or payload fairing certifications. Vandenberg's SLC-6 pad, reborn as a workhorse for national security launches, underwent final shakedowns for the Cobalt-M's mass simulators, confirming that the behemoth upper stages could loft payloads exceeding 4,000 kilograms into precise low-Earth orbits without compromising the satellites' gimbal-stabilized sensors. Contingency planning extended to international allies, with quiet dialogues exploring Ariane 5 surges from Kourou as backups, though domestic primacy remained sacrosanct.\n\nThis preparatory cadence was underpinned by a doctrinal shift within the intelligence community, articulated in classified white papers circulating through the Pentagon's J-2 corridors. The 2008 National Intelligence Strategy had underscored the perils of coverage gaps—windows exploited by adversaries for deniable actions—and Cobalt-M was positioned as the linchpin for persistent ISR dominance. High-tempo operations, as defined by program directives, meant sustaining a launch cadence of two to three vehicles annually, each with a nominal seven-year lifespan extended through dexterous propellant management. This cadence would swell the constellation to a critical mass, enabling stereo imaging for 3D battle damage assessments and automated change detection across vast maritime domains. Budgetary tailwinds from supplemental defense appropriations fueled the surge, channeling funds into redundant supply chains for iridium-clad avionics and cryocoolers that chilled infrared detectors to superconducting efficiencies.\n\nBy early 2009, the pieces were in motion, the program's dormant pulse quickening toward the frenetic operational tempo that would define the next two years. Operators, attuned to the inexorable orbital mechanics, monitored the aging sentinels of the 2004-2007 epochs—veterans like Cobalt-M Block IIs whose solar arrays bore the scars of micrometeorite peppering—knowing their graceful deorbits would soon cede the skies to fresher eyes. The stage was set for a renaissance: launches that would not only replenish but revolutionize, embedding Cobalt-M deeper into the fabric of joint all-domain operations. In the control rooms, where screens flickered with ephemeris predictions and threat vector overlays, anticipation crackled like static before a storm. The era of high-tempo reconnaissance had dawned, promising an unbroken vigil over a world grown ever more contested.\n\nAs the Cobalt-M program accelerated its operational tempo into the new year, the imperative for uninterrupted reconnaissance coverage over critical global theaters became starkly evident, with missions now routinely spanning calendar boundaries to maximize payload returns. Among the early 21st-century achievements that underscored this evolution stood the launch of Kosmos 2445, a zenith in the program's maturing capabilities, bridging the final months of one year into ***2009*** with a payload primed for recovery after months aloft. This crossover mission exemplified the strategic layering of orbital assets, where each satellite's film cassettes—loaded with high-resolution imagery from electro-optical and panoramic cameras—were meticulously managed to ensure data handover without gaps, a testament to the Zenit-derived Zenit-8 platform's reliability in sustaining the Soviet-era legacy into the modern reconnaissance epoch.\n\nKosmos 2445, comprising a 6,300-kilogram reconnaissance module, was inserted into a sun-synchronous orbit optimized for dawn-dusk imaging passes. Over the ensuing weeks, ground controllers at the Titov Main Test Space Center orchestrated a ballet of orbital adjustments and attitude maneuvers, coaxing the satellite through hundreds of imaging cycles that captured fleeting strategic developments from contested borders to naval maneuvers in distant seas. The Cobalt-M's modular design, with its separable service module and reentry vehicle, allowed for extended missions without compromising the integrity of the exposed film, even as solar activity began to nudge atmospheric densities and subtly decay the orbit. This endurance was no accident; it reflected iterative upgrades from prior Yantar and Cobalt iterations, where deorbit propulsion refinements and thermal protection enhancements had pushed nominal mission durations toward the three-month mark, vital for a nation recalibrating its space-based intelligence amid shifting geopolitical sands.\n\nBy mid-February, telemetry confirmed the payload's readiness for return, with the reentry capsule's ablative heatshield prepped and the service module's retro-rockets aligned for a precise deorbit burn. ***On the 23rd of February***, under clear winter skies across the vast Kazakh steppes, the sequence initiated flawlessly: a series of thruster firings slowed the stack from orbital velocity, committing it to a ballistic trajectory that arced toward the designated recovery ellipse near the Aral Sea's shrunken shores. Reentry plasma sheathed the capsule in a fleeting meteor trail, its peak deceleration forces testing the reinforced structure honed through years of program telemetry analysis. Parachutes bloomed in sequence—drogue, then main—halting the descent just meters above the snow-dusted plains, where a waiting cadre of Mi-8 helicopters from the 99th Separate Guards Reconnaissance Air Transport Regiment swooped in.\n\nRecovery teams, clad in fur-lined parkas against the biting -20°C chill, converged with practiced urgency, their GAZ Tigr vehicles churning through the frost-hardened terrain. The capsule, still warm from atmospheric friction, yielded its prize: over 1,000 meters of exposed film from the KAFA panoramic system and SFSR-31 side-looking radar adjuncts, bundled in vacuum-sealed canisters that had withstood the rigors of microgravity and thermal cycling. Initial post-recovery inspections under field tents revealed pristine cassettes, their emulsions capturing resolutions down to 2 meters—data that would soon feed into analysts' queues at Krasnoznamensk, informing assessments of adversary deployments with unprecedented temporal density. This winter touchdown not only closed out Kosmos 2445's chapter but heralded the program's pivot toward even denser launch cadences, as the recovery's success validated the orbital handoffs now routine in the Cobalt-M constellation.\n\nThe event's ripple effects extended beyond the immediate intelligence windfall. Engineering deconstructions in the weeks following revealed minor charring on the heatshield seams, prompting subtle alloy tweaks for subsequent vehicles, while the service module's splashdown in the Aral—tracked via onboard beacons—affirmed the precision of retro-burn sequencing. In the broader chronicle of Cobalt-M's ascent, this February finale underscored a pivotal maturation: from sporadic Cold War relics to a synchronized fleet enabling near-real-time strategic overwatch, all while contending with fiscal constraints and international scrutiny over dual-use space assets. Winter's harsh embrace had tested the program's mettle, yielding not just film but unassailable proof of its operational resilience.\n\nFollowing the dramatic de-orbit and recovery of the preceding Cobalt-M satellite in February 2009, which had extended its operational lifespan across the turn of the year to maintain critical reconnaissance coverage over key global hotspots, the Russian space program swiftly pivoted to the next phase of the Cobalt-M evolution. Engineers and mission planners at the Plesetsk Cosmodrome recognized the imperative of rapid replenishment to sustain the constellation's high-resolution imaging capabilities, essential for monitoring dynamic theaters of interest amid escalating geopolitical tensions. The Spring 2009 deployment emerged as a cornerstone effort, embodying the program's maturing reliability and the Soviet-era legacy of resilient space operations now refined through post-Cold War technical iterations.\n\nAs winter thawed into the brisk promise of spring, ground crews intensified preparations for what would become Kosmos 2450, the latest iteration in the Cobalt-M lineage. This satellite represented incremental advancements in electro-optical sensors, enabling sharper all-weather imaging from sun-synchronous orbits, a vital upgrade for persistent surveillance missions. Payload specialists conducted exhaustive environmental testing in the weeks leading up to launch, simulating the rigors of ascent vibrations and the vacuum of space to ensure the reconnaissance suite's integrity. Fuel loading protocols, refined from prior missions, incorporated hypergolic propellants for precise orbit maneuvers post-insertion, while command and data handling subsystems underwent final software validations to preempt any autonomy lapses during the critical early orbit phase.\n\nThe final countdown sequence unfolded with meticulous precision, underscoring the disciplined choreography of Russian rocketry. On 25 April 2009, teams executed a comprehensive pre-launch rehearsal, dry-running the entire fueling and evacuation procedures under simulated emergency conditions to iron out any procedural latencies. This was followed by the payload integration milestone on 27 April 2009, when the Cobalt-M bus was encapsulated within its fairing amid stringent cleanroom protocols, with optical telescopes aligned and star trackers calibrated for immediate post-separation attitude acquisition. ***Kosmos 2450 finally launched on 29 April 2009, marking the mission's true beginning as the Kosmos-3M rocket ignited its upper stage, propelling the payload skyward from Plesetsk's hallowed pad.***\n\nLiftoff occurred under clear Arctic skies, the vehicle's characteristic plume tracing a flawless arc northward as it pierced the mesosphere. Telemetry streams confirmed nominal performance across all stages: first-stage burnout and separation at T+120 seconds, second-stage ignition yielding the requisite velocity increment, and fairing jettison revealing the satellite's solar arrays unfurling like metallic petals against the Earth's limb. Orbit insertion into the target 680-kilometer sun-synchronous plane was achieved with sub-meter precision, validated by ground stations in Komsomolsk-na-Amure and subsequent passes over Chelyabinsk. Initial battery deployment and power stabilization preceded the first imaging pass just 45 minutes post-separation, capturing validation imagery of Siberian test sites that affirmed the payload's cryogenic coolers and focal plane arrays were fully operational.\n\nThe successful deployment of Kosmos 2450 not only bridged the gap left by its predecessor but also enhanced the Cobalt-M network's redundancy, allowing for interleaved collection tasks that bolstered real-time intelligence feeds to military planners. Early mission data revealed exquisite detail in multispectral bands, from visible panchromatic to infrared signatures, capable of discerning vehicle convoys at standoff ranges exceeding 200 kilometers. This launch exemplified the program's operational tempo, with anomaly-free commissioning paving the way for a multi-year endurance test amid solar maximum radiation challenges. By late May, full constellation synergy was realized, underscoring Russia's enduring prowess in electro-optical reconnaissance from space.\n\nWith the Cobalt-M satellite—designated as Cobalt-M 4—successfully inserted into its primary low Earth orbit trajectory in late April 2009, the program's operational team at the mission control center pivoted swiftly from launch-phase exhilaration to the more protracted challenges of longevity. The initial reconnaissance passes had confirmed nominal imaging performance, capturing high-resolution electro-optical data over priority targets with the expected fidelity. Yet, even as the first datasets streamed down to ground stations, planners were already grappling with a persistent constraint that had shadowed the program since its inception in 2004: mission durations that rarely exceeded six to eight weeks. Early Cobalt-M vehicles, while revolutionary in their agile maneuvering and real-time tasking capabilities, were hamstrung by conservative resource budgets, primarily dictated by propellant reserves for orbit maintenance and power subsystem degradation over time. The imperative now was clear—extend operational life toward a aspirational three-month benchmark to maximize return on investment, enhance coverage density, and demonstrate the maturity of the constellation.\n\nThis push for extended missions crystallized in a series of engineering deep dives codenamed \"Endurance Reviews,\" launched immediately post-insertion. Mission planners, drawing on telemetry from the first three weeks of Cobalt-M 4 operations, identified resource consumption as the linchpin. Propellant usage for station-keeping maneuvers, essential to counter atmospheric drag in the satellite's 450-kilometer circular orbit, emerged as the primary depleter. Initial rates, influenced by variable solar activity and geomagnetic perturbations, were depleting the xenon-based ion thruster reserves at a pace that projected exhaustion well short of 90 days. Engineers responded by refining orbit determination algorithms, integrating more precise drag models derived from prior missions, and implementing predictive station-keeping schedules that anticipated decay trends rather than reacting to them. These adjustments, validated through high-fidelity simulations on ground-based digital twins of the spacecraft, yielded measurable gains: thrust firings were batched more efficiently, reducing overall impulse demands by minimizing thruster cycling wear.\n\nPower management presented an equally thorny challenge, as the satellite's gallium arsenide solar arrays, while efficient at launch, suffered gradual output degradation from ultraviolet exposure and micrometeoroid impacts. Early mission data revealed consumption rates for the imaging payload—particularly during high-duty-cycle stare modes for persistent surveillance—that accelerated battery cycling and risked thermal runaway in the nickel-hydrogen cells. The team countered with a multifaceted strategy: dynamic power budgeting software that prioritized tasks based on real-time orbital geometry and target value, coupled with array articulation tweaks to optimize sun-angle incidence. Thermal engineers, meanwhile, fine-tuned radiator deployment sequences and heater profiles, leveraging passive cooling enhancements from lessons learned on Cobalt-M 3. These interventions extended usable power margins, allowing the satellite to sustain peak imaging loads for longer arcs without dipping into deep-discharge reserves that shortened cell life.\n\nAttitude control resources added another layer of complexity, with reaction wheels and momentum dumps consuming momentum at rates amplified by frequent repointing for multi-target tasking—a hallmark of the Cobalt-M design philosophy. The control team introduced momentum management routines that offloaded wheels into the orbit plane more judiciously, using magnetic torquers during geomagnetic \"sweet spots\" to preserve control moment gyroscope propellant. Software uploads in May 2009, rigorously tested in anechoic chambers mimicking orbital RF conditions, enabled these autonomous routines, freeing operators from constant manual interventions. Collectively, these optimizations formed a resource-aware operational paradigm, where every maneuver, imaging pass, and downlink was scrutinized for its cumulative toll.\n\nBy mid-June, as Cobalt-M 4 approached its two-month milestone, the Endurance Reviews bore fruit. Resource consumption curves, plotted in real-time mission consoles, flattened encouragingly: propellant drawdown slowed to levels projecting beyond 80 days, power budgets held steady under sustained operations, and attitude stability improved without excessive dumps. This wasn't mere incremental tweaking; it represented a systemic evolution in satellite husbandry. Planners extrapolated these gains to the broader constellation, forecasting that Cobalt-M 5, slated for summer deployment, could incorporate hardware-level redundancies like oversized thruster tanks and radiation-hardened array drivers from the outset. Ground teams, collaborating with propulsion specialists from the prime contractor, even explored hybrid chemical-ion augmentation for end-of-life boosts, though fiscal constraints deferred full implementation.\n\nThe extended mission ethos permeated beyond engineering silos, influencing tactical doctrine. Reconnaissance tasking evolved from opportunistic bursts to phased campaigns, balancing high-resolution spot imaging with lower-power synthetic aperture radar modes to conserve energy. Data compression algorithms were uplinked to shrink downlink volumes, easing command stack pressures and allowing more frequent health checks. Risk mitigation loomed large—contingency modes for anomalous consumption spikes were pre-loaded, drawing on forensic analyses from Cobalt-M 2's premature shutdown due to an unforeseen thruster leak. Weekly anomaly resolution working groups, comprising astrodynamics experts, payload scientists, and systems engineers, dissected telemetry trends, ensuring that deviations from baseline rates triggered automated safeguards.\n\nAs summer waned, Cobalt-M 4's telemetry painted an optimistic picture: three months in orbit remained elusive but tantalizingly within reach. The program's architects, reflecting on the 2004 baseline of one-month missions, hailed this as a watershed. Resource modeling tools, honed through iterative campaigns, now predicted fleet-wide endurance averaging 10 weeks, with outliers pushing further. This groundwork not only validated the Cobalt-M architecture's scalability but also informed successor designs, where extended life became a non-negotiable requirement. The late 2009 operations tempo, buoyed by these engineering triumphs, underscored a maturing discipline: reconnaissance satellites no longer as fragile sprinters, but as resilient marathoners, their every gram of propellant and watt of power leveraged to pierce the veil of uncertainty below.\n\nThe spring 2009 mission of the Cobalt-M program marked a pivotal achievement in the ongoing quest to extend operational lifespans, building directly on the engineering refinements that had targeted resource consumption rates to approach the ambitious three-month benchmark. Launched in April aboard a reliable Soyuz-2.1v rocket from Plesetsk Cosmodrome, Kosmos 2450 embodied the cumulative lessons from prior flights, where meticulous calibration of propulsion propellant allocation and power subsystem efficiencies had incrementally stretched endurance limits. Ground controllers at the Russian Space Forces' Mission Control Center near Moscow monitored the satellite's ascent into a sun-synchronous orbit at approximately 680 kilometers altitude, its electro-optical imaging payload primed for high-resolution reconnaissance over diverse global theaters.\n\nFrom the moment of orbital insertion, Kosmos 2450 demonstrated the fruits of these optimizations, maintaining nominal thermal control and attitude stability through the variable solar illumination cycles of early northern hemisphere spring. The spacecraft's stellar attitude sensors and hydrazine thrusters worked in harmony to execute precise slew maneuvers, capturing imagery across urban sprawl, maritime chokepoints, and remote installations—data streams that fed into Russia's strategic intelligence apparatus with unprecedented temporal density. As weeks unfolded, the mission's telemetry revealed no anomalous power draw from the solar arrays or battery degradation beyond models, a validation of the lightweight composite materials and radiation-hardened electronics iteratively tested in ground simulations.\n\n***Kosmos 2450's operational phase endured aloft for 12 weeks and 5 days, a testament to its robust design before deorbiting.*** This duration, just shy of the three-month threshold, represented the longest sustained performance in the Cobalt-M lineage to date, surpassing the fall 2008 mission by a margin that underscored the efficacy of throttled payload duty cycles and autonomous fault-tolerant software. The final days saw a controlled retrograde burn to initiate atmospheric reentry over the Pacific Ocean, ensuring compliance with international orbital debris mitigation protocols while preserving the integrity of classified hardware. Post-mission analysis at the Khrunichev State Research and Production Space Center highlighted how this extended timeline not only amplified data yield—enabling multi-seasonal change detection in key areas of interest—but also informed propulsion modeling for subsequent launches.\n\nIn the broader arc of the program's evolution from 2004 onward, the spring mission's longevity signaled maturity in Cobalt-M operations, bridging the gap between prototype validations and serial production readiness. Engineers noted that the 12-week-plus endurance minimized the frequency of constellation replenishment launches, optimizing the SL-14 Zenit manifest and reducing lifecycle costs amid tightening budgets. This success ripple-effected into refined manufacturing at ISS Reshetnev, where subsequent satellites incorporated marginal boosts in fuel capacity and sensor redundancy, setting the stage for even more protracted vigils in the years ahead. Kosmos 2450's graceful conclusion thus stood not as an endpoint, but as a launchpad for the Cobalt-M's ascent toward routine multi-quarter operations, etching its place in the chronicle of resilient space reconnaissance.\n\nAs the Cobalt-M reconnaissance satellite, designated Kosmos 2450 and launched in April 2009, approached the conclusion of its operational lifespan—spanning nearly three months of intensive imaging and data collection over contested regions—ground controllers at the Russian Space Forces' mission control center in Plesetsk began meticulous preparations for deorbit. This phase marked a critical juncture in the program's operational doctrine, emphasizing responsible end-of-life disposal to mitigate space debris risks in the increasingly congested low Earth orbit regime where these satellites operated at altitudes around 650-700 kilometers. Deorbit mechanics for Cobalt-M platforms followed a standardized sequence honed through prior missions, balancing propulsion constraints with orbital decay dynamics to ensure controlled reentry over oceanic disposal zones, typically the Pacific Ocean's \"Spacecraft Cemetery\" south of Australia.\n\nThe initiation of deorbit commenced with a series of pre-burn health checks and orbital adjustments. Telemetry from the satellite's onboard systems confirmed nominal performance of the integrated propulsion module, derived from the Yakhont upper stage heritage, which housed hydrazine-fueled thrusters capable of delivering precise velocity increments. Ground teams uploaded a sequence of command packets via S-band uplinks from tracking stations in Komsomolsk-na-Amure and Ussuriysk, first executing minor plane-change and circularization maneuvers to optimize the retrograde burn geometry. These preparatory firings, conducted over 48 hours, nudged the satellite's inclination slightly and raised apogee marginally to align the orbital plane for maximum atmospheric drag efficiency post-burn. Engineers monitored real-time parameters such as battery state-of-charge, thermal profiles, and attitude control via star trackers and reaction wheels, ensuring the satellite maintained three-axis stability essential for thruster plume alignment.\n\n***Ground control initiated the primary deorbit burn for the Kosmos 2450 satellite on 20 July 2009.*** This pivotal maneuver, executed during a precise acquisition-of-signal window at approximately 0430 Moscow Time, involved a sustained firing of the main orbital unit thrusters in retrograde orientation relative to the velocity vector. The burn sequence, autonomously managed by the satellite's flight computer after ground initiation, lasted several minutes, imparting a delta-velocity sufficient to depress perigee below 150 kilometers, where aerobraking would rapidly dominate decay. Live downlink data streams to the primary control center revealed smooth ignition, with pressure transducers and accelerometer readings validating full-thrust performance; no anomalies were reported, a testament to the robustness of the Cobalt-M propulsion subsystem refined since the 2004 inaugural flights.\n\nImmediate post-burn analysis from Solovki and subsequent tracking passes confirmed the maneuver's success: telemetry indicated a perigee drop from over 600 kilometers to under 200 kilometers, initiating exponential atmospheric interaction. The satellite's attitude was reoriented to a perigee-impacting pitch for enhanced drag, with solar panels feathered to minimize residual orbit perturbations. This deorbit initiation not only adhered to international orbital debris mitigation guidelines but also showcased evolutionary improvements in the Cobalt-M program, such as enhanced autonomy in burn sequencing to reduce ground intervention risks amid variable weather impacting uplink windows. Over the ensuing days, orbital predictions tracked the inexorable descent, with ground controllers issuing periodic repointing commands to preserve imaging payload integrity until final reentry, underscoring the blend of military utility and prudent space stewardship that defined the 2009 mission's closure.\n\nAtmospheric Interface Protocols\n\nAs the Cobalt-M spacecraft plummeted toward its fiery terminus following the precisely timed primary deorbit burn executed by ground control, the mission transitioned into one of the most unforgiving phases of orbital decay: the atmospheric interface. This critical juncture marked the spacecraft's passage from the near-perfect vacuum of space—where it had orbited for over a decade in microgravity, shielded from molecular interactions—into the tenuous grasp of Earth's upper atmosphere. Here, the protocols governing this interface were not merely operational checklists but a symphony of predictive physics, designed to anticipate and characterize the spacecraft's behavior as it crossed the Karman line's effective boundary, roughly where aerodynamic forces begin to dominate over orbital dynamics.\n\nThe transition from vacuum to atmosphere unfolded as a profound physical metamorphosis. In the vacuum regime, the Cobalt-M glided along Keplerian trajectories, its velocity governed solely by gravitational potentials and residual thrust vectors, encountering no drag or thermal exchange beyond sporadic micrometeoroid impacts or solar radiation. But as perigee dipped below approximately 120 kilometers altitude—precisely the threshold calibrated during pre-deorbit simulations—the exosphere's whisper-thin particle density escalated into a tangible medium. Neutral atoms and molecules, primarily atomic oxygen and nitrogen at these heights, began to impinge upon the spacecraft's forward-facing surfaces. This initial interaction was subtle, manifesting as a drag force that sapped orbital energy incrementally, nudging the satellite into a decaying spiral. Protocols dictated continuous telemetry monitoring via S-band beacons, capturing ephemeris data to refine atmospheric density models in real-time, as even minor discrepancies in solar activity could swell the thermosphere's scale height.\n\nDeeper into the mesosphere and thermosphere boundary, around 80 to 100 kilometers, the encounter intensified into hypersonic aerodynamics. The spacecraft, still hurtling at velocities exceeding several kilometers per second, slammed into air molecules with such ferocity that compression heating dominated. A bow shock formed ahead of the vehicle, ionizing the air into a luminous plasma sheath that enveloped the structure. This plasma, glowing with the incandescence of thousands of degrees Kelvin, absorbed and re-radiated energy while disrupting communications—a phenomenon protocol engineers termed \"blackout onset.\" Thermal loads peaked here, driven by convective heating from the shocked boundary layer and radiative transfer from the superheated gas cap. The Cobalt-M's multi-layered thermal protection, inherited from earlier reconnaissance designs, relied on ablative charring and radiative equilibrium rather than active cooling, as retrofitting cryogenic systems for end-of-life disposal was deemed impractical during the program's austere budget cycles from 2008 onward.\n\nThese protocols emphasized phenomenological forecasting over intervention, given the spacecraft's autonomous terminal phase. Ground teams at the primary control node cross-referenced live accelerometer data against semi-empirical models like the Jacchia-Roberts density profile, adjusting predictions for geomagnetic influences that could puff up the atmosphere by up to 30 percent during solar storms. As the interface progressed, aerodynamic torques induced by uneven drag on solar arrays and antenna booms threatened attitude stability, potentially tumbling the vehicle and altering heat flux distributions. Historical precedents from analogous programs, such as the 2004 Genesis capsule mishap, informed Cobalt-M's design heritage, embedding passive stabilisers to favor a belly-flop orientation that maximized drag while distributing thermal stresses across the widest surface area.\n\nThe crescendo of thermal aggression occurred in the 60- to 80-kilometer altitude band, where peak dynamic pressure—stagnation pressure at the nose—coincided with maximum heating rates. Molecules dissociated into atomic species, enhancing radiative contributions from lines like the nitrogen Swanson bands, turning the reentry corridor into a streak of auroral fire visible from continental distances. Protocols included spectral analysis from ground-based optical trackers, correlating plasma luminosity with heat flux estimates to validate material response. For Cobalt-M, this phase encapsulated the program's evolution: early missions (2004-2008) suffered from conservative perigee targeting that prolonged decay, risking orbital debris proliferation, whereas post-2010 iterations refined burns for steeper entries, compressing the interface window to under 30 minutes and minimizing uncontrolled fragmentation risks.\n\nBeyond peak heating, the atmosphere's increasing density shifted the balance toward fragmentation dynamics. Structural integrity faltered under combined aerothermal and inertial loads, with protocols shifting to survivor prediction—modeling daughter debris trajectories using tools evolved from the program's own orbital mechanics suite. This final transition saw the spacecraft's remnants decelerate from orbital speeds to terminal velocity, dispersing payloads and bus components across a designated oceanic footprint. In retrospect, the atmospheric interface protocols for Cobalt-M exemplified the reconnaissance satellite era's maturation, blending empirical aerophysics with computational foresight to ensure responsible deorbiting amid geopolitical scrutiny over space sustainability. The seamless handover from vacuum silence to atmospheric inferno not only closed the mission loop but also yielded invaluable data for successor constellations, underscoring the inexorable physics that bookends every orbital endeavor.\n\nAs the Cobalt-M reconnaissance satellite, exemplified by the Kosmos 2450 mission launched in 2009, began its inexorable descent through the tenuous upper atmosphere, the intense thermal loads from atmospheric friction—previously outlined in terms of hypersonic compression and radiative heating—gradually subsided into a more subtle regime. This marked the transition from the initial high-drag encounter to the controlled coasting phase, a critical interval where the spacecraft's trajectory was meticulously shaped without reliance on propulsion systems. In this passive reentry prelude, the satellite relied on gravitational perturbations, residual orbital momentum, and aerodynamic forces to execute fine adjustments, preserving the structural integrity tested by earlier aerothermal stresses while steering toward the predetermined deorbit corridor.\n\n***The Kosmos 2450 satellite underwent a precisely controlled 5-day coasting phase through the upper atmosphere to adjust trajectory.*** This extended period, spanning from the moment perigee dipped sufficiently into the mesosphere around 80-100 km altitude until the commitment to final plunge, allowed mission controllers to monitor and refine the decay path with extraordinary precision. Unlike aggressive retro-burn maneuvers employed in some contemporary programs, the Cobalt-M approach emphasized passivity, leveraging the satellite's own ballistic coefficient and attitude orientation to modulate drag profiles. By periodically reorienting via onboard reaction wheels or magnetic torquers—remnants of its reconnaissance-era control systems—Kosmos 2450 could alter its angle of attack, effectively varying the atmospheric bite and inducing controlled precession in its orbital plane. This technique, honed through years of iterative deorbiting in the program's evolution from 2004 onward, minimized fuel expenditure in the satellite's depleted state while compensating for uncertainties in solar activity and geomagnetic influences that subtly altered upper atmospheric density.\n\nThe dynamics of this coasting phase were governed by the interplay of Coriolis forces, Earth's oblateness, and lunisolar perturbations, which over five days cumulatively nudged the argument of perigee and inclination to align with safe reentry grounds—typically expansive oceanic expanses far from populated regions. Telemetry data streamed back via ground stations in the Russian network revealed oscillations in altitude, with perigee altitudes hovering in the 70-90 km band, where molecular diffusion and rarefied gas effects dominated over continuum aerodynamics. Controllers exploited these natural variabilities, issuing commands to yaw or pitch the satellite's bus, thereby asymmetrically distributing drag across its cross-section—a scarred relic of multi-year optical reconnaissance duties. This passive sculpting not only averted premature burnout from excessive heating but also ensured the trajectory's eccentricity damped predictably, transitioning the orbit from a shallow dip to an irreversible decay spiral.\n\nThroughout this epochal five-day traverse, the Kosmos 2450 exemplified the Cobalt-M program's maturation in end-of-life management, where reentry was less a cataclysmic event and more a choreographed denouement. Environmental sensors, still functional amid degrading avionics, captured gradients in neutral density and ionospheric plasma, feeding real-time models that predicted the coast's endpoint with margins under 1 degree of geodetic latitude. The phase's length—deliberately protracted—afforded redundancy against ephemeris errors or unexpected coronal mass ejections, which could inflate the thermosphere and accelerate drag unpredictably. As coasting progressed, the satellite's center of mass experienced minute nodal precessions, aligning the reentry vector with prevailing jet streams at lower altitudes for additional passive stabilization. This methodical drift through the atmospheric frontier underscored the engineering philosophy of the era: harnessing orbital mechanics as a thruster in its own right, transforming potential chaos into a symphony of controlled demise.\n\nBy the conclusion of the coasting phase, Kosmos 2450 had shed sufficient velocity—through cumulative drag losses approximating the delta-v equivalent of a small thruster burn—positioning itself impeccably for the terminal reentry. This passive mastery not only mitigated risks to overflight assets but also preserved the secrecy integral to the program's reconnaissance heritage, with the satellite's disintegration confined to remote abyssal plains. In the broader chronicle of Cobalt-M operations, the 2009 mission's coasting dynamics stood as a pinnacle, influencing subsequent deorbits through 2015 by validating extended passive trajectories as both economical and resilient in the face of variable space weather.\n\nAs the controlled coasting phase drew to a close, the Cobalt-M satellites, honed by years of iterative refinements since the program's inception in 2004, transitioned seamlessly into the critical final approach maneuvers. This phase marked the culmination of deorbit preparations, where precision became paramount to ensure the satellite's controlled reentry over designated Pacific impact zones, minimizing risks to populated areas and safeguarding sensitive payloads from unintended recovery. For the 2009 mission, embodied by Kosmos 2450, ***the reentry included 2 additional days of final descent maneuvers including attitude adjustments and retrofire***, a sequence that exemplified the maturity of Russian orbital reconnaissance deorbitation techniques by that era.\n\nThe first of these two days commenced with a series of meticulously sequenced attitude adjustments to align the satellite precisely toward the oncoming atmospheric interface. Kosmos 2450, launched on 29 April 2009, had already shed much of its operational velocity during coasting, but these maneuvers demanded exceptional accuracy. Ground controllers transmitted commands to rotate the spacecraft from its nadir-pointing survey orientation to a retrograde attitude.\n\nThroughout Day 1, intermittent firings fine-tuned this alignment. These attitude holds were verified through telemetry bursts, confirming precise orientation. As perigee lowered, the satellite executed its primary retrofire to commit to terminal guidance. This deorbit impulse shaved velocity to support aerodynamic capture.\n\nDay 2 intensified the drama of terminal guidance, as atmospheric drag began to assert dominance. Attitude adjustments resumed, maintaining optimal angles for corridor steering toward the designated impact zone. Retrofire sequences punctuated this phase, supporting precise descent control.\n\nThese maneuvers represented the evolutionary pinnacle of the Cobalt-M program by 2009. As reentry peaked, the attitude profile held firm in a controlled display. Kosmos 2450's descent corridor stayed on track, a testament to the two-day ballet of adjustments and retrofires that precluded uncontrolled skips or overshoots. Fragments rained into the ocean post-reentry, validating the program's operational tempo and setting benchmarks for subsequent missions. This terminal guidance phase underscored the Cobalt-M's dual legacy: as a prolific imager and as a masterclass in sovereign space disposability.\n\nFollowing the meticulously executed attitude adjustments over the final two days—refinements that fine-tuned the Cobalt-M satellite's orientation to within arcseconds of the targeted reentry corridor—the 2009 mission culminated in one of the most precise recoveries in the program's nascent history. The payload capsule, after enduring the fiery gauntlet of atmospheric reentry at hypersonic velocities, deployed its drogue parachute flawlessly at an altitude of approximately 30 kilometers, stabilizing the descent before the main parachutes unfurled in a choreographed sequence that minimized oscillations and drift. Ground tracking stations, augmented by real-time telemetry from the overflying recovery aircraft, pinpointed the landing zone in the remote Pacific recovery area with exceptional fidelity, allowing helicopters to converge within minutes of splashdown. This precision was no accident; it stemmed from iterative simulations conducted during the orbital phase, where onboard thrusters corrected for residual perturbations from solar radiation pressure and gravitational anomalies, ensuring the capsule's trajectory intersected the designated ellipse with a dispersion far tighter than the mission's conservative error budgets.\n\nRecovery operations unfolded with textbook efficiency, underscoring the maturation of procedures honed since the program's 2004 inception. The primary recovery ship, positioned via GPS-enhanced inertial navigation, arrived on station mere hours after deorbit burn confirmation, its crew primed for the multi-spectral beacon signals emitted by the capsule. Divers and winch operators secured the bobbing payload within 45 minutes of water impact, preventing any prolonged exposure to saltwater corrosion that could degrade the delicate reconnaissance media housed within. Post-retrieval inspections aboard the vessel revealed no structural compromises: the ablative heat shield had charring consistent with nominal performance, and the pressure vessel maintained hermetic integrity throughout, preserving the internal environment engineered to shield infrared films and electro-optical recording tapes from thermal shock and vacuum exposure. This seamless handoff from orbit to deck marked a pivotal success for the 2009 campaign, validating the Cobalt-M's design philosophy of recoverable high-fidelity intelligence gathering in contested domains.\n\nThe true measure of the mission's triumph, however, lay in the payload's quality upon debrief at the secure processing facility stateside. Technicians, working under stringent cleanroom protocols, extracted over 2,500 frames of panoramic reconnaissance imagery—capturing strategic assets across expansive theaters with ground resolution approaching the system's theoretical limits. The films exhibited negligible fogging or emulsion defects, attributable to the capsule's active thermal control system, which cycled precisely to counteract reentry-induced temperature spikes. Spectral analysis confirmed that multispectral bands, from visible through mid-wave infrared, retained dynamic range integrity, yielding data products that exceeded pre-mission intelligence requirements by enabling feature identification at scales previously reserved for lower-altitude platforms. Complementary digital storage modules, embedded as a technology demonstrator, returned petabytes of compressed metadata and auxiliary telemetry, further enriching the dataset with precise geolocation tags derived from stellar navigation fixes performed en route.\n\nZooming out to the broader 2009 campaign, which encompassed this flagship recovery alongside two ancillary test firings earlier in the year, the Cobalt-M program demonstrated robust operational tempo and adaptability. The year's missions collectively amassed the largest archive of persistent surveillance data in the program's portfolio to date, outstripping aggregate yields from prior launches through enhanced orbital dwell times and refined pointing accuracy. Challenges, such as minor thruster misfires during initial deployment, were mitigated via ground-commanded redundancies, affirming the satellite's fault-tolerant architecture. Lessons from the precision landing—particularly the interplay between attitude control and deorbit predictability—informed trajectory optimization algorithms that would propagate to subsequent vehicles, reducing recovery footprint uncertainties by orders of magnitude.\n\nIn strategic terms, the 2009 successes catalyzed a paradigm shift within the intelligence community, proving that manned-independent, capsule-return reconnaissance could supplant aging dispensable systems while delivering perishable, high-assurance intelligence unattainable via downlink-only architectures vulnerable to jamming or interception. The payload's analytical exploitation yielded actionable insights into adversary maneuvers, directly influencing operational planning and underscoring Cobalt-M's role as a force multiplier. Environmentally, the controlled reentry minimized debris risks, with post-mission sweeps confirming zero orbital remnants—a hallmark of responsible space operations that set a benchmark for peers. As analysts pored over the returned bounty, the consensus was unequivocal: 2009 not only validated the Cobalt-M's technical viability but propelled its evolution toward the multi-satellite constellations envisioned for the coming decade, cementing its legacy as a cornerstone of modern overhead reconnaissance.\n\nBuilding on the triumphs of 2009, where recovery teams had executed flawless precision maneuvers to retrieve payloads of exceptional clarity and detail, the Cobalt-M program surged forward into its next phase with unyielding momentum. Engineers and operators, buoyed by the high-fidelity imagery and robust data returns from the prior campaign, refined their protocols for even greater orbital endurance and resolution. The transition to 2010 marked a pivotal escalation in operational tempo, as the team calibrated ground infrastructure and payload integration for what promised to be the most ambitious deployment yet. Whispers within the tightly knit community of space operations specialists hinted at enhancements in electro-optical sensors, designed to pierce deeper into contested regions under varying light conditions, all while maintaining the program's hallmark stealth and reliability.\n\nAs winter thawed into spring, preparations intensified at the remote northern launch complex, where technicians meticulously assembled the stack under vast, echoing assembly halls. The Cobalt-M's modular architecture allowed for swift adaptations, incorporating lessons from the previous year's reentry dynamics to optimize thermal shielding and attitude control. Ground support crews ran exhaustive simulations, stress-testing telemetry links and propulsion sequencing against the harshest environmental forecasts. Site conditions emerged as a focal point of scrutiny; persistent Arctic winds had scoured the pad area clean of ice, while barometric pressures stabilized at levels ideal for maximum thrust efficiency. Clear visibility extended to the horizon, unmarred by the low-lying fog that had plagued earlier windows, ensuring that tracking radars and optical spotters could maintain uninterrupted line-of-sight from liftoff through initial ascent.\n\nThe culmination arrived amid a palpable hush of anticipation, as final countdown protocols synchronized across control centers. Fueling sequences proceeded flawlessly, with cryogenic propellants chilled to nominal temperatures under vigilant oversight. Range safety officers cleared the airspace, and the booster's turbopumps hummed to life in a symphony of pre-ignition checks. ***Kosmos 2462 soared into orbit on the 100th day of 2010, capturing the attention of space enthusiasts worldwide.*** Flames erupted from the first stage nozzles in a brilliant plume, thrusting the reconnaissance payload skyward on a precisely calculated trajectory toward its operational altitude. Vibrations rippled through the vehicle as it pierced the thickening atmosphere, staging cleanly at predetermined velocity milestones to shed mass and accelerate.\n\nInitial post-launch telemetry confirmed nominal performance across all subsystems, with the satellite achieving circularization in its target regime shortly thereafter. Solar arrays unfurled like metallic petals, greedily harvesting photons to power the suite of imaging instruments that would soon redefine reconnaissance capabilities. Ground controllers, monitoring from fortified bunkers, exhaled in collective relief as the bird sang back confirmations of attitude acquisition and first-light health checks. This launch not only perpetuated the Cobalt-M lineage but also set the stage for a year of sustained vigilance, where the satellite's gaze would roam vast theaters of interest, delivering insights that shaped strategic postures for years to come. The 2010 campaign was underway, a testament to the program's evolutionary resilience and the unerring precision of its human-machine symbiosis.\n\nThe April 2010 launch of Cobalt-M satellite number six from the windswept pads of Vandenberg Air Force Base marked not just another ascent into the orbital fray, but a quiet affirmation of the program's maturation into a paragon of operational consistency. What had begun as a daring venture in 2004, fraught with the uncertainties of cutting-edge reconnaissance technology, had by this juncture evolved into a symphony of standardized precision, where each mission unfolded with the reliability of a well-rehearsed ritual. The launch vehicle, a stalwart Atlas V variant meticulously configured for the Cobalt-M payload, cleaved through the coastal fog with unerring fidelity to protocol, its trajectory mirroring those of its predecessors down to the finest orbital insertion parameters. Gone were the experimental tweaks and last-minute adjustments that characterized the early flights; in their place stood a blueprint of standardization that permeated every facet of the operation, from payload integration to post-deployment verification.\n\nThis standardization was no mere administrative convenience but the bedrock of the program's endurance, forged through iterative refinements across the initial half-dozen missions. Mission profiles had coalesced into a templated archetype: each Cobalt-M satellite, with its advanced electro-optical and synthetic aperture radar suites, was tasked with persistent surveillance over high-priority theaters, orbiting in a sun-synchronous path at approximately 500 kilometers altitude to ensure optimal lighting conditions and revisit rates. Ground crews at the integration facilities in Sunnyvale followed invariant checklists—payload mating, vibration testing, electromagnetic compatibility sweeps—that had been honed to eliminate variability. The satellites themselves embodied this ethos, sharing a common bus architecture derived from the original 2004 design, with modular avionics bays that allowed for sensor upgrades without disrupting the core structure. Propellant loads, attitude control thrusters, and solar array deployments were calibrated to identical specifications, ensuring that once on station, each bird performed indistinguishably from its siblings in terms of power budgeting, thermal management, and data downlink cadences.\n\nThe routine nature of these flights infused the program with an almost industrial cadence, transforming what was once a high-stakes gamble into a predictable production line. Launch windows, once dictated by fleeting opportunities amid technical gremlins, now adhered to a biennial rhythm, with processing timelines compressed to under six months from factory floor to liftoff. Range safety officers at Vandenberg recited the same activation sequences, while mission control at the National Reconnaissance Office's NRO Ground Segment facilities in Colorado Springs monitored ascent with dashboards that had become as familiar as an airliner's cockpit instruments. This predictability extended to anomaly resolution; minor glitches, such as transient solar array articulations or fleeting command link dropouts, were addressed via pre-scripted contingency playbooks, drawing from a shared lessons-learned repository that spanned the fleet. The hardware's reliability, underpinned by radiation-hardened components and redundant fault-tolerant computing, meant that deorbit maneuvers and end-of-life passivation followed a scripted finale, minimizing space debris risks in line with international norms.\n\nBeyond the orbital domain, standardization streamlined the intelligence pipeline, ensuring that the flood of imagery and signals intelligence from Cobalt-M assets flowed seamlessly into analytical workflows. Data processing centers employed uniform compression algorithms and encryption protocols, calibrated to the satellites' high-resolution multispectral feeds, which yielded consistent product quality regardless of the originating platform. Operators trained on identical simulators, rotating through shifts with the discipline of a naval watch system, while software updates—delivered via secure S-band uplinks—were rolled out fleet-wide in synchronized waves. This operational homogeneity not only boosted efficiency but also enhanced interoperability with allied reconnaissance networks, allowing Cobalt-M data to slot effortlessly into multinational fusion centers.\n\nBy the early 2010s, this consistency had ripened into a strategic asset, enabling planners to forecast capabilities with clockwork confidence amid shifting geopolitical demands. Subsequent launches in 2012 and 2014 adhered faithfully to the template, each one a testament to the program's resilience against budgetary headwinds and technological temptations to diverge. Even as emerging threats prompted subtle payload evolutions—like enhanced infrared detectors for low-observable tracking—the mission architecture remained sacrosanct, preserving the interoperability that defined the fleet's value. In the annals of space reconnaissance, the Cobalt-M program stood as a masterclass in operational consistency, where standardization did not stifle innovation but channeled it into sustained excellence, carrying the shadows of secrecy aloft with unwavering dependability through the decade's close.\n\nThe 2011 Evolution\n\nAs the Cobalt-M program entered 2011, the operational tempo established in the preceding years—characterized by standardized launches, reliable hardware performance, and a cadence of routine reconnaissance missions—began to yield to a subtle yet profound transformation. What had become a well-oiled machine of predictable orbital insertions and data relays evolved into something more ambitious, driven by a confluence of technological maturation and strategic imperatives within the intelligence community. Program managers at the lead agency, drawing on lessons from the high-reliability flights of 2010, recognized an opportunity to push the boundaries of endurance. No longer content with missions measured in months or a few years, the focus shifted decisively toward extended-duration operations, marking a pivotal evolution in the program's lifecycle.\n\nThis pivot was not born of crisis but of confidence. The Cobalt-M satellites, with their proven avionics suites, radiation-hardened processors, and modular sensor payloads, had demonstrated resilience far beyond initial projections. Routine post-launch telemetry revealed that power subsystems—anchored by advanced gallium arsenide solar arrays and high-efficiency lithium-ion batteries—degraded at rates significantly lower than conservative models predicted. Attitude control systems, relying on precision reaction wheels and low-thrust xenon ion thrusters, maintained orbital stability with minimal propellant expenditure. These margins of excellence prompted a reevaluation of mission profiles. In early 2011, during a series of design review boards, engineers proposed and secured approval for a new paradigm: satellites engineered explicitly for multi-year persistence in their reconnaissance orbits, prioritizing longevity over rapid turnover.\n\nThe first manifestations of this evolution appeared in the spring launch window of that year. Subsequent Cobalt-M vehicles incorporated refined orbital insertion sequences that optimized for geosynchronous or highly elliptical paths conducive to prolonged station-keeping. Software updates, uploaded via secure ground links during ascent phases, enhanced autonomous health monitoring algorithms, allowing the satellites to dynamically adjust power allocation between imaging sensors—electro-optical and synthetic aperture radar arrays—and essential housekeeping functions. Thermal management systems received iterative upgrades, with multi-layer insulation blankets recalibrated for deep-space thermal cycling and cryogenic coolers for infrared detectors tuned for sustained efficiency. These changes were incremental yet cumulative, transforming what were once short-to-medium-lifespan assets into enduring sentinels capable of delivering persistent surveillance over high-value targets.\n\nOperationally, the shift reverberated through mission control centers. Ground teams, accustomed to planning for finite operational envelopes, now contended with timelines stretching into the indefinite future. Data downlink schedules expanded to accommodate voluminous archives from uninterrupted imaging passes, while predictive analytics models forecast propellant lifetimes and solar panel output over half-decade horizons. The intelligence consumers—military planners, policymakers, and allied partners—welcomed the boon of continuity; a single Cobalt-M could now maintain coverage continuity across seasons, weather anomalies, and geopolitical flashpoints without the vulnerabilities of launch gaps. This extended vigilance proved invaluable in monitoring dynamic theaters, where the cumulative value of longitudinal data sets eclipsed sporadic high-resolution snapshots.\n\nTechnically, the 2011 evolution hinged on several synergistic advancements. Redundant fault-tolerant computing architectures, evolved from earlier iterations, incorporated machine learning primitives to preemptively mitigate single-event upsets from cosmic radiation. Propulsion refinements minimized delta-V requirements for station-keeping maneuvers, preserving xenon reserves for orbit-raising corrections years into the mission. Sensor fusion algorithms matured, enabling the satellites to prioritize imaging tasks based on real-time threat assessments beamed from ground stations, thus conserving bandwidth and power for high-priority acquisitions. Calibration routines became self-sustaining, with onboard star trackers and laser retroreflectors facilitating autonomous boresighting without frequent human intervention. These features collectively elevated the Cobalt-M fleet from reliable workhorses to strategic mainstays.\n\nThe broader implications for the program were transformative. By mid-2011, as the first extended-duration missions settled into their orbits, performance metrics underscored the wisdom of the shift. Anomaly rates plummeted further, data return rates soared, and cost-per-imagery metrics improved dramatically due to amortized launch expenses over longer service lives. This evolution also influenced upstream procurement, with contracts for subsequent blocks emphasizing radiation-tolerant components and long-life cryocoolers from the outset. Within the space operations community, the Cobalt-M's 2011 achievements became a benchmark, inspiring parallel programs to pursue similar endurance goals. Yet, this ambition was tempered by vigilance; ground teams instituted rigorous long-term trending analyses to guard against insidious degradation modes, such as micrometeoroid impacts or gradual charge-trapping in solar cells.\n\nIn retrospect, 2011 stands as the inflection point where the Cobalt-M program transcended its origins as a responsive reconnaissance capability, emerging as a paragon of sustained space domain awareness. The routine reliability of prior years provided the foundation; the extended missions of 2011 built the legacy. As these satellites orbited on, their silent vigil exemplified how incremental engineering triumphs could redefine operational horizons, setting the stage for even more audacious evolutions in the years ahead.\n\nThe Summer 2011 deployment marked a pivotal moment in the Cobalt-M program's evolution, exemplifying the strategic pivot toward extended mission durations that had begun to reshape operational doctrines earlier that year. As analysts pored over telemetry from prior satellites, which had demonstrated unexpectedly robust endurance in their orbital environments, Russian space command authorized a launch cadence adjustment aimed at maximizing return on investment for these sophisticated reconnaissance assets. This deployment, shrouded in the usual veil of secrecy typical of military space operations from Plesetsk Cosmodrome, promised not only to sustain coverage over high-priority regions but also to test the limits of the platform's longevity in a highly elliptical orbit designed for persistent surveillance.\n\nPreparations for the mission unfolded with meticulous precision throughout the spring, drawing on lessons from the iterative refinements of the Cobalt series since its inception in 2004. Engineers at the Khrunichev State Research and Production Space Center fine-tuned the payload integration, ensuring compatibility with the proven Soyuz-2-1v launch vehicle, a workhorse tailored for polar orbits from Russia's northern launch site. The satellite, designated under the international Kosmos series to maintain operational ambiguity, incorporated enhanced solar arrays and radiation-hardened electronics that hinted at the program's ambition for multi-year service lives, a stark departure from the shorter-duration profiles of earlier iterations. Ground crews conducted exhaustive simulations, factoring in solar weather forecasts and geomagnetic influences that could impact ascent and early orbit phases, all while coordinating with tracking stations across the former Soviet expanse.\n\n***The launch date for Kosmos 2472 arrived on 27 June 2011***, under clear Arctic skies that favored a flawless liftoff at precisely 10:29 Moscow time. The Soyuz-2-1v roared skyward from Plesetsk's Site 43 pad, its RD-191 first-stage engine igniting with a thunderous plume that echoed across the tundra, propelling the stack toward the initial suborbital trajectory. Separation events proceeded nominally: the boosters jettisoned at T+118 seconds, the core stage at T+285, and the Fregat upper stage igniting shortly thereafter to circularize the orbit. This sequence, honed through dozens of prior missions, underscored the reliability of the Russian federated launch architecture, which had evolved to support an array of intelligence-gathering payloads without the fanfare of civilian spectacles.\n\nOrbital insertion accuracy stood out as a hallmark of this deployment, with post-launch assessments confirming placement within a tight envelope of the targeted 800-by-40,000-kilometer Molniya-like path optimized for northern hemisphere lingers. Independent verification from U.S. Space Command and Norwegian tracking sites corroborated the precision, noting deviations of mere meters per second in velocity—an achievement attributable to the Fregat's hydrazine thrusters and onboard star trackers. This exactitude minimized the delta-V demands on the satellite's own propulsion system, preserving propellant for station-keeping and potential orbit-raising maneuvers essential to the extended timeline strategy. Early orbital parameters revealed an inclination of 62.9 degrees, ideal for repeated passes over Eurasia and the Pacific theater, where Cobalt-M's synthetic aperture radar and electro-optical sensors could deliver high-resolution intelligence amid contested environments.\n\nInitial tracking data, relayed through the Krona and Okno radar complexes, painted an encouraging picture of spacecraft health from the first ground passes over Komsomolsk-on-Amur. Telemetry bursts indicated full deployment of the articulated solar wings and antenna booms within 45 minutes of separation, with attitude control thrusters firing nominal pulses to achieve three-axis stabilization. Power budgets exceeded projections, courtesy of the gallium arsenide cells that thrived in the high-radiation belts, while thermal systems maintained payloads within operational envelopes despite the June solstice's intense solar beta angles. Spectral analysis from S-band downlinks showed no anomalies in the command receiver or data encoder, signaling readiness for the phased array activation that would soon commence electro-optical mapping campaigns.\n\nThis deployment's success reverberated through the Cobalt-M operational cadre, validating the 2011 doctrinal shift as ground controllers initiated the checkout sequence over subsequent weeks. Unlike predecessors constrained by power degradation or component fatigue within 18 months, Kosmos 2472's architecture—bolstered by redundant avionics buses and autonomous fault detection—positioned it for a projected lifespan pushing toward three years or beyond. Analysts noted subtle tweaks in the orbit maintenance profile, with perigee-raising burns spaced to counter atmospheric drag more efficiently, a technique refined from ground-based modeling. As summer progressed into the relentless northern daylight, the satellite's first imagery products began flowing to end users at Yasny and other bunkered facilities, capturing dynamic maritime activities in the Sea of Okhotsk and subtle infrastructure shifts along border regions.\n\nThe broader implications for the program's trajectory were profound, as this launch encapsulated the maturation of Russia's post-Soviet space reconnaissance enterprise. By leveraging incremental hardware evolutions—such as improved cryogenic coolers for infrared detection and AI-augmented signal processing—the Cobalt-M lineage was transitioning from tactical responders to strategic sentinels. International observers, monitoring via optical telescopes from Maui and Diego Garcia, registered the satellite's signature maneuvers, including a subtle plane change that refined its ground track for optimal revisit rates. Yet, beneath the technical triumph lay the unyielding calculus of space domain awareness: each precise insertion like this one fortified Moscow's informational edge, extending the gaze of its orbital fleet into an era of protracted peer competition. As tracking networks logged hundreds of passes through the fall, Kosmos 2472 emerged not merely as a milestone but as a harbinger of the endurance-focused deployments that would define the program's next phase.\n\nWith the orbital insertion of Kosmos 2472 confirmed to within meters of its planned trajectory in late June 2011, and initial tracking data streaming reliably from ground stations across the Northern Hemisphere, attention swiftly shifted from launch dynamics to the satellite's long-term viability in the harsh environment of low Earth orbit. This Cobalt-M platform, the latest iteration in a series that had steadily pushed the boundaries of reconnaissance endurance since the program's inception in 2004, was poised to demonstrate not just functionality but exceptional persistence. Previous missions in the lineage, such as those launched in the mid-2000s, had typically adhered to shorter operational timelines constrained by fuel budgets, solar panel degradation projections, and the cumulative toll of micrometeoroid impacts and atomic oxygen erosion on orbit. Kosmos 2472, however, benefited from refined avionics, enhanced thermal coatings, and more efficient ion thrusters, setting the stage for a mission that would eclipse its predecessors in duration and data return.\n\n***The baseline operational plan for Kosmos 2472 envisioned a primary mission phase lasting 85 days.*** This figure was derived from meticulous pre-launch simulations that accounted for the satellite's 500-kilogram hydrazine propellant load, optimized for station-keeping maneuvers to maintain its sun-synchronous orbit at around 650 kilometers altitude. Engineers at the TsNIIMash mission control center had calibrated this duration to balance high-resolution electro-optical imaging passes over priority targets—denied areas in Asia and the Middle East—with periodic battery recharges and antenna realignments for downlink bursts. The plan included three distinct phases: an initial shakedown period for sensor calibration, a core imaging campaign, and a terminal deorbit sequence to ensure compliance with international space debris mitigation guidelines. Early post-insertion telemetry painted an optimistic picture, with solar arrays deploying flawlessly and generating 1.2 kilowatts of power under full illumination, far exceeding the minimum thresholds for sustained operations.\n\nYet, as the first week of orbit unfolded, a subtle anomaly emerged in the propulsion subsystem. ***A minor propulsion glitch during early orbit operations prompted a reduction of the planned duration by 6 days, adjusting the target to 79 days.*** Specifically, a transient pressure irregularity in one of the attitude control thrusters—likely triggered by a microscopic impurity in the fuel line—manifested as a 2 percent deviation in delta-V during a routine yaw maneuver. Ground teams responded with characteristic precision, isolating the affected valve through redundant diagnostics and implementing a software patch that rerouted flow through backup nozzles. This incident, while not mission-threatening, necessitated conservative fuel budgeting to preserve margins for later corrections. The adjustment to 79 days reflected a prudent recalibration: subtracting those 6 days ensured that remaining propellant reserves could still support the essential orbital plane maintenance against atmospheric drag, which at this altitude exerted a gradual decay force of approximately 50 meters per day without intervention. Publicly, Russian space authorities downplayed the event as routine housekeeping, but internal logs reveal it as a pivotal moment that tested the Cobalt-M's fault-tolerant architecture, ultimately reinforcing confidence in its robustness.\n\nAs weeks progressed into the core operational regime, the satellite's performance metrics exceeded expectations across multiple fronts. High-resolution cameras, operating in visible and infrared spectra, captured thousands of frames daily, relaying terabytes of imagery on strategic infrastructure, naval movements, and transient military deployments. The propulsion hiccup faded into insignificance against this backdrop, and mission planners began contemplating extensions. The Cobalt-M series had evolved precisely to enable such flexibility; earlier variants like Kosmos 2420 had been curtailed by battery cycle fatigue after barely two months, but iterative upgrades in lithium-ion cells and radiation-hardened electronics now promised greater longevity. With propellant gauges reading 15 percent above projections and no degradation in the star trackers essential for precise pointing, the green light was given for an ambitious prolongation.\n\n***This extension added 25 days to the adjusted 79-day target, specifically to accommodate enhanced Earth observation tasks.*** These additional passes prioritized time-critical reconnaissance over high-value targets, including expanded coverage of littoral zones and rapid revisit cycles for dynamic events like troop concentrations. The decision cascaded through a rigorous review process: orbital analysts modeled drag perturbations using real-time atmospheric density data from the U.S. Space Surveillance Network (monitored via passive collection), confirming that the extra maneuvers remained within fuel envelopes. Onboard data processors, upgraded with field-programmable gate arrays, handled the increased imaging volume without thermal runaway, while cryogenic coolers for infrared sensors maintained sub-100 Kelvin temperatures despite prolonged solar beta angles. This phase not only amplified the mission's intelligence yield—estimated at 40 percent above baseline—but also validated the Cobalt-M's scalability for future deep-space derivatives. Ground crews celebrated the milestone with a classified briefing, noting how the extension transformed a standard mission into a benchmark for endurance.\n\nThe momentum of success built further as autumn approached, with Kosmos 2472 navigating the equinox transition flawlessly. Solar activity remained low, minimizing geomagnetic storms that could disrupt command links, and the satellite's Whipple shields deflected several millimeter-sized debris particles without telemetry interruptions. By this point, cumulative data downlink had surpassed 10 petabytes, compressed via wavelet algorithms and beamed to S-band receivers in Kaliningrad. Planners, ever mindful of the program's evolution toward multi-year capabilities by the mid-2010s, saw an opportunity to push limits one step more. The original constraints—rooted in conservative reentry predictions to avoid uncontrolled decay over populated regions—yielded to empirical evidence of superior health.\n\n***The mission was then further prolonged by 15 days to maximize data yield before initiating safe reentry procedures.*** This final stretch focused on archival imaging of seasonal changes in agricultural heartlands and persistent surveillance of launch sites, squeezing every possible orbit from the aging but resilient platform. Thruster firings for deorbit were pre-staged, plotting a retrograde burn sequence to target the Pacific Ocean impact ellipse, in line with the Inter-Agency Space Debris Coordination Committee standards. As the terminal days counted down, cross-checks with international trackers confirmed the satellite's position to arc-second accuracy, a testament to the ground segment's integration with GLONASS augmentation.\n\nIn retrospect, Kosmos 2472's journey from launch pad to fiery reentry encapsulated the Cobalt-M program's maturation. What began as a meticulously planned endeavor evolved through adaptive decision-making, turning potential setbacks into triumphs of engineering foresight. This mission's protracted timeline, deduced from the sequential adjustments—starting at 85 days, trimmed to 79, bolstered by the 25-day extension to the adjusted target, and capped with the further 15-day prolongation—marked a watershed, more than doubling the effective endurance of inaugural flights and paving the way for subsequent satellites like Kosmos 2495. It underscored the Russian space agency's commitment to iterative refinement: better materials, smarter autonomy, and bolder operational envelopes. For the intelligence community, the payoff was invaluable—a sustained orbital sentinel that redefined reconnaissance persistence in an era of proliferating threats. As debris sensors registered the final thruster pulse and the heat shield engaged, Kosmos 2472 retired not as a spent asset, but as a legend in the annals of orbital endurance.\n\nAs the Cobalt-M program's most ambitious flight to date drew toward its conclusion, mission controllers at the Plesetsk Cosmodrome and associated ground stations turned their focus to the intricate choreography of recovery operations. With a deployment of 119 days exceeding the typical operational envelopes of earlier satellites in the series, Kosmos 2472 had amply demonstrated the platform's robustness in orbit, collecting high-resolution imagery and signals intelligence across diverse targets from its sun-synchronous path. The mission not only validated enhancements in thermal management, power subsystems, and attitude control but also provided invaluable data on material degradation under prolonged exposure to the space environment, setting the stage for future iterations.\n\nRecovery planning commenced months in advance, with preliminary projections centering on an ambitious mid-October reentry to capitalize on favorable atmospheric conditions and ground recovery assets positioned in the vast steppes of Kazakhstan. Initial assessments pegged ***17 October 2011*** as the optimal landing window, accounting for fuel reserves, orbital decay rates, and real-time adjustments to perigee. These estimates evolved as telemetry revealed slightly higher-than-expected drag coefficients from upper atmospheric expansion, prompting a refined timeline that prioritized precision over haste.\n\nBy early October, the flight dynamics team finalized the deorbit maneuver, scheduling the critical burn for ***22 October 2011*** to initiate controlled descent. This sequence adhered closely to the earlier projection of ***17 October 2011***, adjusted for conservative propellant margins and contingency buffers against solar activity fluctuations. Ground teams mobilized recovery forces, including Mi-8 helicopters, Il-76 transports, and specialized Kosmospas teams equipped with radiation detectors and bio-containment protocols, staging from forward bases near the Aral Sea to cover the predicted footprint.\n\nThe deorbit burn executed flawlessly on ***22 October 2011***, firing the retro-rockets for approximately 400 seconds to lower perigee into the denser atmosphere, transforming the satellite's stable orbit into a steep reentry trajectory. Over the subsequent 48 hours, Kosmos 2472 encountered escalating frictional heating, its ablative heat shield glowing plasma-bright as it skipped through the mesosphere. Real-time tracking via S-band radars at Balkhash and Kamchatka confirmed the capsule's stability, with onboard beacons pulsing health data amid the fiery plunge.\n\n***The satellite finally landed on 24 October 2011***, touching down intact in a predetermined zone amid the windswept plains, mere kilometers from the primary recovery grid. Search teams, vectored by GPS uplinks from the capsule's emergency locator transmitter, reached the site within hours, greeted by a parachute-shrouded pod exhibiting only superficial charring and minor attitude thruster scorching. Post-landing inspections revealed the film return canister pristine, yielding terabytes of unencrypted reconnaissance data—crisp electro-optical panchromatic images, infrared multispectral scans, and sidelooking radar maps that would fuel Russian military assessments for months.\n\nThe Autumn 2011 recovery marked a watershed for the Cobalt-M lineage, unequivocally proving the platform's aptitude for missions of 119 days, surpassing the 60-90 day norms of predecessors like the Yantar series. Engineering analyses of the returned hardware illuminated pathways for next-generation upgrades, including reinforced solar arrays and advanced attitude gyros, while operational lessons refined deorbit sequencing for enhanced accuracy. This triumph not only bolstered confidence in extended reconnaissance deployments but also underscored the program's strategic edge in an era of proliferating imaging constellations, paving the way for bolder Cobalt-M evolutions through the mid-2010s.\n\nThe 2012 Mission Cycle\n\nWith the Cobalt-M platform safely recovered in October 2011 after an extended deployment that shattered expectations for endurance and reusability, the program entered a phase of unprecedented operational maturity. The engineering teams at the primary integration facility wasted little time in turning the spacecraft around. Post-mission inspections revealed minimal wear on the critical landing systems—thermal protection layers showed only superficial ablation, hydraulic struts maintained near-perfect pressure retention, and the precision guidance avionics logged no faults beyond routine calibration drifts. This robustness validated years of iterative design refinements, from the hypersonic reentry vehicle's composite heatshield to the autonomous runway alignment algorithms honed through wind tunnel simulations and suborbital drop tests. Following a streamlined refurbishment cycle that incorporated upgraded sensor payloads and enhanced cryogenic fuel cells, Cobalt-M was prepped for relaunch aboard a heavy-lift booster from Vandenberg Space Launch Complex.\n\nThe ascent marked the commencement of the 2012 mission cycle, a meticulously planned orbital mission designed to capitalize on the platform's proven longevity. Initial checkout maneuvers confirmed full functionality across all subsystems: the electro-optical imagers achieved nadir resolution well beyond declassified benchmarks, synthetic aperture radar swept vast swaths of terrain with phase-coherent precision, and signals intelligence antennas locked onto elusive emission profiles from the outset. Orbit insertion into a sun-synchronous polar trajectory at approximately 500 kilometers altitude optimized revisit rates over high-priority theaters, allowing for persistent surveillance of dynamic conflict zones, proliferation activities, and maritime chokepoints. What distinguished this cycle from prior efforts was its seamless rhythm—departure from the pad, orbital handoff to mission control, and the inexorable march toward nominal data collection unfolded with the predictability of a well-rehearsed symphony.\n\nRoutine intelligence gathering dominated the first quarter, as Cobalt-M methodically prosecuted its tasking list. Operators at the distributed ground stations prioritized real-time tasking for time-sensitive targets, leveraging the satellite's agile pointing capabilities to slew between collection windows with minimal slew losses. Infrared sensors captured heat signatures from mobile launchers in arid expanses, while multispectral imagers dissected urban infrastructures for subtle indicators of regime instability. The landing systems, often the Achilles' heel in earlier prototypes, faded into the background as reliable workhorses; periodic deorbit rehearsals—dry runs that simulated reentry profiles without commitment—verified parachute deployment sequences and GPS-aided touchdown logic flawlessly. This confidence allowed mission planners to extend dwell times over high-value targets.\n\nSpring brought a subtle escalation in operational tempo, as geopolitical tensions prompted ad hoc retasking. Cobalt-M's endurance shone through extended blackouts over denied areas, where it loitered in safe modes to evade counter-space threats while relaying buffered hyperspectral data via laser crosslinks to relay constellations. The routine nature of these maneuvers belied their complexity: autonomous attitude control systems juggled momentum wheel desaturation with thruster firings, all while the primary payload bus churned through terabytes of raw imagery, compressing and encrypting it for downlink bursts during low-elevation passes over secure uplinks. Ground crews monitored propellant margins with hawk-like vigilance, but the bipropellant main engine and cold-gas attitude jets showed no signs of degradation, a testament to the materials science advances in ablative liners and additive-manufactured injectors.\n\nBy summer, the mission had settled into a cadence of sustained high-tempo operations, underscoring the landing gear's continued reliability through rigorous deorbit rehearsals amid challenging orbital dynamics. Ground teams prepared for eventual recovery, confirming zero anomalies in simulated landing profiles, with crosswinds factored into autonomous touchdown algorithms.\n\nThroughout these evolutions, the intelligence yield was prodigious and routine in equal measure. Cobalt-M's fusion of staring focal plane arrays and agile gimbal turrets enabled stereoscopic mapping of transient phenomena, from convoy routings across porous borders to naval transshipments in contested littorals. Analysts downstream praised the platform's low-latency data pipeline, which bypassed traditional film-return bottlenecks to deliver near-real-time battle damage assessments and order-of-battle updates. Even as the mission cycle wound down with a final landing ***on 24 September 2012***—buffeted by strong jet streams yet arresting with pinpoint accuracy—the Cobalt-M program had transformed reconnaissance from episodic forays into a sustained, recoverable enterprise. The 2012 operations not only affirmed the landing systems' ironclad dependability but also normalized an intelligence-gathering paradigm where endurance and repeatability supplanted one-off heroics, setting the stage for even more ambitious cycles ahead.\n\nLanding Operations 2012\n\nAs the Cobalt-M program's 2012 mission progressed into its final phases, the operational tempo shifted seamlessly from the steady rhythm of orbital reconnaissance to the meticulously orchestrated ballet of descent and recovery. Kosmos 2480, the designated spacecraft for this cycle, had embodied the maturing reliability of the platform, delivering high-fidelity intelligence on strategic targets across contested regions without the glitches that had occasionally plagued earlier iterations. Ground controllers at the Plesetsk Cosmodrome's mission support center monitored telemetry with the quiet confidence born of repetition, their screens alive with projections of atmospheric reentry corridors refined over years of iterative testing. The descent module, a compact marvel of ablative heat shielding and precision parachutes, carried petabytes of encrypted imagery and signals intelligence—payloads that promised to sharpen Russia's geopolitical edge in an era of escalating hybrid threats.\n\nPreparation for landing commenced weeks in advance, with retro-rocket burns fine-tuning the orbit to align with the primary recovery zone in the vast steppes of Kazakhstan. This arid expanse, crisscrossed by recovery teams in rugged GAZ Tigr vehicles and Mi-8 helicopters, had become the program's de facto proving ground, its forgiving terrain ideal for post-landing retrievals. Engineers cross-checked barometric sensors and GPS beacons embedded in the module, ensuring redundancy against the capricious winds that could scatter debris across hundreds of kilometers. Unlike the high-drama recoveries of the program's infancy, where optical trackers strained against dust storms, 2012's operations leaned on automated sequencing: a deorbit burn at perigee, followed by a skip reentry to bleed off velocity, culminating in main chute deployment at 5 kilometers altitude. The routine nature of these maneuvers underscored Cobalt-M's evolution from experimental outlier to workhorse asset, with failure probabilities now hovering in the sub-one-percent realm through hardened avionics and real-time anomaly detection.\n\n***The climax arrived six days before the month's end on September 30, 2012, as Kosmos 2480's descent module touched down flawlessly in the designated ellipse, its beacon pulsing triumphantly amid the golden hues of a late-autumn dawn.*** This precisely timed culmination—neither rushed nor delayed—reflected the mission planners' mastery of orbital mechanics, where every second of thrust vectoring shaved precious distance from potential overshoot risks. Recovery crews, prepositioned since the penultimate orbit, converged within minutes, their thermal imagers piercing any lingering dust to locate the cylindrical module nestled in a shallow crater. The air buzzed with the thrum of rotors as helicopters ferried technicians to the site, where they methodically disarmed pyrotechnics and extracted the data core, cocooned in shock-absorbing foam to preserve its fragile reels of high-resolution film and solid-state drives.\n\nPost-recovery protocols unfolded with textbook efficiency, a testament to the interoperability honed between Roscosmos specialists and military intelligence handlers. The module was airlifted to a secure staging area at Baikonur, where initial integrity checks confirmed zero breaches in the pressure vessel—no salt corrosion from an unlikely splashdown, no impact fractures from uneven terrain. Data offload began under armed guard, with fiber-optic tethers streaming contents to hardened servers for decryption and preliminary analysis. Spectral imaging from the module's primary sensor revealed urban sprawl patterns in denied-access zones, while electronic intercept arrays yielded troves of unencrypted communications—insights that fed directly into Kremlin briefings on NATO maneuvers and Asian proxy conflicts. This haul, richer in volume than the prior year's return, validated the Cobalt-M's upgraded optics, which now pierced cloud cover with synthetic aperture radar overlays.\n\nThe success of Kosmos 2480's landing ripple through the program writ large, reinforcing the landing system's pedigree as the linchpin of operational sustainability. With reentry vehicles consistently achieving 99 percent recovery rates, planners could now allocate resources toward next-generation payloads rather than remedial hardware fixes. Anecdotal accounts from recovery veterans spoke of a newfound complacency—not complacency in execution, but in expectation—where once-tense countdowns had mellowed into procedural recitations. Yet beneath this veneer lay the unyielding rigor of post-mission deconstructions: wind tunnel recreations of the descent profile, metallurgical autopsies of heat shield charring, and algorithmic audits of parachute bloom timings. These efforts, documented in classified addendums to the master operations log, propelled incremental tweaks—like enhanced GPS jamming resistance—for the 2013 cycle.\n\nIn retrospect, the 2012 landing operations encapsulated Cobalt-M's transitional poise: a bridge from the raw pioneering of the mid-2000s to the hardened maturity of the program's zenith. Each recovered module not only repatriated intelligence but also cycled back engineering lessons, fueling a virtuous loop of refinement. As the dust settled over Kazakhstan's plains that crisp September evening, the program's custodians turned their gaze upward once more, plotting the next launch window with the assuredness of a system that had tamed the perils of reentry. Kosmos 2480's touchdown, unheralded in open sources but pivotal in closed circles, marked yet another data return triumph, sustaining the satellite's role as an unseen sentinel in the shadowed arenas of global power projection.\n\nFollowing the triumphant recovery of the descent module in September 2012, which returned a trove of high-fidelity imagery from orbit, the Cobalt-M program stood at a pivotal juncture of technological maturation by 2013. Over nearly a decade of iterative launches and operational refinements since its inception in 2004, the system had evolved from a promising prototype constellation into a robust, battle-tested reconnaissance architecture. This maturation was not marked by revolutionary leaps but by the steady accumulation of engineering insights—subtle yet profound enhancements that elevated reliability, endurance, and data yield to levels that rivaled the most advanced photoreconnaissance platforms of the era.\n\nCentral to this progress were incremental improvements in film capacity, which transformed the payload's imaging potential. Early Cobalt-M missions grappled with the inherent trade-offs of analog film systems: limited canister volumes constrained the number of exposures, while orbital dynamics demanded efficient use of every frame. By 2013, refinements in emulsion chemistry and spooling mechanisms allowed for denser packing of high-resolution panchromatic and multispectral films. These advances meant satellites could sustain prolonged imaging campaigns over priority targets—denied areas, mobile launchers, and fleeting naval maneuvers—without the frequent interruptions that plagued predecessors. The result was a marked increase in the volume of actionable intelligence per mission, with film magazines now optimized to capture finer granular details across expansive theaters, from arid test ranges to fog-shrouded coastlines. Engineers had mastered the alchemy of balancing film speed, granularity, and spectral sensitivity, ensuring that even low-light passes yielded crisp, interpretable results that ground stations could process with minimal latency.\n\nEqually critical was the maturation of the return capsule itself, whose reliability had ascended from a point of occasional vulnerability to near-flawless execution. Initial descent modules contended with the brutal gauntlet of reentry: ablative heat shields that sometimes frayed under peak plasma flows, parachutes prone to partial deployments in variable winds, and beacons that faltered amid recovery zone clutter. By 2013, a series of post-flight teardowns and wind-tunnel validations had yielded layered upgrades. Heat shield compositions incorporated advanced phenolics with embedded insulators, distributing thermal loads more evenly and reducing mass to permit larger film payloads. Parachute clusters were redesigned with reefing stages for precise descent profiles, adapting to altitudes from 10 to 40 kilometers. Locator systems integrated redundant GPS-derived beacons with infrared strobes, ensuring recovery teams could home in on capsules splashing down in the vast Pacific or nestled in remote steppes. Mission after mission, these capsules returned intact, their film vaults pristine, underscoring a recovery success rate that reflected the program's institutional memory—lessons from each splashdown feeding directly into the next build.\n\nThis dual maturation of film and capsule was underpinned by broader systemic hardening. The satellite bus, once susceptible to radiation-induced glitches in the South Atlantic Anomaly, now featured shielded avionics with error-correcting memory and autonomous attitude recovery routines. Power subsystems, drawing from gallium arsenide solar arrays, sustained attitude control thrusters through extended missions, often exceeding baseline lifetimes by margins that astonished launch crews. Ground segment integration had also ripened: forward-deployed processing labs employed automated emulsion developers and stereoscopic plotters, slashing the time from canister crack to photo interpreter desks. Orbital mechanics software, honed by years of ephemeris data, predicted deorbit windows with pinpoint accuracy, minimizing fuel dumps and maximizing film utilization.\n\nBy 2013, these evolutions coalesced into a technology ecosystem of exquisite balance—analog purity wedded to digital-age precision. The Cobalt-M constellation, now numbering several operational assets in staggered low-Earth orbits, delivered persistent stares over hotspots with a cadence and fidelity that outstripped digital imaging rivals hampered by downlink bottlenecks. Operators marveled at the system's resilience: mid-mission anomalies, such as primary gyro tumbles, were rectified by star-tracker handoff without data loss. Such vignettes epitomized the maturation: not invincible, but improbably dependable, a testament to the unsung grind of systems engineers who iterated through telemetry logs night after night.\n\nIn retrospective analysis, 2013 marked the apogee of Cobalt-M's analog reconnaissance paradigm, just as digital transitions loomed on the horizon. The program's technological poise enabled policymakers to pivot from reactive tasking to anticipatory collection strategies, with film returns informing everything from treaty verification to counterproliferation ops. Yet this maturity carried a poignant undercurrent—a swan song for film-based spying, whose tactile, high-fidelity allure had been refined to perfection amid whispers of obsolescence. The capsules returned through these years were more than hardware; they were artifacts of a lineage where human ingenuity had coaxed extraordinary performance from photochemical roots, setting a benchmark for space operations chronicles to come.\n\nThe 2014 Launch Campaign\n\nAs the Cobalt-M program crossed into 2014, the technological refinements achieved by the close of the previous year—particularly the boosted film capacity and hardened return capsule designs—set the stage for what would become a pivotal operational milestone. Engineers and mission planners at the program's core facilities shifted seamlessly from protracted development phases into the high-stakes rhythm of a full-scale launch campaign. This period, spanning the crisp early spring months, embodied the culmination of over a decade's evolution in film-based reconnaissance satellite architecture, with teams meticulously orchestrating every facet from payload assembly to orbital insertion. The Cobalt-M, designated under the Kosmos series for operational security, promised enhanced imaging resolution and endurance, tailored for persistent surveillance over dynamic geopolitical hotspots. Mission parameters emphasized a sun-synchronous orbit optimized for high-latitude coverage, repeated passes over priority targets, and the deployment of multiple reentry capsules to ferry exposed film back to Earth, ensuring a steady data return cycle unhindered by real-time downlink vulnerabilities.\n\nPreparations accelerated through the winter thaw, building on the maturity of subsystems proven in ground simulations and prior incremental tests. A critical suborbital test flight, validating the Fregat upper stage's performance under Cobalt-M mass configurations, lifted off on 12 March 2014 from the Plesetsk Cosmodrome, providing vital data on propulsion margins and separation dynamics just weeks ahead of payload mating. With that green light, integration specialists advanced to the payload encapsulation phase, securing the satellite bus, optics module, and film magazines atop the adapted Soyuz-2.1v vehicle by the ***payload integration date of 20 April 2014***. This step, shrouded in the controlled frenzy of cleanroom protocols, marked the birth of Kosmos 2495 as a fully assembled flight unit, its reconnaissance payload now irrevocably committed to the rigors of spaceflight.\n\nGround campaigns intensified thereafter, with fueling operations, avionics health checks, and range safety verifications compressing into a final sprint. By 30 April 2014, the stack stood fully erect on Launch Complex 43/4 at Plesetsk, bathed in the pale northern sunlight, as technicians sealed hatches and evacuated the service tower amid a cascade of go/no-go polls rippling up the chain of command. The initial planned launch window had been set for 1 May 2014, aligning with favorable orbital insertion slots and seasonal lighting conditions for post-launch tracking, but a minor anomaly in the Fregat stage's attitude control thruster telemetry prompted a prudent 72-hour scrub and regression testing. These adjustments, commonplace in the unforgiving ballet of human spaceflight, ensured no latent risks propagated into ascent. Thus, under clear skies and with synchronized clocks across Moscow, Plesetsk, and remote telemetry stations, the ***actual launch date for Kosmos 2495 was 6 May 2014***.\n\nLiftoff at 14:24 UTC propelled the 2,800-kilogram stack skyward on a pillar of RP-1 and liquid oxygen flames, the Soyuz core stage thundering through max-Q before separation at T+118 seconds revealed the boosters' fiery divergence against the Arctic horizon. The orbital unit, comprising the Fregat and Cobalt-M payload, executed flawlessly: three burns over the subsequent hours circularized the satellite into its primary mission orbit, a near-polar inclination tuned for global revisit rates exceeding those of legacy Yantar-class predecessors. Telemetry confirmed nominal deployment of solar arrays, attitude initialization via star trackers, and the unfurling of the primary electro-optical suite, all within minutes of separation. Kosmos 2495's expected operational lifespan was calibrated for at least 18 months, punctuated by four to six film canister ejections, each timed to exploit atmospheric reentry corridors over the Eurasian landmass for recovery by specialized aircraft and parachute teams.\n\nThe campaign's success reverberated through the Russian space apparatus, validating Cobalt-M's evolutionary leap amid a landscape of international scrutiny over reconnaissance capabilities. On-orbit checkouts through late May affirmed imaging chains, thermal stability, and capsule jettison mechanisms, with the first film return slated for early autumn to capture peak seasonal contrasts. This launch not only anchored the program's shift from prototyping to serial production but also underscored the resilience of analog film return in an era dominated by digital constellations, where electromagnetic denial threats loomed large. Analysts pored over initial status reports, noting the satellite's aptitude for sub-meter resolution over contested maritime zones and transient ground maneuvers, setting a benchmark for subsequent missions in the 2015 cadence. In the annals of post-Cold War space reconnaissance, the 2014 campaign stood as a testament to iterative mastery, where each spring date in the timeline—from March trials to May ignition—wove into a tapestry of precision and perseverance.\n\nAs the Cobalt-M satellite achieved its initial orbit in early May 2014, hurtling into the strategic void above Earth at over 7 kilometers per second, it did so against a backdrop of unprecedented geopolitical turbulence that placed extraordinary demands on reconnaissance capabilities. The world of 2014-2015 was one of rapid unraveling alliances, proxy conflicts, and assertive power plays, where real-time, high-resolution imagery from space had become not just an asset but a necessity for decision-makers navigating crises that could escalate into broader confrontations. Traditional intelligence gathering—human sources, signals intercepts, and ground-based sensors—proved insufficient in an era of blurred battle lines, hybrid warfare, and non-state actors wielding sophisticated tactics, thrusting overhead reconnaissance platforms like Cobalt-M into the forefront of national security operations.\n\nThe most immediate flashpoint was Europe's eastern flank, where Russia's annexation of Crimea in March 2014 marked the first forcible alteration of post-Cold War borders, sending shockwaves through NATO and igniting the Donbas conflict in eastern Ukraine. What began as pro-Russian separatist unrest quickly evolved into a grinding war of attrition, with Moscow's \"little green men\"—deniable special forces—blending seamlessly with irregular militias. Western intelligence agencies scrambled to monitor troop buildups along the 2,000-kilometer Russian-Ukrainian border, track unmarked convoys ferrying heavy armor into separatist-held territories like Donetsk and Luhansk, and verify claims of foreign intervention. Cobalt-M's multispectral imaging, capable of distinguishing between T-72 tanks and civilian tractors under camouflage netting, provided critical corroboration amid a fog of disinformation. By late 2014, as the Minsk Protocol faltered and fighting intensified around Debaltseve, the satellite's data fed directly into U.S. and allied assessments, helping to calibrate sanctions, bolster NATO's Rapid Reaction Force deployments in the Baltic states, and deter further incursions without triggering Article 5.\n\nSimultaneously, the Middle East descended into a maelstrom of jihadist expansion that redefined global counterterrorism priorities. The Islamic State's lightning conquests across Iraq and Syria—capturing Mosul in June 2014 and declaring a caliphate—exposed the fragility of post-Arab Spring order. ISIS's mastery of mobile warfare, with Toyota-mounted fighters evading fixed defenses and foreign fighters streaming in from Europe and beyond, demanded persistent overhead surveillance to map their sprawling oil smuggling networks, training camps in the Syrian desert, and beheading sites used for propaganda. Cobalt-M's infrared and synthetic aperture radar modes pierced dust storms and night skies, revealing convoy routes from Raqqa to the Turkish border and hidden stockpiles of captured U.S. weaponry. This intelligence underpinned the U.S.-led Operation Inherent Resolve, launched in August 2014 with airstrikes that relied on satellite-derived targeting to minimize civilian casualties in urban sprawls like Fallujah. As the year turned to 2015, with ISIS pushing toward Baghdad and Kurdish peshmerga forces mounting counteroffensives, the satellite's role expanded to track Iranian-backed Shia militias flooding into Iraq, complicating the sectarian mosaic and fueling fears of a broader regional war.\n\nBeyond these theaters, Asia-Pacific tensions simmered with implications for global trade and nuclear stability. China's assertive island-building in the South China Sea—dredging reefs into militarized outposts on Fiery Cross and Mischief Reefs—prompted urgent monitoring of dredging operations, airstrip constructions, and PLAN naval deployments. Cobalt-M's high-resolution optics captured the transformation of coral atolls into forward bases, informing U.S. freedom-of-navigation operations and alliances with Japan, the Philippines, and Vietnam. North Korea's barrage of ballistic missile tests, including the KN-08 intermediate-range missile paraded in Pyongyang parades, heightened alarms over its uranium enrichment at Yongbyon and potential submarine-launched threats from the Sea of Japan. In parallel, Iran's nuclear brinkmanship—centrifuge expansions at Natanz and Fordow amid stalled P5+1 talks—necessitated vigilant tracking of dual-use shipments through Bandar Abbas and covert facility expansions, data that proved pivotal as the Joint Comprehensive Plan of Action negotiations gained momentum in 2015.\n\nThese converging crises amplified the imperative for reconnaissance satellites tuned for endurance and precision. Legacy systems strained under the volume of tasking requests, their aging orbits yielding to newer constellations, but Cobalt-M's deployment filled a vital gap with its extended lifespan projected through 2015 and beyond. Operational teams at the National Reconnaissance Office's ground stations faced round-the-clock prioritization dilemmas: balancing Ukraine's armored columns against ISIS's desert raiders, or Chinese dredgers versus DPRK rocket launches. The satellite's autonomous retargeting algorithms, refined from prior missions, allowed dynamic adjustments to shifting threats, while encrypted downlinks ensured data security amid cyber-espionage campaigns attributed to actors from Moscow to Beijing. In this high-stakes environment, the program's evolution underscored a broader truth: space reconnaissance had transitioned from Cold War snapshots to a continuous, indispensable pulse on the planet's fault lines, where a single image could avert escalation or expose deception on a global scale. As 2014 bled into 2015, Cobalt-M not only chronicled these events but embodied the technological edge required to maintain strategic equilibrium in an increasingly volatile world.\n\nAs the geopolitical landscape of 2014-2015 intensified demands for unparalleled reconnaissance coverage—spanning tense border skirmishes, naval maneuvers in contested waters, and the rapid militarization of remote regions—the Cobalt-M program reached its zenith and inevitable conclusion. Operators at mission control centers grappled with the imperative to sustain film-based intelligence gathering amid whispers of an impending technological shift, one that would render the analog era obsolete. It was against this backdrop of urgency and transition that the final Cobalt-M satellite ascended, marking not just the end of a production line but the closure of a storied chapter in Russia's space reconnaissance legacy.\n\n***Kosmos 2505 rocketed into orbit on the one hundred fifty-sixth day of 2015, kicking off its operational phase with the precision that had defined the series.*** Dispatched from the familiar pad at Plesetsk Cosmodrome aboard a reliable Soyuz-2.1v booster, this last-of-its-kind spacecraft embodied the culmination of over a decade's refinements in film-return reconnaissance. Technicians had meticulously calibrated its twin Peleng imaging systems, ensuring the high-resolution optics could capture vast swaths of terrain under varying light conditions, from the shadowed valleys of mountainous frontiers to the sun-glinted expanses of open seas. The mission profile called for an initial checkout period in low Earth orbit, where ground teams verified attitude control thrusters, solar array deployment, and the integrity of the reentry canister housing thousands of meters of unexposed film.\n\nThe significance of Kosmos 2505 extended far beyond its technical specifications; it represented the swan song of the Cobalt-M architecture, a hybrid of Cold War-era durability and post-Soviet incremental upgrades. Throughout its predecessors' runs—from the early Cobalt-M(1) variants with their basic panoramic cameras to the more sophisticated M(3) models boasting improved resolution and extended endurance—this series had delivered tangible intelligence payloads, with reentry capsules plummeting back to Earth at intervals to disgorge canisters scooped from the steppes by waiting Mi-8 helicopters. Yet by 2015, the tide had turned decisively toward digital electro-optical successors like the Persona and Lotos-S satellites, which promised real-time data streams unburdened by the logistical dance of physical film recovery. Kosmos 2505, therefore, operated under a poignant mandate: to bridge the gap, providing continuity in an era when adversaries moved faster than ever.\n\nIn the weeks following its insertion into a sun-synchronous orbit optimized for midday overpasses, the satellite commenced its primary imaging campaigns, prioritizing high-value targets identified through interagency tasking. Flight dynamics engineers monitored apogee and perigee perturbations with hawk-like vigilance, employing periodic orbital maneuvers fueled by hydrazine reserves to maintain imaging windows amid the clutter of space debris and adversarial counterspace threats. The ground segment, centered at the sprawling 40th Separate Command Post near Krasnoznamensk, processed initial metadata bursts via S-band links, confirming acquisition success rates that rivaled the program's historical peaks. Each pass yielded rolls of exposed film destined for chemical processing in secure labs, where emulsions revealed details invisible to digital proxies of the time—subtle terrain signatures, vehicle convoys in dust plumes, and infrastructure anomalies that shaped strategic assessments.\n\nAs the mission progressed into its nominal lifespan, the Cobalt-M team's reflections turned retrospective. This final launch encapsulated the program's evolutionary arc: born in 2004 amid post-perestroika fiscal constraints, it had weathered launcher failures, film recovery mishaps, and the relentless march of Moore's Law, all while delivering over a dozen operational assets. Kosmos 2505's endurance—projected to span months of vigilant surveillance—served as a testament to the robustness of vacuum-sealed mechanics and radiation-hardened electronics, even as younger digital platforms loomed on the horizon. Deorbit planning, triggered by propellant depletion or film exhaustion, would culminate in a controlled reentry, with the canister's parachute bloom signaling the definitive end of analog reconnaissance primacy.\n\nIn essence, the ascent of Kosmos 2505 on that pivotal day in 2015 did more than deploy hardware; it etched the Cobalt-M saga into the annals of space operations history. Operators, many of whom had shepherded the series from inception, watched telemetry streams with a mix of pride and melancholy, knowing this orbit would be the last to carry the weight of silver halide grains into the void. The transition to fully digital systems, already underway with prototype validations, heralded a new paradigm of persistent stare and automated analysis—but none could dispute that the Cobalt-M's tactile, proven methodology had fortified national security through an era of profound uncertainty. Thus, with its final frames captured and capsule recovered, the program yielded the stage, its legacy enduring in the declassified mission logs and the strategic decisions it informed.\n\nFollowing the successful launch of Kosmos 2505 on 5 June 2015, aboard a Soyuz-2.1v rocket from Plesetsk Cosmodrome, mission controllers at the Russian Space Forces' primary ground station shifted their focus from ascent dynamics to the delicate ballet of orbital inception. The Cobalt-M satellite, the culminating jewel in a lineage that had spanned over a decade of photoreconnaissance supremacy, separated cleanly from its Fregat upper stage approximately 45 minutes post-liftoff, injecting into an initial low Earth orbit with an apogee of around 650 kilometers and a perigee near 250 kilometers. Early telemetry bursts confirmed nominal attitude control and basic housekeeping functions, but true operational life demanded a methodical startup sequence, bridging the raw mechanics of deployment with the precision of reconnaissance readiness.\n\nThe activation phase commenced as the spacecraft's pyrotechnic devices fired in precise choreography, unfurling its solar arrays to capture the sun's unfiltered glare and extending a suite of articulated antennas for S-band and UHF command uplinks. Ground teams at the Titov Main Test and Control Center in Krasnoznamensk monitored these extensions via redundant signal paths, cross-verifying deployments against pre-flight simulations that had accounted for microgravity flexures and thermal gradients. Power budgets stabilized within hours, with batteries transitioning seamlessly to solar recharge, a testament to the Cobalt-M's evolutionary refinements in gallium arsenide cells that maximized efficiency in eclipse-prone inclinations. Orbit stabilization followed, employing the satellite's hydrazine thrusters in a series of deterministic burns to circularize the orbit and align the nodal precession for optimal ground track repeatability over key theaters of interest.\n\n***The initial activation and testing period of Kosmos 2505 in low Earth orbit lasted 37 days***, a deliberate tempo calibrated to unearth any latent anomalies before committing to full mission parameters. This extended shakedown unfolded in layered milestones: the first week prioritized core bus validation, cycling through inertial measurement units, star trackers, and reaction wheels to establish three-axis stability with sub-degree precision. Controllers commanded low-resolution imaging passes using the primary electro-optical sensor, a hybrid film-digital payload that represented the program's swan song, capturing calibration targets over the Barents Sea to benchmark radiometric fidelity against onboard blackbodies. By day 10, propulsion diagnostics intensified, mapping impulse bits from cold-gas attitude jets and verifying main engine gimballing, all while refining the orbit to a near-circular 300-kilometer altitude optimized for dwell times over high-latitude targets.\n\nChallenges emerged mid-phase, as transient data dropouts—later attributed to plasma sheath interference during high-beta solar angles—tested the resilience of the uplink chain. Redundant transponders were activated, and Doppler-aided ranging compensated for ephemeris drifts, ensuring uninterrupted command authority. The subsequent fortnight delved into payload commissioning: canister film advance mechanisms whirred through test reels, emulsion integrity checks confirmed via proxy spectrometry, and the recovery beacon pulsed affirmatively for de-orbit planning years hence. Orbit stabilization reached its zenith around day 25, with final perigee-raising burns nullifying drag-induced decay, achieving a projected lifespan exceeding five years. Ground analysts pored over gigabytes of housekeeping logs, cross-correlating thermal profiles from the multi-layer insulation blankets against predictive models that incorporated the 2015 solar maximum's heightened flux.\n\nAs the 37-day odyssey crested, Kosmos 2505 transitioned to operational cruising, its electro-optical heart now pulsing with validated acuity. Full-resolution reconnaissance windows opened, capturing swaths of terrain with the characteristic Cobalt-M granularity that had eluded adversaries for a generation. This final unit's startup not only affirmed the analog film's unyielding prowess amid the digital dawn but also etched a capstone of reliability into the program's lore, bridging the empirical grit of early 2000s missions with the procedural maturity honed through iterative flights. Controllers breathed collective relief as the bird sang clear on all bands, poised for the strategic vigils that would define its tenure until the inexorable pivot to pixel-perfect successors.\n\nFollowing the meticulous testing and orbit stabilization period that spanned several weeks after Kosmos 2505's activation, the Cobalt-M program's flagship satellite transitioned seamlessly into its operational peak in 2015, marking the zenith of the entire 2004-2015 endeavor. This phase represented the culmination of years of iterative refinements in Russian reconnaissance satellite technology, where the spacecraft—equipped with advanced electro-optical imaging sensors capable of resolving ground features down to sub-meter scales—unleashed its full potential in a relentless campaign of intelligence gathering. Ground controllers at the Titov Main Test Space Systems Center, leveraging real-time telemetry from the satellite's S-band and X-band transponders, orchestrated a symphony of orbital adjustments and sensor activations, ensuring optimal sun-synchronous passes over priority regions across Eurasia, the Middle East, and select Pacific theaters.\n\n***The core data acquisition phase of Kosmos 2505 lasted 45 days***, a meticulously planned window of peak productivity that began in mid-2015 once all subsystems had demonstrated flawless performance during checkout. During this interval, the satellite executed over a thousand imaging passes, prioritizing dynamic targets such as military maneuvers, infrastructure developments, and naval deployments that demanded the highest temporal resolution. Its primary payload, a high-resolution panchromatic and multispectral camera system derived from the upgraded Persona lineage, captured vast datasets in visible, near-infrared, and shortwave infrared spectra, enabling detailed change detection analyses back on Earth. Each orbit, the spacecraft would slew its gimbaled optics toward tasking lists uploaded via secure Tundra communication relays, snapping hyperspectral imagery strips that spanned hundreds of kilometers while compensating for atmospheric distortion through onboard processing algorithms honed over the program's decade-long evolution.\n\nThe intensity of this 45-day surge was unprecedented for the Cobalt-M series, as Kosmos 2505 benefited from enhanced power management via its gallium arsenide solar arrays, which sustained continuous sensor operation even during the demanding summer solstice lighting conditions. Mission planners divided the phase into micro-cycles: dawn-dusk orbits for shadow-enhanced urban mapping, midday passes for broad-area surveillance, and nocturnal infrared sweeps to track heat signatures from mobile launchers and airfields. Data volumes soared, with daily downlinks exceeding 100 gigabits funneled through the Russian Quantum Encryption Network to processing hubs in Krasnoznamensk and Plesetsk, where automated tools fused imagery with signals intelligence from complementary assets like Liana ocean surveillance satellites. This deluge of raw electro-optical intelligence not only validated the Cobalt-M's role as a cornerstone of Russia's space-based ISR architecture but also provided critical insights into geopolitical flashpoints, from contested maritime claims in the South China Sea to troop buildups along volatile borders.\n\nChallenges arose, as they invariably do in the unforgiving realm of space operations, yet they underscored the satellite's robustness. Minor thermal fluctuations during high-latitude passes prompted adaptive attitude control maneuvers using its hydrazine thrusters, while cosmic ray-induced bit errors in the solid-state recorders were mitigated by redundant error-correcting codes—a lesson carried forward from earlier Cobalt iterations. Ground teams monitored propellant margins closely, preserving enough delta-v for post-peak deorbit preparations, all while the satellite's anti-jamming receivers thwarted potential electronic interference from adversarial actors. The phase's success hinged on the seamless integration of human expertise and automation; flight dynamics engineers at the TsNIIMash center ran predictive models to preempt yaw drifts, ensuring pointing accuracy within arcseconds—a feat that elevated Kosmos 2505 above its predecessors in the program.\n\nAs the 45-day core acquisition window drew to a close, the operational peak yielded a treasure trove of intelligence products that informed strategic assessments through the remainder of 2015 and beyond. This period encapsulated the Cobalt-M program's evolution from experimental launches in the mid-2000s to a mature, battle-tested constellation element, demonstrating how persistent orbital reconnaissance could reshape modern conflict dynamics. The satellite's performance metrics—sustained uptime above 99 percent, imaging quality unmarred by degradation—affirmed Russia's mastery of mid-resolution electro-optical systems, even as international observers noted the implications for global transparency regimes. In retrospect, 2015's operational zenith for Kosmos 2505 not only closed the chapter on the Cobalt-M era with resounding authority but also set benchmarks for successor programs like Razdan, proving that the fusion of optical prowess and orbital endurance could sustain national security imperatives in an era of proliferating threats.\n\nAs the Cobalt-M satellites hurtled through their meticulously choreographed orbits during the 2015 mission's peak data acquisition phase—a grueling 28-day sprint of relentless imaging that captured terabytes of high-fidelity intelligence—the spacecraft's antiquated heart began to reveal its swan song. Nestled within the payload bays of these venerable workhorses were the last vestiges of a bygone technological paradigm: spools of specialized photographic film, wound tight with the promise of unparalleled resolution. This final operational cadence marked not just the culmination of the program's core imaging objectives but the poignant finale to an entire epoch in reconnaissance satellite history, where physical media return capsules plummeted from the edge of space like time capsules from a fading age.\n\nThe Cobalt-M series, operational from 2004 to 2015, stood as a resolute holdout in an industry long since seduced by the siren call of digital imaging. Born from the lineage of Cold War-era pioneers like the Corona program—which revolutionized overhead reconnaissance in the 1960s by ejecting film canisters recovered mid-air by C-130 aircraft—Cobalt-M perpetuated this mechanical ballet into the 21st century. Each satellite unfurled its telescopic optics, exposing vast reels of fine-grain emulsion to the unfiltered blaze of sunlight on shadowed terrains below. The film, engineered with exotic silver halide crystals capable of discerning details as fine as a license plate from 150 miles up, captured multispectral data impervious to the electronic noise that plagued early digital sensors. But this fidelity came at a steep price: the inexorable wait for reentry, the nail-biting parachute deployments over remote Pacific drop zones, and the meticulous darkroom processing that could take days to yield actionable prints.\n\nContrast this with the digital vanguard that had already reshaped the field. By the late 1970s, the KH-11 Kennen series introduced charge-coupled device (CCD) arrays, beaming electro-optical imagery via encrypted X-band downlinks to ground stations in real time. No more perilous reentries; data flowed like a digital river, instantly exploitable by analysts wielding nascent image-processing software. The advantages snowballed through the 1990s and 2000s: improved signal-to-noise ratios via advanced focal plane arrays, hyperspectral capabilities unlocked by onboard spectrometers, and the sheer volume enabled by solid-state storage. Yet Cobalt-M's architects clung to film for its proven resilience against radiation hardening issues, its superior dynamic range in low-light conditions, and—perhaps most crucially—its deniability. A recovered canister left no electronic trail, no vulnerable uplink signature that adversaries could jam or spoof.\n\nThe 2015 mission encapsulated this tension in microcosm. Launched amid escalating geopolitical flashpoints, Cobalt-M 12 (the program's capstone vehicle) was burdened with dual payloads: a primary film return system augmented by experimental digital burst imagers. During peak activity, the satellite's film magazines churned through exposures at a rate of hundreds per orbit, prioritizing time-critical targets like mobile missile launchers and naval maneuvers in contested waters. Ground controllers at the secretive NRO facilities synchronized reentry windows with weather patterns and recovery assets, a ritual honed over a decade of Cobalt operations. On mission day 32, the final canister—a 200-pound cylinder packed with over 10,000 frames—separated, its retro-rockets firing in a blaze of pyrotechnics 80 miles above the ocean. Parachutes bloomed against the dawn sky, snagged by hovering helicopters in a flawless snatch that evoked the program's glory days. Back in the labs, the negatives revealed exquisite detail: textures of desert camouflage nets, the subtle wakes of submerged submarines—intelligence gold that digital prototypes still struggled to match without massive data compression losses.\n\nYet even as technicians unpacked those last reels under red safelights, the writing was on the wall. The 2015 recovery was the 47th and final film return of the Cobalt-M era, sealing the program's retirement. Cost analyses had long favored digital: each canister mission demanded $50 million in recovery logistics alone, from specialized aircraft to biohazard protocols for reentry-heated film. Digital successors, like the enhanced electro-optical systems on follow-on platforms, slashed that to fractions while multiplying revisit rates. Radiation-hardened CMOS sensors, cooled to cryogenic temperatures, now rivaled film's resolution at 0.1-meter ground sample distances, with onboard AI edging toward automated target recognition. The transition wasn't merely technical; it symbolized a philosophical shift—from the tactile craftsmanship of analog photography to the ethereal precision of bits and bytes, from delayed gratification to instantaneous dominance.\n\nThis pivot heralded the end of an era with quiet finality. No fanfare accompanied the decommissioning of Cobalt-M's film winders; instead, the program's archives swelled with lessons etched in emulsion. Engineers who had nursed these satellites through solar flares and orbital perturbations reflected on the poetry of it all: film, that fragile alchemy of chemistry and light, had outlasted the Space Shuttle, bridged the gap to the International Space Station age, and delivered pivotal insights during interventions from Libya to the South China Sea. Its obsolescence underscored the relentless march of Moore's Law in orbit, where storage densities exploded and bandwidths widened, rendering physical returns as archaic as floppy disks. For the National Reconnaissance Office, the Cobalt-M finale was a valediction—a case study in graceful obsolescence, paving the way for constellations of agile, software-defined imagers that would redefine space-based vigilance. In the control rooms, as the last telemetry faded, a chapter closed not with a bang, but with the soft click of a shutter, forever preserved in the digital annals to come.\n\nAs the final Cobalt-M mission, Kosmos 2505, reached the culmination of its operational phase, mission controllers at the Plesetsk Cosmodrome's ground stations initiated the meticulously planned deorbit sequence, a procedure that underscored the program's disciplined approach to spacecraft retirement and payload recovery. This marked not only the shutdown of the last reconnaissance satellite reliant on physical film return but also a poignant close to over a decade of evolving orbital intelligence gathering. With primary imaging objectives fulfilled—having captured extensive high-resolution coverage across targeted regions—the focus shifted seamlessly to preserving the integrity of the reentry capsule, which housed the mission's crowning cache of exposed film canisters. Engineers began by commanding a series of low-thrust retrograde burns using the satellite's remaining hydrazine propulsion reserves, gradually reducing its perigee from the nominal 250-kilometer operational altitude toward the denser layers of the upper atmosphere.\n\n***The controlled deorbit and recovery preparation sequence of Kosmos 2505 lasted 22 days,*** a deliberate timeframe that allowed for precise orbital decay management, exhaustive systems diagnostics, and coordination with recovery assets on the ground. This extended duration was essential in a program where haste could jeopardize the fragile film payloads, susceptible to radiation degradation or thermal stress during uncontrolled reentry. Day by day, the sequence unfolded with rhythmic precision: initial burns on day one lowered perigee by approximately 20 kilometers, triggering preliminary atmospheric drag that mission planners monitored via S-band telemetry links. Subsequent days involved alternating periods of coasting—permitting natural decay—and corrective maneuvers to maintain an elliptical descent profile, ensuring the capsule's trajectory aligned with predetermined splashdown zones in the Pacific Ocean's remote expanse, far from shipping lanes or populated areas.\n\nThroughout this phase, the shutdown process was methodical, prioritizing subsystem isolation to safeguard the capsule. Power systems were progressively depowered, starting with non-essential avionics like star trackers and auxiliary heaters, while the primary service module's attitude control thrusters fired in short bursts to stabilize orientation. Thermal control loops were reconfigured to protect the film compartment, maintaining a stable 15-20°C environment against the encroaching heat of reentry. Data handling units executed final memory dumps, transmitting residual housekeeping telemetry and orbital parameters to ground stations in Kaliningrad and Moscow, confirming battery health and propulsion residuals. By day 10, the service module's main engines were fully inhibited, rendering the stack inert except for the capsule's independent pyrotechnic sequencing, a design hallmark of the Cobalt lineage that ensured separation just prior to peak heating.\n\nRecovery preparations intensified in parallel, leveraging the 22-day window to synchronize oceanic assets. Specialized naval vessels from the Pacific Fleet, equipped with helicopter cranes and bio-containment protocols for potential film emulsion hazards, maneuvered into position, their crews conducting daily drills amid variable weather patterns. Meteorological teams at the Russian Academy of Sciences forecasted reentry windows, adjusting for solar activity that could perturb drag coefficients. Parachute deployment simulations validated the capsule's dual-drogue and main canopy sequence, critical for a soft ocean landing at terminal velocity. Ground recovery protocols, honed from prior missions like Kosmos 2486, emphasized rapid retrieval—targeting under 30 minutes post-splashdown—to minimize saltwater exposure, with divers and winch operators on standby.\n\nAs the sequence progressed into its final week, perigee dipped below 100 kilometers, intensifying aerodynamic stresses that controllers observed through fading signals. The capsule's ablative heatshield, layered with phenolic resins proven across Yantar derivatives, was primed for the 7-kilometer-per-second plunge, while the service module was programmed for destructive reentry to minimize space debris. On the penultimate day, a confirmation burn fine-tuned the impact ellipse to within 50 kilometers of the prime recovery ship. Shutdown culminated in the command link's final transmission: a sequenced ignition of separation charges, severing the capsule at 120 kilometers altitude. Plummeting through plasma sheaths glowing at 2,500°C, it deployed parachutes flawlessly, splashing down under clear skies. Recovery teams, racing via Mi-38 helicopters, secured the bobbing canister within 22 minutes, ferrying it to a secure quarantine facility where technicians extracted 48 intact film spools— a testament to the deorbit sequence's flawless execution.\n\nThis 22-day ballet of propulsion, telemetry, and terrestrial logistics not only ensured the safe return of the Cobalt-M program's valedictory intelligence haul but also symbolized the Soviet-Russian space reconnaissance tradition's unwavering commitment to controlled termination. In an era shifting toward digital constellations, Kosmos 2505's deorbit stood as a masterclass in analog-era precision, bridging the physical return of film with the inexorable march toward electro-optical futures.\n\nAs the meticulously orchestrated deorbit sequence for Kosmos 2505 progressed through its final phases, ground control teams at the Russian Space Forces' mission centers maintained vigilant oversight, their displays alive with telemetry streams charting the satellite's inexorable descent from low Earth orbit. The preparation window, spanning several orbits, had allowed for precise nodal regression adjustments to align the reentry corridor over the designated recovery zone in the vast steppes of Kazakhstan—a region long favored for its expansive, sparsely populated terrain ideal for parachute-assisted splashdowns or soft landings. Engineers fine-tuned perigee burns using the remaining hydrazine propellant, ensuring the decaying orbit would culminate in a controlled atmospheric interface rather than an uncontrolled tumble into oceanic oblivion, a fate that had befallen lesser missions in the program's earlier, less refined iterations.\n\nTension mounted in the hours leading to reentry, as the Cobalt-M's service module, having fulfilled its role in delivering the reconnaissance capsule back to Earth after 104 days aloft, began shedding velocity at the cusp of the sensible atmosphere. The capsule, encapsulating a treasure trove of unclassified structural remnants and any surviving data storage modules from its classified imaging payloads, relied on its ablative heat shield—a technological heir to the storied Zenit and Yantar series—to withstand the plasma inferno of peak deceleration. Infrared sensors aboard tracking aircraft and ground-based radars painted a vivid picture of the fiery streak slicing through the mesosphere, a fleeting meteor engineered by human intent. Separation from the spent propulsion stage occurred flawlessly at an altitude of approximately 100 kilometers, propelling the bell-shaped reentry vehicle into its ballistic arc.\n\n***The landing of Kosmos 2505 touched down successfully on 17 September 2015***, precisely within the predicted footprint amid the golden autumn grasses of the Kazakh landing ellipse, where recovery crews in Mi-8 helicopters and GAZ Tigr vehicles stood poised. Parachute deployment sequenced without anomaly: the drogue stabilized the descent at 10 kilometers, followed by the main canopy unfurling at 5 kilometers, reducing terminal velocity to a gentle 8 meters per second. The capsule's impact, cushioned further by retrorockets firing in the final seconds, registered minimal structural stress, preserving the integrity of its pressure vessel for post-flight analysis. Recovery teams swarmed the site within minutes, securing the canister against potential scavenging or environmental degradation, their gloved hands confirming the telltale charring of reentry while noting the faint hiss of residual heat dissipating into the crisp air.\n\nThis touchdown not only validated the Cobalt-M program's crowning engineering achievement but also symbolized the graceful sunset of an era in optical reconnaissance. Over eleven years, from the inaugural launches in 2004 to this poignant finale, the constellation had amassed petabytes of imagery under the veil of military secrecy, adapting to evolving threats from insurgent shadows in asymmetric warfare to the creeping militarization of near-space domains. Kosmos 2505, launched in 2015 as the last of its line, had circled Earth thousands of times, its Zeiss-derived lenses capturing resolutions that pushed the boundaries of film-based electro-optical systems before the inevitable shift to digital constellations loomed on the horizon.\n\nIn the debriefings that followed, Russian space officials lauded the mission's success, attributing it to iterative improvements in orbital mechanics modeling and autonomous deorbit triggers. The retrieved hardware from Kosmos 2505 underwent rigorous disassembly at facilities in Moscow and Baikonur, yielding insights into long-duration material fatigue, radiation hardening, and the subtle wear of micrometeoroid impacts—data that would inform successors like the anticipated Persona series. Yet, beyond the technical triumphs, the landing evoked a quiet reflection among veterans of the program: the thud of that final capsule on Kazakh soil echoed the close of a chapter where analog precision met digital destiny, marking September 2015 as the definitive terminus of Cobalt-M's operational odyssey. With no more capsules slated for return, the skies fell silent to their signature signatures, ceding ground to a new vanguard of uncrewed sentinels.\n\nAs the Cobalt-M reconnaissance satellite program drew to a definitive close with the controlled deorbit and landing of its final operational asset in September 2015, its legacy emerged not merely as a footnote in the annals of space-based intelligence but as a cornerstone of modern military reconnaissance. Spanning over a decade from its inaugural launch in 2004, Cobalt-M represented a pivotal evolution in electro-optical and signals intelligence capabilities, transforming raw orbital data into actionable insights that underpinned national security strategies across multiple theaters. This era marked a shift from the intermittent, film-return missions of earlier generations to persistent, high-resolution surveillance that could pivot from strategic monitoring to tactical support in near-real time, fundamentally altering how intelligence was gathered, processed, and disseminated.\n\nAt its core, the program's impact lay in its unprecedented fusion of advanced sensor suites—combining multispectral imaging with synthetic aperture radar and electronic intercept arrays—that delivered resolutions fine enough to discern individual vehicle markings or infrastructure vulnerabilities from hundreds of kilometers aloft. During this period, Cobalt-M assets orbited ceaselessly, compiling petabytes of data that fed into fusion centers worldwide, enabling commanders to track adversary movements with a granularity previously confined to ground-based assets. The program's agility was evident in its rapid retasking protocols, which allowed satellites to slew toward emerging hotspots within minutes, providing decision-makers with \"eyes on target\" during crises that ranged from counterinsurgency operations in rugged terrains to maritime domain awareness in contested seas. This responsiveness not only shortened the observe-orient-decide-act loop but also minimized reliance on riskier manned or unmanned aerial platforms, preserving assets and lives while extending coverage to denied-access regions.\n\nBeyond immediate operational yields, Cobalt-M's legacy reverberates through the technological advancements it spurred. Its onboard processing architectures, which employed early machine learning precursors for automated target recognition, set benchmarks for anomaly detection amid vast data streams, reducing human analyst workload by orders of magnitude and paving the way for today's autonomous satellite constellations. The program's emphasis on modular bus designs facilitated iterative upgrades via mid-mission software patches and secondary payload integrations, achieving a mean mission life that exceeded initial projections through meticulous orbital maintenance and debris mitigation maneuvers. These innovations influenced procurement doctrines, emphasizing resilience against anti-satellite threats with hardened electronics and maneuverable orbits that confounded predictable targeting.\n\nStrategically, Cobalt-M's contributions fortified deterrence postures by furnishing unambiguous evidence of provocations, from missile deployments to covert base constructions, thereby shaping diplomatic maneuvers and preemptive planning. In the intelligence community's ecosystem, it bridged gaps between siloed domains—pairing visual confirms with intercepted communications to unmask hybrid threats—while its archived datasets remain invaluable for post-mission forensic analysis and training simulations. The program's cost-effectiveness, achieved through serialized production and shared ground infrastructure, demonstrated scalable space power projection, influencing budget allocations that prioritized orbital reconnaissance over legacy systems.\n\nEven as newer platforms eclipsed Cobalt-M's specifications, its doctrinal imprint endures: the normalization of space as a warfighting domain, where persistent ISR (intelligence, surveillance, and reconnaissance) underpins joint all-domain operations. Veterans of the program, from systems engineers to orbital analysts, carried forward lessons in constellation management and data sovereignty, seeding expertise into successor initiatives. In retrospect, Cobalt-M's eleven-year vigil not only illuminated shadows across the globe but also illuminated the path for an era where space dominance equates to informational supremacy, ensuring that the faint glimmers of its infrared sensors continue to echo in the strategic calculations of tomorrow.\n\nThe operational triumphs of the Cobalt-M reconnaissance satellite program from 2004 to 2015 were inextricably linked to the steadfast performance of its launch vehicles, primarily drawn from the venerable Soyuz family. In an era where space access demanded not just innovation but unyielding dependability, the Soyuz rockets emerged as the backbone of the program's deployment strategy, ensuring that delicate reconnaissance payloads reached their precise orbital slots with minimal disruption. This statistical overview delves into the reliability metrics that defined these launches, highlighting a track record that underscored the maturity of Russian launch infrastructure and its pivotal role in sustaining a continuous flow of intelligence-gathering assets into space.\n\nThe Soyuz lineage, evolved from the R-7 intercontinental ballistic missile design of the late 1950s, had by the early 2000s amassed decades of empirical proof of its robustness. Throughout the Cobalt-M era, variants such as the Soyuz-U and the progressively refined Soyuz-2 series were tasked with lofting these satellites from sites like Plesetsk and Baikonur Cosmodromes. What set these vehicles apart was their evolutionary refinement: incremental upgrades to propulsion systems, avionics, and structural integrity had incrementally elevated their performance envelope, transforming potential vulnerabilities into hallmarks of consistency. Launch data from this period reveals a pattern of near-flawless execution, where the interplay of rigorous ground testing, redundant safety protocols, and a deep institutional knowledge base minimized anomalies that could derail missions.\n\nReliability in launch operations is quantifiable not merely through raw success counts but through the scarcity of partial or total failures across mission phases—liftoff, staging, payload fairing separation, and orbital insertion. For the Cobalt-M program, Soyuz vehicles demonstrated an enviable proficiency in these critical junctures, with ascent profiles tailored to the satellites' demanding requirements for sun-synchronous or highly elliptical orbits. The boosters' liquid-fueled RD-107 and RD-108 engines, renowned for their throttle responsiveness and restart capability, provided a forgiving margin against the perturbations of atmospheric reentry and upper-stage burns. Archival logs from the program's dozen or so dedicated launches indicate that deviations, when they occurred, were confined to negligible telemetry glitches rather than catastrophic events, a testament to the vehicle's fault-tolerant architecture.\n\nA deeper analysis uncovers the statistical resilience embedded in Soyuz's operational philosophy. Pre-flight simulations, often exceeding a thousand iterations per campaign, correlated strongly with in-flight outcomes, fostering a predictive accuracy that bordered on prescient. During 2004-2015, as geopolitical tensions escalated the need for persistent surveillance, the launch cadence accelerated without compromising this reliability; intervals between Cobalt-M deployments shrank from quarterly to bimonthly peaks, yet the vehicles adapted seamlessly to varying payload masses and injection altitudes. This adaptability stemmed from modular strap-on boosters and digital flight control systems introduced in the Soyuz-2 iterations, which enhanced thrust vectoring precision and reduced dispersion errors to fractions of a degree—key metrics in achieving the sub-kilometer orbital accuracy demanded by reconnaissance missions.\n\nContextualizing Soyuz's performance within the broader launch manifest of the era further illuminates its superiority. While contemporary Western launchers grappled with high-profile setbacks tied to novel solid-rocket technologies, Soyuz leaned on a heritage of over two thousand flights, its failure modes exhaustively cataloged and mitigated through a centralized engineering consortium. In the Cobalt-M context, this translated to a deployment reliability that enabled the program to outpace budgetary constraints and technical hurdles, placing assets that would underpin strategic decision-making for over a decade. The absence of launch-induced losses preserved not only hardware but also the momentum of intelligence continuity, allowing subsequent satellites to inherit and build upon the orbital networks established early in the timeline.\n\nBeyond the launch pad, Soyuz's reliability extended into post-insertion phases, where upper-stage passivation and deorbit kits ensured compliance with space debris mitigation standards, indirectly bolstering long-term program sustainability. Statistical trends from anomaly reports—spanning vibration spectra, thermal profiles, and separation dynamics—paint a picture of progressive enhancement: early 2000s missions showed minor fairing jettison variances, refined to negligible by 2010 through acoustic shielding augmentations. This iterative mastery not only fortified Cobalt-M's operational tempo but also positioned Soyuz as a benchmark for state-sponsored space endeavors, where the cost-per-kilogram to orbit remained competitively low without sacrificing mission assurance.\n\nIn summation, the Soyuz launch vehicles' statistical profile during the Cobalt-M program exemplifies a rare confluence of historical pedigree, engineering discipline, and operational pragmatism. Their high success rates—manifest in unbroken chains of orbital insertions—were no accident but the product of a system honed by adversity and ambition. This reliability was the unsung enabler of the program's evolution, transforming ambitious reconnaissance visions into a tangible legacy of space-based vigilance that echoed far beyond 2015.\n\n### Statistical Overview: Mission Durations\n\nWhile the Soyuz launch vehicles demonstrated exemplary reliability in delivering Cobalt-M satellites to their operational orbits, the true measure of the program's endurance lay in the satellites' ability to sustain mission profiles over extended periods. Transitioning from the launch phase to on-orbit operations, mission durations provide a compelling statistical lens through which to view the Cobalt-M program's maturation. In the nascent years of the program, from 2004 to around 2008, mission lengths such as ***76 days for Kosmos 2420 and Kosmos 2427, and 108 days for Kosmos 2410*** were achieved. These operational spans reflect the initial constraints of the early satellite designs.\n\nAs the program progressed into its middle phase, spanning approximately 2009 to 2012, a noticeable elongation in mission durations emerged, ***such as 89 days***. Statistical analysis of this era reveals a clear upward trajectory in mission durations.\n\nThe pinnacle of this trend manifested in the later years, from 2013 to 2015, where mission durations ***such as 104 days for Kosmos 2505*** underscored the program's maturation. Across the full 2004-2015 arc, the program's mission duration statistics paint a portrait of relentless improvement. Variability also diminished over time. These trends highlight steady progress in mission lengths.\n\nThis progression in mission lengths had profound operational implications for the Cobalt-M constellation. Early short-duration missions necessitated frequent relaunches, straining the Soyuz manifest and launch cadence. By contrast, the extended lifespans of later satellites enabled a leaner sustainment model, sustaining constellation coverage with fewer active assets and freeing resources for technology maturation toward the successor program.\n\nIn essence, the statistical arc of Cobalt-M mission durations encapsulates the program's evolution—from tentative forays with shorter missions to a robust operational paradigm with extended lifespans. This not only amplified the intelligence yield but also set benchmarks for subsequent reconnaissance architectures, proving that in the unforgiving vacuum of space, longevity is the ultimate validator of design excellence.\n\nAs mission durations stretched from the initial 60-70 days in the program's early phases to well over 100 days by the mid-2010s, the Cobalt-M reconnaissance satellite constellation demanded a correspondingly robust evolution in its ground segment infrastructure. This transformation was not merely an afterthought but a deliberate engineering campaign to ensure seamless command, control, telemetry, tracking, and data relay (C3TDR) operations across increasingly extended orbital lifetimes. The ground segment, encompassing tracking stations, mission control centers, and data processing facilities, underwent phased upgrades that mirrored the satellites' own advancements in propulsion, power systems, and sensor endurance, enabling operators to maximize the intelligence yield from each orbit.\n\nIn the program's nascent years around 2004-2006, ground tracking relied on a modest network of legacy U.S. Space Force stations, primarily drawing from the Air Force Satellite Control Network (AFSCN) heritage. These facilities, scattered across sites like Vandenberg Space Force Base in California, Buckley Space Force Base in Colorado, and Andersen Air Force Base in Guam, featured S-band and X-band antennas with modest apertures—typically in the 10-15 meter range—that provided intermittent passes of 8-12 minutes per overflight. Tracking was largely manual, with operators relying on ephemeris predictions from aging orbital models prone to cumulative errors over multi-week missions. Data downlinks were buffered during passes, then ferried via physical media or early fiber links to centralized processing nodes at the National Reconnaissance Office's (NRO) NRO Ground Facility equivalents. This setup sufficed for short-duration missions but strained under the pressure of accumulating orbital perturbations, radiation-induced anomalies, and the need for precise attitude maneuvers to maintain imaging windows.\n\nBy 2008, as Cobalt-M satellites began demonstrating enhanced on-orbit stability, the ground segment pivoted toward automation and network expansion. A key inflection point came with the deployment of the Enhanced Tracking and Command System (ETCS), which integrated GPS-augmented TLE (Two-Line Element) data with real-time laser ranging from newly commissioned optical trackers at sites like Maui Space Surveillance Complex. Antenna farms were modernized: larger 18-meter dishes with cryogenic low-noise amplifiers (LNAs) boosted signal-to-noise ratios by factors that allowed for continuous tracking during low-elevation passes, even in adverse weather. The introduction of phased-array antennas at key nodes—first prototyped at Cape Canaveral—enabled beam steering without mechanical gimbals, slashing acquisition times from minutes to seconds and supporting simultaneous multi-satellite handoffs. This was critical as the constellation grew to four operational birds by 2010, demanding agile scheduling to avoid pass conflicts.\n\nData processing centers, once siloed in vaulted bunkers with racks of Sun Microsystems servers crunching raw imagery via custom FORTRAN codes, evolved into distributed high-performance computing (HPC) clusters. The shift to Linux-based blade servers running parallelized algorithms for SAR (Synthetic Aperture Radar) focusing and electro-optical sharpening accelerated product generation from hours to near-real-time. By 2011, the integration of commercial off-the-shelf (COTS) software like ENVI for hyperspectral analysis and custom neural nets for change detection marked a departure from bespoke military-grade tools, leveraging Moore's Law to handle the terabyte-scale downlinks from upgraded onboard solid-state recorders. Secure fiber optic backhauls, hardened against cyber threats with quantum key distribution pilots, linked these centers into a resilient mesh, with primary hubs at NRO's Aerospace Data Facility-East (ADF-E) in Virginia and ADF-West in Colorado.\n\nThe pinnacle of ground segment maturity arrived in the 2012-2015 epoch, coinciding with the longest Cobalt-M missions. Global partnerships expanded the tracking footprint: cooperative agreements with allies added stations in the UK (RAF Fylingdales), Australia (Pine Gap), and even temporary deployables in Diego Garcia, forming a near-continuous coverage belt with over 90% visibility uptime. Unified S/X/Ka-band gateways, compliant with the Space Data System Standard (SDSS), facilitated cross-bandwidth agility, allowing satellites to dump high-volume Ka-band video during optimal windows while falling back to S-band for TT&C (Telemetry, Tracking & Command) in emergencies. Automation reigned supreme through the Ground Resource Optimization Tool (GROT), an AI-driven scheduler that dynamically allocated passes based on threat intelligence feeds, orbital drag forecasts from Space Weather Prediction Center models, and payload tasking priorities. Redundancy was baked in: hot-swappable control rooms with virtualized cockpits enabled seamless failover, while edge processing at remote trackers pre-filtered data to reduce latency.\n\nThese ground segment enhancements were not without challenges—early automation glitches in 2009 led to a temporary \"tracking blackout\" during a solar maximum event, prompting the hasty rollout of radiation-hardened FPGAs in receiver chains. Yet, the iterative upgrades yielded dividends: station-keeping maneuvers, once requiring 24-hour planning cycles, shrank to under two hours, preserving imaging apertures that might otherwise degrade by degrees per week. Data latency plummeted from days to minutes, empowering time-sensitive operations like maritime surveillance in contested littorals. By 2015, as Cobalt-M transitioned toward successor architectures, the ground segment stood as a template for resilient space operations—a symphony of antennas sweeping the skies, processors humming in cooled halls, and operators guiding digital sentinels through the void, all in service of an intelligence edge sharpened by two decades of relentless evolution.\n\nAs the ground segment infrastructure matured through the mid-2000s, enabling more precise orbital tracking and rapid data downlink from the Cobalt-M satellites, a parallel evolution occurred in the domain of physical payload recovery—a hallmark of the program's design that harkened back to the film-return era of reconnaissance satellites. Unlike purely digital imaging systems, Cobalt-M missions relied on reentry capsules containing high-resolution film canisters, cryogenic sensors, and hardened data recorders, necessitating a robust logistics chain to retrieve these assets intact from remote landing zones. This recovery phase, often the most perilous and logistically intensive segment of each mission, demanded seamless integration between military operators, naval recovery teams, and civilian support entities, transforming potential chaos into a choreographed ballet of precision and urgency.\n\nThe recovery sequence commenced with deorbit initiation, typically executed over the Pacific Ocean to leverage vast, sparsely populated splashdown zones while minimizing geopolitical risks. Ground controllers at upgraded tracking stations—now augmented with real-time ephemeris prediction software—issued burn commands to the satellite's propulsion module, propelling the conical capsule into a steep reentry trajectory. Parachute deployment at approximately 20,000 feet marked the onset of the terminal phase, with beacons activating to broadcast GPS coordinates via UHF signals. Here, the U.S. Air Force's 6594th Test Squadron, evolved from its Corona-era roots, coordinated with the Navy's Airborne Mine Countermeasures (AMCM) assets and P-3 Orion patrol aircraft, which loitered in predetermined boxes to acquire the initial fix. Civilian involvement ramped up through Federal Aviation Administration (FAA) notices to airmen (NOTAMs), clearing airspace and alerting maritime traffic, while NOAA provided real-time ocean current forecasts to refine drift predictions.\n\nLanding zones were strategically selected across a spectrum of environments, from oceanic splashdowns off the California coast to overland recoveries in the Utah Test and Training Range, adapting to mission profiles and weather windows. Oceanic recoveries, comprising the majority of operations, exemplified interagency synergy: Navy helicopters from carriers like the USS Ronald Reagan or shore-based detachments would deploy swimmer teams equipped with infrared strobes and hoist gear, often within 30 minutes of splashdown. These teams, trained in hazardous material handling due to the capsules' residual hypergolic propellants, secured the payload via slings or flotation collars before airlifting it to forward staging areas. In one emblematic 2009 mission, a capsule drifted 15 nautical miles farther than modeled due to unforecasted winds, prompting an ad-hoc rerouting of Coast Guard cutters from San Diego, underscoring the value of redundant civilian maritime assets in the logistics web.\n\nOverland recoveries introduced additional complexities, particularly in coordinating with civilian land managers and ranchers in the American West. The Air Force's pararescue jumpers (PJs) parachuted into the predicted footprint, establishing beacons and securing the site against scavengers or inadvertent interference, while local sheriffs enforced cordons under prearranged memoranda of understanding. Federal Bureau of Land Management (BLM) personnel facilitated access across public lands, and in arid zones like Nevada's Black Rock Desert, dust abatement teams mitigated helicopter brownouts. This civilian-military interface evolved significantly post-2010, with integrated training exercises at Dugway Proving Ground simulating night recoveries under electronic warfare conditions, honing protocols that reduced turnaround times from touchdown to lab handover from days to hours.\n\nLogistical backbone was provided by a fleet of C-17 Globemasters and C-130J Super Hercules, prepositioned at Travis and Hickam Air Force Bases, which ferried recovered capsules to secure facilities at Vandenberg or the National Reconnaissance Office's payload processing center in Sunnyvale. En route, capsules underwent preliminary decontamination in mobile clean rooms to neutralize biohazards from reentry ablation, with chain-of-custody logs maintained via encrypted blockchain precursors for tamper-proof audit trails. Challenges persisted, including a 2012 incident where corrosive saltwater ingress compromised a film cassette, spurring upgrades to composite heatshield materials and self-sealing hatches. By 2015, recovery success rates approached 98 percent, a testament to predictive analytics fused from ground segment data, which refined splashdown ellipses to under five nautical miles.\n\nThis logistics ecosystem not only ensured the Cobalt-M program's viability but also set precedents for hybrid digital-analog reconnaissance architectures. The interplay of military discipline with civilian agility—exemplified by joint operations centers fusing DoD radars with FAA flight data—fostered a resilient framework, capable of scaling to the constellation's peak of 12 active vehicles. As the program wound down amid shifting priorities toward fully electronic payloads, the recovery logistics review revealed a legacy of operational artistry: turning fiery descents from orbit into the safe return of intelligence gold, mission after mission.\n\nAs the Cobalt-M program drew to a close in the mid-2010s, the intricate ballet of capsule recovery—those tense hours of aerial spotting, mid-air snatches by C-130 crews, and seamless handoffs between Air Force recovery teams and FAA-monitored landing zones—faded into operational memory. Yet, this logistical prowess was merely the visible tip of a vast inheritance, one that profoundly shaped the reconnaissance architectures of the future. The program's true legacy lay not in the analog film canisters that parachuted earthward, but in the technological and procedural DNA it bequeathed to the digital era of space-based intelligence. Newer platforms, unburdened by physical returns, absorbed these lessons, evolving into leaner, more resilient systems capable of real-time data dissemination without the vulnerabilities of reentry.\n\nAt the heart of this inheritance were the reentry vehicle innovations honed over Cobalt-M's decade-long run. The program's capsules, engineered to withstand the fiery gauntlet of atmospheric plunge while preserving delicate film payloads, pioneered ablative heat shields composed of advanced phenolic resins that dissipated plasma sheaths with unprecedented efficiency. These materials, iteratively refined through post-mission teardowns in secure facilities at Vandenberg and beyond, directly informed the thermal protection systems of subsequent hypersonic vehicles, including those tested in the DARPA Falcon program and later orbital maneuvering units. Guidance and attitude control systems, reliant on inertial measurement units (IMUs) and stellar trackers to achieve pinpoint deorbit accuracy within kilometers of predicted splashdown zones, transitioned seamlessly into the avionics of digital satellites. Future programs like the Enhanced Integrated Framework for Reconnaissance (EIFR) and the NRO's next-generation electro-optical birds adopted these robust, radiation-hardened IMUs, ensuring stable pointing amid the jitter of low-Earth orbit. The failure modes cataloged from Cobalt-M's occasional \"black box\" recoveries—where beacons failed or parachutes tangled—spurred the development of redundant GPS-aided beacons and steerable drogue chutes, now standard in de-orbiting cargo pods from the International Space Station and commercial resupply missions.\n\nOperational procedures, forged in the high-stakes pressure cooker of live recoveries, provided an equally vital blueprint. The Cobalt-M era's emphasis on multi-agency fusion—melding NORAD's orbital predictions with civilian weather services and Navy P-3 Orion spotters—evolved into the integrated mission control paradigms of today's reconnaissance constellations. Lessons from coordinating across classified channels and open skies informed the architecture of the National Reconnaissance Office's (NRO) ground segments, where automated orbit determination software now ingests data from GPS networks and commercial synthetic aperture radar (SAR) feeds to preemptively task digital assets. The program's ritualistic post-recovery chain-of-custody protocols, designed to shuttle film from Pacific drop zones to darkrooms in record time, prefigured the end-to-end encryption pipelines of modern systems. In an age of hyperspectral imaging and AI-driven change detection, the discipline of minimizing latency from capture to analyst desk—once measured in days for Cobalt-M film processing—became codified in software-defined radios and laser inter-satellite links, enabling near-instantaneous data relay to forward-deployed forces.\n\nData handling paradigms underwent the most transformative shift, as Cobalt-M's analog workflows illuminated the path to digital supremacy. The laborious process of chemical development, precision scanning with wet-gate film digitizers, and geometric correction to counter orbital distortions yielded algorithms that automated radiometric calibration and orthorectification. These tools, born from reverse-engineering thousands of kilometers of exposed Kodak film, were ported into the processing chains of platforms like the Future Imagery Architecture (FIA) successors, where onboard compression engines now apply similar corrections in real time. Cobalt-M's experience with signal-to-noise degradation in long-duration exposures taught future designers to prioritize focal plane arrays with cryogenic cooling, mitigating thermal noise in infrared bands—a direct lineage seen in the spectral sensors of the WorldView commercial lineage and military equivalents. Moreover, the program's covert recovery ops underscored the need for anti-jamming beacons and low-probability-of-intercept (LPI) telemetry, technologies that matured into the spread-spectrum communications underpinning smallsat swarms like those in the NRO's proliferated architecture.\n\nThis technological osmosis extended to resilience engineering, where Cobalt-M's endurance against space weather and adversarial threats set new benchmarks. Missions that survived solar flares through judicious orbit phasing and shielded electronics paved the way for fault-tolerant onboard computers in digital sats, capable of autonomous reconfiguration during geomagnetic storms. The iterative design cycles—each launch incorporating metallurgical tweaks to withstand micrometeoroid punctures—influenced the composite structures of agile imaging platforms that can slew 180 degrees in seconds to track fleeting targets. Procedurally, the debriefs from \"no-recovery\" incidents, where capsules sank into uncharted ocean trenches, birthed global search-and-rescue simulations now embedded in training for hypersonic glide vehicles and reusable orbital platforms.\n\nBy the late 2010s, the imprint of Cobalt-M was unmistakable in the operational tempo of digital reconnaissance. Programs like the Tactical Reconnaissance Orbital Platforms (TROP) and the Joint Overhead Persistent Surveillance (JOPS) initiative inherited not just hardware derivatives but a philosophy of redundancy and adaptability. The capsule recovery's emphasis on human-in-the-loop verification transitioned to hybrid AI-human workflows, where machine learning models trained on Cobalt-M's vast film archives detect anomalies with 99% fidelity before human validation. Coordination models refined in dusty landing zones scaled to multinational data-sharing consortia, enabling allied forces to tap into shared orbital assets during crises from the South China Sea to Eastern Europe.\n\nIn essence, Cobalt-M's technological inheritance transformed reconnaissance from a episodic, film-dependent endeavor into a persistent, digital vigil. What began as parachutes billowing over the horizon evolved into invisible streams of petabytes cascading through space, yet the foundational rigor—unyielding precision in reentry, ironclad procedures in chaos, and relentless pursuit of data integrity—ensured that the shadows cast by those early capsules continue to guide the unseen eyes overhead. This legacy, quietly woven into classified blueprints and commercial spin-offs alike, underscores a timeless truth in space operations: true innovation emerges not from solitary leaps, but from the cumulative wisdom of missions that dared the void and returned to tell the tale.\n\nAs the Cobalt-M program matured and its analog imaging technologies began bridging toward the digital architectures of successor platforms, one critical operational imperative emerged that would define its legacy in sustainable space operations: orbital debris mitigation. In an era when Low Earth Orbit (LEO) was increasingly congested by defunct satellites, spent upper stages, and fragmentation debris from collisions and explosions, the program's architects recognized that reconnaissance missions—frequently launched into sun-synchronous orbits around 500-800 kilometers altitude—posed unique long-term risks. Each Cobalt-M satellite consisted of a primary imaging payload housed within a reentry capsule designed for physical return to Earth, separated from a robust service module that provided power, attitude control, propulsion, and thermal management throughout the mission. Upon capsule release and deorbit, the service module remained in orbit, transforming from an active asset into a potential hazard unless meticulously managed. This disposal phase became a cornerstone of the program's adherence to nascent international standards, such as those outlined in the Inter-Agency Space Debris Coordination Committee (IADC) guidelines and NASA's orbital debris mitigation requirements, which emphasized passivation, deorbiting, and minimizing post-mission survivability.\n\nThe Cobalt-M service modules were engineered from the outset with debris mitigation as a design driver, reflecting lessons from earlier film-return systems like the KH-9 Hexagon and the challenges encountered during the program's inaugural launches in 2004. Following capsule separation—typically executed via pyrotechnic devices after 3 to 6 months of operational imaging—the service module underwent a scripted passivation sequence. This process began with the depletion of all remaining hypergolic propellants through controlled firings of the attitude control thrusters, venting residual pressure to prevent unintended explosions that could generate thousands of trackable fragments. Batteries were deliberately discharged to deep levels, isolating power buses and shorting cells to eliminate stored electrical energy, a measure proven effective in averting arcing events observed in other LEO programs. Solar arrays, which spanned over 20 meters in some configurations, were feathered into a low-drag orientation to accelerate atmospheric reentry, while any deployable antennas or booms were commanded into retracted stowage to reduce cross-sectional area and collision vulnerability.\n\nOperational procedures evolved significantly over the program's decade-long span, incorporating real-time telemetry monitoring from ground stations to verify passivation success. Early missions, such as those in 2004-2006, relied primarily on natural decay trajectories, positioning service modules in orbits with predicted lifetimes of under 25 years—a threshold aligned with contemporary U.S. government policies aiming for disposal within this window to limit long-term population growth. By 2008, following high-profile debris-generating events like the Fengyun-1C antisatellite test, the program integrated dedicated deorbit kits into later service module designs. These comprised small solid rocket motors or drag-enhancing sails, activated post-passivation to lower perigee below 300 kilometers, ensuring reentry within months rather than years. Mission planners meticulously modeled these maneuvers using tools like NASA's Debris Assessment Software (DAS), accounting for solar activity cycles, atmospheric density variations, and third-party conjunction assessments from the U.S. Space Surveillance Network (SSN). In one notable evolution, the 2010-2012 launches introduced autonomous fault-tolerant software that triggered deorbit sequences even in the event of command link loss, safeguarding against \"zombie\" satellites drifting uncontrolled.\n\nChallenges abounded, particularly given the classified nature of reconnaissance payloads, which constrained public disclosure and international collaboration. Service modules occasionally experienced anomalies—such as thruster valve leaks or solar array drive failures—that complicated full passivation, prompting ad-hoc ground interventions via high-gain antennas at Vandenberg or Cape Canaveral. Yet, the program's track record remained exemplary; telemetry logs indicated that over 90% of disposed modules achieved full energy depletion, with the remainder posing minimal fragmentation risk due to their robust yet frangible construction. This focus on service module disposal not only complied with the 2006 U.S. Orbital Debris Mitigation Standard Practices but also preempted regulatory pressures that would intensify post-2015 with the rise of mega-constellations. By prioritizing low-earth-return profiles over geostationary disposals, Cobalt-M avoided the perpetual clutter of higher altitudes, where decay times stretch to centuries.\n\nThe mitigation strategies developed under Cobalt-M reverberated beyond the program's 2015 sunset, informing the propulsion passivation protocols and deorbit burn profiles of digital successors like the Enhanced Imaging System satellites. Operators refined conjunction avoidance maneuvers, integrating service module ephemeris data into shared catalogs to alert CubeSat deployers and commercial imagers. Educational campaigns within the intelligence community highlighted case studies from Cobalt-M passivations, underscoring how even small residuals—paint flecks or titanium pressure vessels—could cascade into Kessler Syndrome scenarios. In retrospect, the program's disciplined approach to service module end-of-life management exemplified a paradigm shift: from viewing space as an inexhaustible frontier to treating it as a finite resource demanding stewardship. This legacy ensured that the orbital highways patrolled by reconnaissance assets remained viable for future generations, even as mission tempos accelerated and payload complexities grew.\n\nFollowing the program's disciplined approach to orbital debris mitigation—particularly the deorbiting of service modules post-capsule separation—the Cobalt-M missions drew inevitable scrutiny from the global community of satellite watchers, a diverse cadre ranging from dedicated amateurs to state-sponsored intelligence apparatuses. In an era when spaceflight transparency was the exception rather than the norm for secretive military programs, these external observers pieced together the puzzle of Russia's reconnaissance efforts through a combination of publicly available data, optical and radar tracking, and informed speculation. The Kosmos designation, a longstanding veil for Soviet and post-Soviet military payloads, continued to cloak the Cobalt-M satellites, launching primarily from Plesetsk Cosmodrome on Soyuz-2 rockets into sun-synchronous polar orbits ideal for high-resolution Earth imaging. Independent trackers, leveraging Two-Line Element (TLE) sets disseminated by the U.S. Space Command (later Space Force), meticulously cataloged each ascent, noting the characteristic 500-600 kilometer altitudes and slight inclinations that betrayed their photoreconnaissance purpose.\n\nAmateur astronomers and satellite enthusiasts, organized through forums like SeeSat-L and platforms such as Heavens-Above, played a pivotal role in this grassroots surveillance. Equipped with backyard telescopes, high-speed cameras, and software like Orbitron or Heavens-Above's prediction tools, they captured passes of the Kosmos vehicles streaking across night skies worldwide. Flares from the satellites' attitude control thrusters or the occasional glint off solar panels provided fleeting glimpses, often shared in real-time mailing lists with precise timings and brightness estimates. These observations not only confirmed orbital parameters but also hinted at operational nuances: brief station-keeping burns or the telltale dimming during imaging passes when attitude was adjusted for nadir-pointing cameras. For enthusiasts in Europe and North America, a Kosmos launch—typically announced tersely via NOTAMs restricting airspace over recovery zones in Siberia—signaled an opportunity to contribute to the open-source intelligence ecosystem, fostering a sense of global participation in demystifying Moscow's space activities.\n\nProfessional international observers, including those from the U.S. Space Surveillance Network (SSN) with its constellation of phased-array radars like those at Eglin Air Force Base and Kwajalein Atoll, afforded a far more granular view. These assets generated high-fidelity orbital data, tracking the Cobalt-M satellites from booster separation through their multi-week missions. NATO allies, through shared intelligence channels and facilities like the UK's Royal Air Force Fylingdales or France's GRACE radar, corroborated these readings, painting a picture of a robust, evolving program. Externally, the Cobalt-M series was perceived as a bridge between the aging Yantar film-returners of the Cold War and more modern electro-optical systems, with its persistent use of reentry capsules underscoring Russia's preference for physical film recovery over digital downlinks—likely to evade electronic interception. Analysts noted the program's resilience amid post-Soviet economic constraints, with launch cadences holding steady at 4-6 per year, suggesting sustained investment in electro-optical and possibly synthetic aperture radar capabilities.\n\nThe recovery phase elicited particular fascination and frustration among observers. Capsule reentries, choreographed over the vast Orenburg or Kazakhstan steppes, were shrouded in operational security, with restricted airspace and rapid ground recovery teams minimizing visibility. Yet, infrared sensors from geostationary early-warning satellites occasionally detected the telltale heat signatures of deorbit burns, while seismic networks picked up faint impacts from parachuted landings. Foreign intelligence reports, declassified years later, revealed estimates of mission durations averaging 20-30 days, with success rates inferred from subsequent launches; failures, such as premature reentries or lost capsules, occasionally betrayed themselves through anomalous TLE decays or unrecovered debris splashes. This opacity fueled narratives of technological continuity laced with incremental upgrades—improved resolution from upgraded optics, perhaps, or enhanced maneuvering to evade collisions—positioning Cobalt-M as a reliable workhorse in Russia's space-based intelligence architecture.\n\nBeyond raw tracking, the international gaze interpreted the program's broader implications. Western think tanks like the Secure World Foundation and the Union of Concerned Scientists chronicled it within annual assessments of military space assets, highlighting its role in monitoring NATO exercises, border tensions, and global hotspots from the Caucasus to the Arctic. Chinese observers, via their nascent Yuanwang tracking ships and Xi'an Satellite Control Center, mirrored these efforts, viewing Cobalt-M through the lens of competitive space reconnaissance. Speculation abounded on payload specifics: panoramic framing cameras for wide-area survey, high-acuity spotters for tactical targets, and even oblique sensors for stereo mapping. Yet, the program's low-key execution—absent the bombast of crewed flights or mega-constellations—reinforced an image of pragmatic endurance, a testament to Russian engineering amid geopolitical isolation. By 2015, as Cobalt-M yielded to next-generation designs, its decade-long run had become a benchmark for external analysts, illustrating how even veiled operations could be illuminated through persistent, multinational vigilance, underscoring the inherently observable nature of low Earth orbit in the satellite age.\n\nWhile independent trackers and foreign intelligence services could meticulously chart the launches, orbital maneuvers, and reentries of Cobalt-M satellites under the guise of Kosmos missions, the true value of these reconnaissance platforms lay not in their visible trajectories but in the sensitive intelligence they gathered and relayed. Protecting the telemetry streams—rich with high-resolution imagery, signals intelligence, and sensor data—and the command uplinks that directed their operations was paramount. From the program's inception in 2004 through its evolution into the mid-2010s, the Cobalt-M team implemented layered cryptographic data security measures to shield these links from interception, jamming, or spoofing by adversaries. This invisible armor ensured that even if an observer pinpointed a satellite's ground stations or S-band/UHF frequencies, deciphering the payload remained an insurmountable challenge.\n\nAt the heart of these defenses was end-to-end encryption of all telemetry, tracking, and command (TT&C) communications. Telemetry downlinks, which transmitted vast quantities of compressed electro-optical and radar data back to primary control centers like those at Plesetsk or Krasnoznamensk, employed symmetric key algorithms with rotating session keys derived from pre-shared secrets. These keys, updated via secure bootstrapping during orbital insertion, rendered intercepted signals into indecipherable noise without the precise temporal synchronization required for decryption. Command uplinks, conversely, incorporated digital signatures and challenge-response authentication protocols to prevent spoofing attacks, where a malicious actor might attempt to hijack control by mimicking legitimate ground station signals. This dual approach not only encrypted the content but also verified the authenticity of every transmission, drawing on principles honed from earlier Soviet-era systems like the Almaz and adapted for the digital age.\n\nFrequency-agile spread-spectrum techniques further obfuscated the links, making it exceedingly difficult for passive listeners to even acquire a stable signal. Cobalt-M satellites dynamically hopped across allocated bands—typically in the 2-8 GHz range for imaging data dumps—using pseudo-random sequences synchronized to the encryption keys. This was particularly crucial during high-value phases, such as post-maneuver data bursts over contested regions like the Middle East or the South China Sea, where U.S. or NATO SIGINT platforms might lurk. Anti-jamming resilience was bolstered by low-probability-of-intercept (LPI) modulation schemes, including direct-sequence spread spectrum (DSSS), which diluted signal power across wide bandwidths while maintaining robust error correction via convolutional or turbo codes. Over the program's lifespan, software-defined radios onboard the satellites allowed for over-the-air key renegotiation and algorithm upgrades, enabling responses to emerging threats like advanced software-defined receivers wielded by foreign powers.\n\nData protection extended beyond raw links to the integrity of the payloads themselves. Onboard processors segmented reconnaissance data into encrypted packets, each tagged with integrity check values (ICVs) using hash-based message authentication codes (HMACs). This prevented tampering during transmission, ensuring that even partial interceptions—say, from opportunistic low-Earth orbit passes by adversary microsatellites—yielded no exploitable fragments. Key management was a sophisticated ballet: ground stations at hardened facilities utilized hardware security modules (HSMs) compliant with evolving Russian standards, generating ephemeral keys tied to Greenwich Mean Time and satellite ephemeris data. During the 2008-2010 modernization phase, following lessons from Georgia conflict intercepts, Cobalt-M incorporated forward secrecy mechanisms, where compromised session keys could not retroactively expose prior communications.\n\nThe efficacy of these measures was underscored by the scarcity of verified leaks throughout the program's decade-plus run. Western analysts, despite prolific orbital tracking via networks like Space-Track or amateur radio enthusiasts decoding Kosmos beacons, rarely pierced the cryptographic veil. Occasional glimpses—such as faint, unencrypted housekeeping telemetry for orbital maintenance—served as deliberate chaff, masking the hardened primary channels. By 2015, as Cobalt-M yielded to next-generation platforms, its security paradigm had influenced broader Russian space doctrine, emphasizing quantum-resistant primitives in anticipation of future computational threats. Yet, the foundational reliance on robust, multi-layered cryptography had proven that in the shadowed realm of space reconnaissance, data protection was not merely technical but existential, safeguarding national secrets amid an era of proliferating surveillance eyes.\n\nAs the Cobalt-M program matured into its second decade, the robustness of secure telemetry and command links proved indispensable for mission success, yet these systems relied fundamentally on a stable power foundation provided by the spacecraft's solar arrays. Transitioning from the cryptographic safeguards that protected data flows, the solar array performance emerged as a critical metric for evaluating the endurance of reconnaissance operations, particularly during the extended missions launched in 2011 and 2012. These later Cobalt-M variants, designed for multi-year orbital vigils in low Earth orbit, pushed the boundaries of photovoltaic endurance, revealing nuanced degradation patterns that informed subsequent satellite architectures.\n\nThe solar arrays on Cobalt-M satellites employed gallium arsenide multijunction cells, a technological leap from the silicon-based panels of earlier reconnaissance platforms, optimized for high efficiency under the variable illumination of LEO trajectories. Each array wing, spanning approximately 10 meters when fully deployed, generated the baseline power required for imaging sensors, onboard processors, and attitude control systems. In the initial phases of missions, performance metrics consistently exceeded design specifications, with peak output aligning closely to pre-launch predictions under nominal solar beta angles. However, as these 2011 and 2012 spacecraft—designated CM-14 through CM-17—progressed beyond their first year on orbit, ground controllers began documenting subtle but progressive declines in power generation capacity, a phenomenon emblematic of the harsh space environment's toll on photovoltaic materials.\n\nDegradation rates observed during these longer missions followed a characteristic trajectory, beginning with minimal losses attributable to initial ultraviolet exposure and atomic oxygen erosion on the array surfaces. By the second orbital year, telemetry data indicated compounded effects from high-energy particle radiation in the South Atlantic Anomaly, where Cobalt-M inclinations frequently routed the satellites through intensified proton fluxes. Engineering teams at the program’s operations center meticulously reviewed power generation statistics, noting quarter-over-quarter trends that highlighted a stabilization in degradation after initial rapid declines. For instance, the arrays maintained sufficient margin to support full payload operations well into the third year, underscoring the resilience engineered into the system through robust coverglass passivation and micrometeoroid shielding.\n\nA deeper analysis of the power subsystem logs from the 2011 launches revealed that eclipse season performance provided particularly revealing insights. During periods of maximum beta angle misalignment, when arrays operated at reduced incidence angles, the effective power yield dropped predictably, yet the underlying cell efficiency held steady longer than anticipated, thanks to the arrays' flexible blanket design that mitigated thermal stress cycling. Comparatively, the 2012 missions exhibited slightly accelerated degradation in high-latitude passes, where increased exposure to auroral electrons correlated with measurable voltage droop under load. These statistics, correlated against environmental models from NASA's AE8/AP8 radiation belts, allowed operators to refine orbit maintenance maneuvers, preemptively boosting perigee to skirt peak radiation zones and thereby extending viable power budgets.\n\nThe interplay between solar array output and mission profiling became especially pronounced in these extended campaigns. Power generation statistics demonstrated that array degradation directly influenced data downlinks, as diminished margins necessitated selective powering of high-bandwidth transmitters during optimal illumination windows. Ground-based simulations, fed with real-time telemetry, projected end-of-life power levels that aligned with observed behaviors, validating the conservative margins built into the electrical power subsystem (EPS) design. Notably, the absence of sudden failures—unlike some contemporary programs plagued by cell string outages—spoke to the quality of manufacturing processes, including rigorous vibration and thermal vacuum testing that simulated years of on-orbit stress.\n\nBeyond raw output metrics, the review encompassed secondary indicators such as shunt regulator activity and battery charge cycles, which painted a holistic picture of array health. In the 2011 missions, statistics showed consistent overproduction during solstice periods, building surplus capacity that buffered against degradation-induced shortfalls. The 2012 cohort, benefiting from iterative design tweaks like enhanced anti-static coatings, logged marginally flatter degradation curves, with power generation sustaining nominal levels for 20% longer into mission life before throttling non-essential subsystems. These trends prompted a program-wide reassessment of photovoltaic lifetime models, shifting from linear decay assumptions to more accurate logarithmic profiles informed by Cobalt-M flight data.\n\nOperational adaptations further highlighted the arrays' pivotal role. Controllers implemented dynamic power management algorithms that reprioritized loads based on real-time generation forecasts, ensuring reconnaissance imaging windows remained uninterrupted despite waning array performance. The statistics from these maneuvers revealed efficiencies gains of several percentage points, effectively stretching mission durations toward the four-year mark for select spacecraft. This era of Cobalt-M operations thus marked a pivotal evolution, where solar array performance data not only chronicled hardware limits but also catalyzed advancements in autonomous power optimization—lessons that rippled into next-generation reconnaissance platforms.\n\nIn retrospect, the solar array degradation review for the 2011 and 2012 missions encapsulated the Cobalt-M program's engineering ethos: relentless pursuit of reliability amid unforgiving orbital realities. By meticulously tracking power generation statistics across multiple vehicles, the team quantified environmental impacts with unprecedented granularity, fostering a legacy of durable space power systems that underpinned the reconnaissance enterprise through 2015 and beyond.\n\nAs the Cobalt-M satellites pushed the boundaries of endurance during the extended missions of 2011 and 2012, where solar array degradation gradually curtailed power budgets, the spacecraft's thermal control systems emerged as a critical linchpin for sustained performance. These systems were engineered not merely to survive the harsh thermal extremes of low Earth orbit—ranging from intense solar fluxes during dawn-dusk passages to the frigid shadows of eclipse periods—but to precisely regulate temperatures for the program's most sensitive payloads: the high-resolution optical camera assemblies and the specialized film stocks used in early imaging modes. Unlike purely electronic sensors, the Cobalt-M's hybrid electro-optical design retained analog film cartridges for redundancy and ultra-high-fidelity panchromatic imaging, demanding isothermal environments between 15°C and 25°C to prevent emulsion cracking, fogging, or dimensional warping. Thermal mismanagement here could render entire mission segments unusable, underscoring why the thermal subsystem was dubbed the \"silent guardian\" in program documentation.\n\nThe baseline thermal architecture for Cobalt-M, inherited from late KH-11 lineage but refined through iterative ground testing at the Air Force's Arnold Engineering Development Complex, blended passive and active strategies to minimize power draw—a prescient choice given later solar array wear. Multi-layer insulation (MLI) blankets, comprising up to 25 layers of aluminized Kapton and Dacron spacers, enveloped the bus and payload module, yielding effective emittances exceeding 0.8 while reflecting over 90% of incident solar radiation. Deployable beta blankets on the solar arrays doubled as thermal shields, and high-emissivity white paints on select sun-facing surfaces further attenuated heat loads. Yet passive elements alone proved insufficient for the payload's thermal mass; variable-emittance coatings experimented with in prototype Block I vehicles were shelved after orbital trials revealed hysteresis issues, paving the way for more robust active interventions.\n\nAt the heart of active thermal management lay the single-phase fluid loop system, a closed-circuit network circulating a custom propylene glycol-water mixture—selected for its low freezing point (-50°C), high specific heat (4.2 J/g·K), and non-corrosive compatibility with aluminum alloys. Pumped by redundant centrifugal micro-pumps drawing under 10W each, the loop spanned 45 meters of 6-mm diameter tubing, weaving through the camera's cryogenic optics barrel, film vault isolators, and electronics bays. Heat acquisition occurred via cold plates bolted directly to the primary mirror assembly and film spool housings, where phase-change material (PCM) inserts—paraffin wax composites with 180 J/g latent heat—buffered transient loads during attitude maneuvers. The fluid, maintained at 20°C nominal, absorbed up to 1.2 kW peak from avionics and imager cryocoolers, preventing hotspots that could exceed 40°C and degrade film granularity.\n\nRadiator panels formed the loop's rejection backbone, four 2.5 m² deployable assemblies of aluminum honeycomb sandwich structures coated with silver Teflon (ε=0.85, α=0.12) for optimal deep-space viewing. Hinged on the anti-sun nadir face, these panels unfurled post-separation via shape-memory alloy actuators, achieving full extension within 30 minutes and maintaining <1° dihedral alignment via piezoelectric trimmers. During nominal operations, the loop rejected 80-90% of payload heat through these surfaces, with transport lines insulated by aerogel sleeves to curb parasitic losses. Eclipse cooldowns relied on loop bypass valves routing fluid directly to the radiators, dropping temperatures by 5°C per orbit while electric heaters—thermistors slaved to platinum resistance temperature detectors (RTDs)—countered overcooling, ensuring film vaults never dipped below 12°C.\n\nOperational telemetry from the inaugural 2004 Cobalt-M1 launch illuminated the system's finesse. Ground controllers at the National Reconnaissance Office's (NRO) Consolidated Space Operations Center (CSpOC) monitored over 200 RTDs sampling every 10 seconds, with autonomous software executing proportional-integral-derivative (PID) control loops to tweak pump speeds and valve positions. Peak challenges arose during \"death rolls\"—high-beta-angle orbits where solar beta exceeded 60°, slamming radiators with unintended insolation. Here, the system shone: louver assemblies, 16 electro-mechanical iris-like blades covering radiator faces, modulated view factors from 0.1 to 0.9, shedding excess heat without loop freezing. Mission planners scheduled payload blackouts during these phases, preserving film integrity as temperatures stabilized within 2°C bands.\n\nBy the 2011-2012 elongated campaigns, where solar array output had eroded to 65% of specification after 4,000 thermal cycles, thermal margins tightened perilously. Degraded power forced sequential shedding of non-essential heaters, exposing the fluid loop to risks of glycol crystallization—a gremlin mitigated by introducing trace antifreeze additives via propellantless resupply concepts tested on Cobalt-M7. Radiator efficacy waned too, as micrometeoroid hypervelocity impacts pitted Teflon coatings, reducing emittance by up to 15% over 30 months on-orbit. Engineers responded with software patches uplinked via TDRSS, optimizing louver hysteresis and incorporating predictive algorithms based on historical ephemeris data to preempt thermal excursions. One notable anomaly on Cobalt-M12 involved a pump seizure from bubble ingestion during a thruster firings; redundant failover engaged seamlessly, but it spurred a fleet-wide retrofit of micro-filters in subsequent blocks.\n\nEvolutionary tweaks across the program underscored adaptive engineering. Block II vehicles (2008 onward) integrated a secondary two-phase CO2 loop for cryocooler cold heads, boosting heat rejection density to 300 W/m² and decoupling it from the glycol primary—vital for sustaining 3.5 K optics amid rising infrared background loads. Film stock thermal enclosures evolved from rigid composites to actively pumped conformable bladders, slashing gradient deltas to <0.5°C across 50 kg spools. Ground simulations at NASA's White Sands Test Facility, using 1:1 thermal-vacuum mockups, validated these upgrades, predicting 95% on-orbit reliability. By 2015's Cobalt-M15 swan song, thermal control had transcended mere survival, enabling 42-month missions that captured pivotal intelligence windows, from North Korean rocket tests to South China Sea militarization—testaments to a subsystem that quietly orchestrated the satellite's operational symphony.\n\nIn retrospect, the Cobalt-M thermal regime exemplified the program's philosophy: robustness through redundancy and foresight. While solar arrays faltered under UV and atomic oxygen onslaughts, the fluid loops and radiators endured, their fluid dynamics and radiative physics unyielding sentinels. Archival NRO after-action reports credit thermal stability for 92% of imaging data usability across 12 vehicles, a metric that outshone even propulsion reliability. As the program yielded to digital successors like the Enhanced Imaging System, these analog-era thermal innovations lingered in classified playbooks, influencing next-generation constellations where thermal precision remains the arbiter of mission success.\n\nAs the Cobalt-M reconnaissance satellites maintained precise thermal equilibrium through their intricate fluid loops and radiator arrays—safeguarding the sensitive camera optics and film emulsions from the harsh vicissitudes of orbital environments—the program's operational integrity hinged equally on another critical subsystem: the propulsion architecture. These satellites, designed for extended reconnaissance missions in low Earth orbit, relied on a suite of maneuvering engines to execute station-keeping burns, yaw and pitch adjustments, and, ultimately, controlled deorbit maneuvers at mission end. The propulsion system's reliability became a cornerstone of the program's longevity, enabling satellites to linger in their imaging sweet spots for years while adhering to international space debris mitigation guidelines.\n\nThe heart of the Cobalt-M propulsion setup comprised clusters of small thrusters, primarily monopropellant hydrazine units augmented by a few higher-impulse bipropellant engines for major orbital corrections. These engines, clustered in axial and radial configurations around the satellite bus, fired in precise pulses to counter atmospheric drag, precessional drift, and the gradual nodal regression inherent to sun-synchronous orbits. Hydrazine's simplicity—decomposing catalytically over iridium-coated beds to produce thrust without an oxidizer—proved ideal for the long-duration demands of reconnaissance, where autonomy was paramount. Redundancy was baked in from the outset: each satellite carried dual-string thruster sets, with cross-strapping to isolate failures, ensuring that a single valve malfunction or catalyst degradation wouldn't doom the mission.\n\nThroughout the early launches from 2004 to 2007, the propulsion system's performance set a benchmark for reliability in the classified realm of electro-optical imaging satellites. Initial on-orbit checkouts revealed thruster ignition success rates that exceeded expectations, with cold starts after months of dormancy functioning flawlessly due to the robust pyrotechnic squib initiators. Orbit maintenance burns, typically conducted in short bursts every few weeks, demonstrated exceptional repeatability, preserving the ground track accuracy essential for repeatable overflight coverage of high-value targets. Anecdotal telemetry from these pioneering missions highlighted minimal propellant slosh issues, thanks to bladder-type tanks that minimized ullage gas ingestion—a common Achilles' heel in earlier programs.\n\nBy the program's mid-decade maturation around 2008-2010, subtle challenges emerged that tested the propulsion envelope, yet underscored its inherent robustness. Prolonged exposure to atomic oxygen in the upper atmosphere led to occasional erosion of thruster nozzles, manifesting as slightly elongated burn durations but without compromising impulse delivery. One notable incident involved a satellite experiencing intermittent radial thruster hesitation, traced to propellant filter partial blockages from manufacturing residue; ground teams mitigated this through altered firing sequences, extending the bird's life well beyond nominal. These episodes prompted incremental software uplinks—refinements to the onboard propulsion management algorithms that optimized burn profiles for efficiency, reducing cumulative thermal stress on the catalyst beds. Far from eroding confidence, such adaptability affirmed the system's fault-tolerant design.\n\nThe latter half of the Cobalt-M era, spanning 2011 to 2015, showcased propulsion reliability at its zenith, particularly in the execution of deorbit campaigns. As each satellite approached end-of-life, having amassed terabytes of imagery, the bipropellant main engine took center stage for the decisive lowering burns. These maneuvers demanded exacting precision to target reentry corridors over oceanic graveyards, minimizing ground risk. Mission after mission, the engines responded with unerring fidelity: full-thrust startups after years of idling, sustained firings that shaved hundreds of kilometers from perigee, and clean shutdowns that left residual propellant margins for final attitude holds. The absence of hypergolic leaks or chamber cracks—plagues of lesser systems—spoke to the meticulous qualification testing endured pre-launch, including vibration spectra mimicking Titan IV liftoffs and thermal-vacuum cycling to simulate decade-long soaks.\n\nQuantifying this track record without classified metrics, the propulsion subsystem's uptime approached near-perfection across the fleet, with no mission lost to primary propulsion failure. Evolutionary tweaks, such as enhanced passivation protocols to vent residuals post-deorbit, reflected lessons from the thermal management realm bleeding into propulsion ops—ensuring that even depleted hydrazine posed no explosion hazard during reentry. Comparative to contemporaneous programs, Cobalt-M's engines outshone in longevity, their modular architecture facilitating heritage reuse from prior generations while incorporating micro-thruster innovations for finer control.\n\nIn retrospect, the propulsion system's reliability not only sustained the Cobalt-M chronicle but epitomized the unsung heroism of space operations engineering. It bridged the gap between fleeting launches and enduring vigilance, allowing these silent sentinels to orbit faithfully until called home. This dependability, forged in the crucible of iterative flights, paved the way for successor architectures, where electric propulsion whispers might one day supplant chemical roars—yet the hydrazine legacy of Cobalt-M endures as a testament to mechanical poetry in the void.\n\nAs the Cobalt-M satellites executed their final deorbit burns with the proven reliability of their maneuvering engines, the mission transitioned seamlessly into one of the most unforgiving phases of operations: atmospheric reentry. This critical juncture relied not on propulsion but on the meticulously engineered aerodynamics of the SPK descent capsule, a compact, purpose-built reentry vehicle designed to shepherd sensitive reconnaissance payloads back to Earth intact. The SPK, standing for Secure Payload Kit, encapsulated the film's spools, electronics, and recovered imagery data within a robust aeroshell, transforming the satellite's orbital husk into a controlled ballistic projectile hurtling toward the atmosphere at near-orbital velocities.\n\nThe physics of SPK reentry began with the capsule's separation from the service module, typically at an altitude of around 120 kilometers, where residual orbital momentum propelled it into the tenuous upper atmosphere. Here, the interplay of gravitational pull and atmospheric drag initiated a dramatic deceleration profile. The capsule entered the hypersonic regime almost immediately, with flow speeds vastly exceeding the speed of sound—often by factors of twenty or more—creating a bow shock wave that enveloped the vehicle like a luminous cocoon. This shock layer compressed incoming air molecules into a superheated plasma, glowing with ionized gases that formed a blackout sheath, severing radio communications for several minutes. The SPK's aerodynamic profile was optimized for this environment: a blunt, conical forebody with a rounded nose radius transitioned into a truncated base, maximizing drag while minimizing peak heating. This shape exploited the Newtonian impact theory of hypersonic flow, where pressure distribution dominated over viscous effects, generating immense aerodynamic forces that scrubbed off velocity exponentially as density increased.\n\nStability during this hypersonic deceleration phase was paramount, as any deviation could spell disintegration or off-nominal landing. The SPK achieved this through a low center-of-gravity placement, positioning the dense payload and battery pack forward within the capsule, ensuring the center of pressure—the effective point of aerodynamic force application—remained aft. This static margin provided inherent longitudinal stability, preventing tumbling in the chaotic plasma flow. Unlike lifting reentry vehicles that banked for cross-range control, the SPK followed a near-ballistic trajectory, its high ballistic coefficient—a measure of mass versus drag area—dictating a steep entry corridor that traded altitude for rapid energy dissipation. The forebody's spherical segment geometry induced a natural angle of attack, typically a few degrees, which generated sufficient restoring moments to dampen oscillations. Ablative heat shield materials, layered in a phenolic resin matrix, not only withstood stagnation-point temperatures exceeding several thousand degrees Kelvin but also contributed to stability by eroding predictably, subtly altering the profile to maintain trim as mass was shed.\n\nAs the SPK plunged deeper, crossing from hypersonic into supersonic flow around 60 kilometers altitude, the aerodynamic environment evolved. The detached bow shock thinned, transitioning to an attached oblique shock system that reduced wave drag while still providing deceleration. Boundary layer effects grew prominent, with laminar-to-turbulent transition triggering intense heating spikes along the frustum. The capsule's base, featuring a shallow flare, acted as a diffuser, recovering pressure and further stabilizing pitch dynamics. Roll stability was conferred by subtle circumferential asymmetries in the heat shield—micro-textured grooves that induced a gentle spin-up during entry, countering aerodynamic torques without active control surfaces. This passive approach, honed through wind tunnel tests and computational fluid dynamics simulations during the program's early development, proved resilient across the 2004-2015 operational span, even amid variable atmospheric conditions like solar activity-induced density perturbations.\n\nThe hypersonic phase culminated in peak deceleration, where dynamic pressures peaked, stressing the structural integrity of the titanium pressure vessel housing the payload. Here, the physics of compressible flow revealed the SPK's genius: its drag polar, dominated by pressure drag, followed a near-constant value across Mach numbers, ensuring predictable energy management. As velocities moderated into the transonic regime, compressibility effects waned, and wave drag diminished, allowing the capsule to stabilize at a zero-angle-of-attack attitude. A small drogue parachute, deployed via pyrotechnic mortar at around 10 kilometers, further augmented stability, reeling out to orient the base-down configuration before main chute deployment. This orchestrated descent underscored the Cobalt-M program's engineering philosophy: simplicity in the face of plasma infernos, where every curve of the aeroshell was a calculated bet against chaos.\n\nThroughout the program's history, the SPK reentry aerodynamics demonstrated remarkable consistency, with over 90% of capsules recovered within primary zones despite the inherent unpredictability of upper atmospheric densities. Early missions in 2004-2006 refined entry corridors based on real-time ephemeris data, mitigating risks from geomagnetic storms that puffed the thermosphere. By the mid-2010s, iterative improvements—such as refined nose radius scaling—enhanced margins against convective heating, where the heat flux scaled with the cube of velocity and inversely with nose radius. The physics at play was unforgiving yet elegant: conservation of energy funneled orbital kinetic and potential into thermal and dissipative forms, with the SPK's profile as the indispensable mediator. This phase not only preserved the irreplaceable intelligence yields but also validated the ballistic reentry paradigm for future reconnaissance architectures, bridging the gap between orbital sentinels and terrestrial analysts.\n\nAs the descent capsule of the Cobalt-M reconnaissance satellite transitioned from the fiery gauntlet of hypersonic deceleration—its aerodynamic profile having ensured pitch stability and minimized thermal stresses—the mission's architects turned their ingenuity to the delicate art of controlled descent. With atmospheric friction having bled off the bulk of its orbital velocity, the capsule now plunged through the stratosphere at speeds still far exceeding safe landing thresholds. Here, the parachute systems took center stage, a meticulously engineered multi-stage ballet designed not merely to slow the craft but to cradle its precious film payload with the precision of a surgeon's hand. This phase marked the culmination of reentry engineering, where raw survival gave way to data preservation, ensuring that the high-resolution imagery captured over hostile territories could be recovered intact.\n\nThe parachute deployment sequence commenced automatically at a predetermined altitude, triggered by a barometric altimeter fused with inertial guidance data from the capsule's onboard avionics. First to unfurl was the pilot parachute, a diminutive canopy of ultra-light Kevlar-reinforced nylon, tethered to the capsule via a stout extraction line. No larger than a backpack in its stowed form, this vanguard device served a dual purpose: extracting the larger drogue parachute from its canister while providing initial drag to quell any residual tumbling inherited from the hypersonic regime. In the Cobalt-M program, this pilot chute was a product of iterative refinement, drawing lessons from earlier reconnaissance missions where premature oscillations had threatened structural integrity. Its deployment, marked by a sharp pyrotechnic mortar burst, initiated within seconds of the capsule breaching the upper mesosphere, setting the stage for the drogue's emergence.\n\nThe drogue parachute itself represented the system's robust intermediary, a conical or ribbon-style drag device optimized for supersonic-to-subsonic transition. Spanning several meters in deployed diameter, it was constructed from high-tenacity fabrics capable of withstanding deployment shocks exceeding thousands of pounds of force, yet lightweight enough to avoid excessive weight penalties in orbit. In the Cobalt-M capsules, the drogue featured a unique reefing system—progressive sleeve restraints that modulated its opening in staged increments—to distribute the deceleration load over time, preventing the catastrophic \"opening shock\" that had plagued predecessor programs. This parachute aggressively reduced velocity from hundreds of meters per second to well under terminal limits, stabilizing the capsule's attitude and orienting it apex-down for main parachute extraction. Telemetry from recovered units revealed that this phase typically spanned mere minutes, during which ground control teams monitored descent rates via UHF beacons, ready to vector recovery aircraft if beacons confirmed nominal performance.\n\nWith the capsule now firmly subsonic and yawing gently under the drogue's influence, the main parachute system deployed in a choreographed handoff. Mortar-fired from a dedicated pod, the main canopy—a massive, fully radial design rivaling the span of a small aircraft wing—billowed forth in a carefully sequenced reefing sequence. Initial partial inflation absorbed the energy transfer, followed by full bloom at lower altitudes, achieving a descent rate calibrated for soft touchdown. Materials science advancements shone here: the Cobalt-M mains employed fluorocarbon-coated nylons for puncture resistance against high-altitude particulates, interwoven with aramid strength members to handle the cumulative loads of a 500-plus-kilogram capsule. Canopy geometry, informed by wind tunnel data and computational fluid dynamics simulations, incorporated slots and vents to dampen pendulum motion, ensuring the capsule dangled stably rather than swinging wildly in crosswinds. This stability was paramount; any excessive pendulation risked compromising the film's gelatin emulsion layers, which were notoriously sensitive to accelerations exceeding a few g's.\n\nBeyond mere deceleration, the parachute ensemble integrated recovery aids that transformed a plummeting artifact into a beacon-guided prize. Flashing strobes, dye markers for visual acquisition, and S-band transponders pulsed mission data, including impact coordinates derived from GPS augmentation—a nod to post-2004 navigational evolutions. In the Cobalt-M era, mid-air retrieval by C-130 or modified C-141 aircraft became the norm, with helicopters serving as backups for marginal weather. Parachute risers incorporated quick-release swivels to prevent twisting, and the entire system was jettisonable post-recovery to lighten the load for analysis teams racing against film latency degradation. Ground impact scenarios, though rare, benefited from crushable foam bumpers beneath the capsule, but the parachutes' true genius lay in preempting such contingencies.\n\nThe evolution of these systems across the Cobalt-M program's decade spanned subtle yet critical enhancements. Early missions (2004-2007) relied on heritage designs akin to those of the KH-11 era, with mortars prone to occasional misfires necessitating redundant igniters. By 2009, following a pair of non-nominal descents traced to fabric fatigue from cosmic radiation exposure, engineers introduced spectroscopic doping to the canopy polymers, boosting UV and atomic oxygen resistance for prolonged orbital storage. Later iterations (2012-2015) experimented with semi-autonomous inflation via inertial sensors, adapting reefing profiles in real-time to local wind shear—a feature validated in high-altitude drop tests over the Pacific ranges. Reliability metrics, gleaned from over 40 recovered capsules, underscored the system's maturity: deployment success approached 98 percent, with data integrity losses confined to environmental anomalies rather than mechanical failure.\n\nYet, the parachute review reveals more than technical prowess; it embodies the operational philosophy of the Cobalt-M enterprise. In an age of digital ubiquity, these analog sentinels—low-earth orbit film returnees—demanded parachutes that were not just reliable but forgiving, accommodating the unpredictability of reentry corridors shaped by solar activity and geomagnetic variances. Each stage, from pilot to main, formed a layered defense against the atmosphere's caprice, ensuring that the satellite's eye on the world alighted softly for human hands. This gentle terminus to a relativistic journey underscored the program's enduring legacy: bridging the void between stars and soil with unerring fidelity.\n\nAs the multi-stage parachute systems gradually arrested the descent of the Cobalt-M reconnaissance satellite's film capsules, reducing their terminal velocity to mere tens of meters per second, the mission's architects recognized that parachutes alone could not guarantee the pristine condition required for the delicate photoreconnaissance payloads. Even under ideal aerodynamic conditions, ground impact posed risks of structural deformation, emulsion damage, or data corruption from jarring shocks. This vulnerability necessitated a sophisticated final-stage deceleration system: the soft-landing engines, a quartet of compact, solid-propellant retro-rockets ingeniously integrated into the capsule's base. These engines represented the pinnacle of precision pyrotechnics in reentry vehicle design, engineered to ignite in perfect synchrony just milliseconds before touchdown, transforming a potentially destructive plunge into a feather-light settling onto the recovery zone.\n\nThe soft-landing engines drew from proven solid-propellant formulations akin to those used in ballistic missile nosecone recoveries and early space capsule abort systems, but refined for the unique demands of the Cobalt-M program. Each engine, roughly the size of a large thermos flask, housed a proprietary grain of double-base propellant—typically a nitroglycerin-nitrocellulose composite augmented with aluminum particulates for enhanced specific impulse. This mixture was cast into a cylindrical chamber with a star-shaped core geometry, optimizing burn uniformity and thrust profile to deliver a brief, high-intensity pulse rather than a sustained burn. Encased in lightweight titanium alloy housings pressure-tested to withstand reentry-induced thermal stresses exceeding 1,000 degrees Celsius, the engines were clustered symmetrically around the capsule's nadir, angled outward at 45 degrees to generate both vertical thrust and a stabilizing radial component. Redundant igniters, powered by thermal batteries activated post-chute deployment, ensured fail-safe initiation, while frangible nozzles directed the exhaust plume away from the parachute risers and recovery beacon antennas.\n\nThe choreography of ignition was a marvel of autonomous avionics, orchestrated by a ruggedized proximity radar altimeter embedded in the capsule's avionics bay. As the parachuted capsule drifted toward the predetermined recovery ellipse—often vast swaths of desert or oceanic drop zones calibrated for minimal civilian interference—the altimeter continuously polled the terrain contour below. At a preset threshold of 2 to 5 meters above ground level, accounting for variables like parachute oscillation and wind shear, the system triggered the engines via a hardened fire-control sequencer. Firing duration was exquisitely brief: 0.1 to 0.3 seconds, imparting a counter-thrust of approximately 10 to 20 kN total, sufficient to slash vertical velocity from 8-12 m/s to under 1 m/s. This millisecond-precision timing, honed through thousands of drop tests from C-130 Hercules platforms and high-altitude balloons, minimized dust kick-up in arid zones and prevented \"bounce\" on uneven surfaces, all while the radar's Doppler processing discriminated true ground returns from false echoes off vegetation or waves.\n\nIn operational practice across the Cobalt-M missions from 2004 to 2015, these engines proved their mettle time and again, elevating capsule recovery success rates to over 95 percent. Early flights, such as those in the 2004-2006 shakedown series launched atop Zenit-3SLB rockets from Baikonur, revealed teething issues like occasional thrust asymmetry from propellant voids, prompting iterative reforms in grain casting and quality assurance at the primary fabrication facility in Samara. By the mid-program zenith around 2010, enhancements included pyrotechnic thrust-vectoring vanes for finer attitude control and integration with GPS-augmented drogue steering, allowing real-time adjustments to align the capsule over softer terrain. A notable evolution came in 2012 with the adoption of eco-tuned propellants reducing hydrochloric acid emissions, aligning with evolving international environmental protocols for splashdown recoveries in the Black Sea. Anecdotal accounts from recovery teams paint vivid pictures: engines thundering to life with a staccato roar, billowing white smoke veils that shrouded the capsule like a spectral apparition before it kissed the earth, payloads emerging unscathed with film spools intact and telemetry logs pristine.\n\nBeyond mere functionality, the soft-landing engines embodied the Cobalt-M program's ethos of resilient minimalism—forgoing complex liquid-fueled alternatives or inflatable airbags in favor of reliable, mass-producible solids that could endure the program's austere logistics chain. Their design philosophy echoed Cold War-era imperatives updated for the digital age: simplicity for wartime surge production, autonomy to obviate ground links in contested airspace, and modularity for rapid upgrades. In one harrowing 2008 incident over the Gobi recovery grid, a capsule endured a partial chute failure, plummeting at double nominal speed; the engines, sensing the peril via altimeter overload, fired with unerring fidelity, averting total loss and salvaging irreplaceable imagery of transient geopolitical maneuvers. Such reliability underpinned the program's endurance through shifting geopolitical sands, from initial KH-11 augmentation roles to later signals intelligence hybrids, ensuring that even as orbital assets evolved, the terrestrial handoff remained a ballet of engineered grace.\n\nUltimately, the soft-landing engines closed the recovery loop with surgical elegance, bridging the gulf between stratospheric fury and earthly retrieval. They not only cushioned the physical descent but safeguarded the ephemeral intelligence value encoded in silver-halide grains—data that fueled strategic decisions across a decade of flux. As the Cobalt-M era waned by 2015, supplanted by fully digital successors, these engines lingered as a testament to analog ingenuity, their fiery kiss upon the ground a ritual that preserved secrets where parachutes left off.\n\nWhile the solid-propellant soft-landing engines provided a critical buffer against the harsh realities of terrestrial reentry, ensuring the Cobalt-M capsules arrived intact amid the vast, unforgiving expanses of the American West, the true test of the program's resilience lay in the hands of the men and women tasked with their recovery. These search and rescue (SAR) teams, drawn from a cadre of elite military and civilian specialists, embodied the human element that bridged the gap between orbital precision and earthly retrieval. Operating under the umbrella of the U.S. Air Force's 58th Rescue Squadron and augmented by contractors from firms like Evergreen Helicopters, these operatives transformed the high-stakes gamble of capsule descent into a symphony of coordinated human endeavor, where split-second decisions and unyielding grit often meant the difference between mission success and classified obscurity.\n\nTraining for these teams began long before any capsule streaked through the atmosphere, forged in the arid badlands of Utah's Dugway Proving Ground and the rugged terrains of Nevada's Test and Training Range. Recruits, typically pararescue jumpers (PJs) with backgrounds in special operations, underwent a grueling regimen that simulated the chaos of real-world recoveries. For weeks on end, they practiced parachute insertions onto mock impact sites marked by battered boilerplate capsules, honing skills in rapid assessment: scanning for structural integrity, neutralizing any residual hypergolic propellants from the retro-rockets, and securing the payload bay against environmental hazards. Night operations were particularly brutal, with teams navigating by infrared beacons and GPS waypoints under pitch-black skies, their headlamps cutting through dust storms whipped up by rotor wash from hovering HH-60 Pave Hawks. Survival training emphasized self-reliance in remote zones—building improvised shelters from capsule debris, purifying water from sporadic desert springs, and evading simulated adversaries, a nod to the classified nature of Cobalt-M's reconnaissance intelligence. Psychological conditioning drilled home the mantra of \"anytime, anywhere,\" preparing them for capsules that might plummet into boulder-strewn canyons, snow-swept plateaus, or thorny scrublands far from roads, where a single misplaced step could spell disaster.\n\nDeployment protocols were a masterclass in interagency orchestration, triggered the instant a capsule's S-band beacon pulsed its recovery signal. Ground stations at Vandenberg Space Force Base triangulated the landing ellipse—a probabilistic footprint spanning hundreds of square miles—while orbiting assets from the Space Surveillance Network refined the fix to within kilometers. Alerts cascaded through a dedicated ops center at Beale Air Force Base, where mission controllers synchronized SAR assets with National Guard units, BLM rangers, and even local ranchers familiar with the backcountry. A typical response unfolded in phases: forward spotters in fixed-wing OV-10 Broncos or drones circled the zone, painting targets with laser designators; insertion teams rappelled from Black Hawks onto the hot zone; and recovery birds—CH-47 Chinooks slung with Stokes litters and cargo nets—hovered in exfil support. In the early years of the program, from 2004 to 2008, these operations leaned heavily on human spotters, whose eyes caught the glint of a capsule's heat shield amid sagebrush where electronics faltered. By the mid-2010s, integration of ruggedized tablets linked to real-time satellite imagery allowed teams to overlay descent telemetry on augmented-reality visors, but it was the PJs' instincts that sealed the recoveries—disarming booby-trap ordnance, wrestling 500-pound capsules onto hoist lines, and medevacing injured teammates after rotor blades clipped ridgelines.\n\nThe human stories etched into Cobalt-M's operational lore underscored the raw valor required. Take the 2007 recovery in the Fishlake National Forest, where PJ Master Sergeant Elena Vasquez led a four-man team through a predawn blizzard to secure Capsule CM-47, its soft-landers having fired perfectly but landing amid a talus field that shredded the primary chute. Vasquez's crew, frostbitten and oxygen-deprived at 10,000 feet, jury-rigged a harness from static lines and hauled the payload upslope meter by meter, their radios crackling with encouragement from orbiting controllers. Or consider the 2012 incident over the Mojave, where a guidance glitch scattered debris across a minefield-riddled dry lake bed; team lead Captain Marcus Hale, a former SEAL, crawled through the hazards on his belly, using a probe to verify safe paths before signaling the helo for pickup. These weren't anomalies but the norm, with SAR personnel logging over 150 recoveries across the program's lifespan, each demanding a blend of technical prowess and primal endurance. Attrition was high—sprains, fractures, and heat exhaustion sidelined dozens—yet rotation schedules and cross-training with NASA's astronaut rescue teams kept the pipeline robust.\n\nAs Cobalt-M evolved, so did its SAR doctrine, reflecting broader shifts in space operations. Early reliance on ad-hoc mobilizations gave way to pre-staged forward operating bases at places like Tonopah and Winnemucca, stocked with cold-soak tents, fuel bladders, and classified data links. Joint exercises with the Coast Guard honed overwater contingencies for Pacific splashdowns, while unmanned aerial vehicles took on initial surveys, freeing humans for the delicate extraction phase. Yet amid technological strides, the program's architects never lost sight of the indispensable human core: the PJ who cradled a flickering beacon through a sandstorm, the rigger who lashed a capsule amid 60-knot gusts, the medic who stabilized a teammate's compound fracture en route to Nellis AFB. In remote areas where satellites ended and survival began, these guardians of the sky's secrets ensured that Cobalt-M's intelligence haul—from crisp electro-optical imagery of adversarial maneuvers to signals intercepts of fleeting launches—reached analysts unscathed, perpetuating the reconnaissance legacy through sheer force of will. Their coordination wasn't merely logistical; it was the heartbeat of recovery, pulsing with the unquantifiable spirit that turned potential catastrophes into triumphs.\n\nFollowing the triumphant recoveries orchestrated by the elite search and rescue teams in the most unforgiving terrains—from the windswept steppes of Central Asia to the dense canopies of Pacific atolls—the returned capsules of the Cobalt-M reconnaissance satellites entered a critical phase of their lifecycle: post-flight refurbishment. This process, conducted primarily at secure facilities within the program's primary ground stations and specialized aerospace depots, represented a pivotal commitment to sustainability and efficiency in an era of constrained budgets and escalating mission demands. Far from being discarded as mere expendables, these capsules were meticulously evaluated for hardware reuse, embodying the Cobalt-M program's philosophy of maximizing return on investment through iterative refurbishment rather than wholesale replacement.\n\nThe refurbishment workflow began immediately upon arrival at the processing hangars, where teams of engineers and technicians, clad in sterile cleanroom suits, initiated a comprehensive disassembly under controlled environmental conditions to prevent contamination of sensitive components. Each capsule, battered yet resilient after withstanding the inferno of atmospheric reentry, was methodically broken down into its constituent modules: the ablative heat shield, recovery parachute assembly, attitude control thrusters, avionics bays, structural frame, and the central payload compartment housing the reconnaissance optics or data recorders. Initial visual and non-destructive inspections using borescopes, ultrasonic scanners, and X-ray imaging revealed the extent of thermal stress, impact damage, and exposure to harsh reentry plasmas. This phase often uncovered dramatic tales of survival—charred outer skins peeling away to expose underlying titanium frames that had endured temperatures exceeding 2,000 degrees Celsius, or parachutes tangled but salvageable after deployment at hypersonic speeds.\n\nA key determinant in the reuse equation was the design philosophy of the Cobalt-M capsules themselves, which evolved significantly from the program's inception in 2004. Early missions, such as Cobalt-M1 through M4, leaned toward a near-single-use paradigm for the reentry vehicles, influenced by the imperative for reliability in unproven recovery operations. Here, the primary payload modules—encasing high-resolution film cassettes or encrypted data modules—were invariably treated as expendable, their contents extracted under nitrogen-purged gloveboxes before secure vaulting for intelligence analysis. However, non-payload hardware showed promise: structural longerons and bulkheads, fabricated from high-strength aluminum-lithium alloys, underwent cryogenic cleaning and fatigue testing, with overhauls enabling their redeployment on subsequent flights after certification. By the mid-2000s, as recovery success rates climbed above 95 percent thanks to refined orbital decay predictions and SAR enhancements, the program shifted gears. Refurbishment protocols were formalized under a \"Reuse Readiness Index,\" a tiered assessment that classified components into green (fully reusable), yellow (conditionally reusable with upgrades), and red (single-use discard) categories.\n\nCentral to this evolution was the treatment of the thermal protection system, a marvel of materials engineering comprising phenolic-impregnated carbon ablator tiles and reinforced nose cone assemblies. While initial hype around full reusability akin to the Space Shuttle proved overly optimistic—ablation layers often eroded by 40-60 percent per mission—these shields were not consigned to scrap. Technicians employed laser ablation profiling and plasma torch reshaping to restore contours, followed by recoating with advanced silica-based insulators derived from lessons learned in suborbital tests. Thruster pods, powered by hydrazine monopropellant systems, fared even better; valves and nozzles were flushed, pressure-tested, and requalified, their hypergolic ignition chambers showing minimal wear due to the capsules' precise deorbit burns. Avionics presented a mixed bag: radiation-hardened computers and inertial measurement units (IMUs), shielded against the Van Allen belts' onslaught, routinely passed electromagnetic interference (EMI) revalidation and software reloads, extending their service life across multiple missions. In contrast, beacons, pyrotechnic sequencers, and drogue parachutes were steadfastly single-use, their one-shot reliability paramount to avoiding mid-descent failures that could doom an entire recovery.\n\nThis selective reuse strategy yielded profound operational dividends, transforming the Cobalt-M fleet from a fleet of fire-and-forget capsules into a semi-reusable constellation. By 2008, with the introduction of the Block II capsules on missions M12-M15, refurbishment cycles shortened from six months to under 90 days, incorporating automated robotic disassembly arms and AI-driven anomaly detection to accelerate turnaround. Historical records from the program's declassified archives highlight standout examples: the reentry vehicle from Cobalt-M7, recovered intact from the Gobi Desert in 2006, had its frame and avionics refurbished for reuse on M10, enduring a second reentry with only minor shield patchwork. Similarly, the attitude control module from M19 (2011) flew thrice more after progressive upgrades, logging over 1,200 hours of orbital maneuvering cumulatively. Challenges abounded, however—saltwater recoveries from ocean splashdowns corroded electronics beyond salvage, prompting the development of conformal polymer coatings by 2012, while micrometeoroid punctures in high-altitude reentries occasionally mandated full module swaps.\n\nYet, not all components escaped the single-use fate. The payload bays, cradling the program's crown jewels—electro-optical imagers or synthetic aperture radar data recorders—were hermetically sealed upon return and dissected only for data harvest, their optics plagued by outgassing residues and focal plane distortions from microgravity vibrations. Parachute canisters and main chute textiles, stressed by dynamic pressures exceeding 10 g's, were retired post-mission to mitigate the risk of frayed lines unraveling at 300 meters per second descent rates. This pragmatic delineation underscored a broader truth in space operations: true reusability demanded balancing mission assurance against refurbishment costs, a calculus refined through iterative flight data.\n\nAs the Cobalt-M program progressed into its later years (2013-2015), refurbishment matured into a high-fidelity industrial process, with dedicated \"capsule farms\" at remote test ranges simulating reentry wear via arc-jet facilities and vibration tables. Metrics of success emerged organically: by program's end, approximately 70 percent of non-payload mass from returned capsules achieved reuse, a figure that rivaled contemporary expendable launchers' recovery ambitions. This hardware recycling not only curbed proliferation of space debris precursors but also fostered a culture of stewardship, ensuring that each recovered artifact contributed to the next orbit. In essence, post-flight refurbishment transcended mere maintenance; it was the unsung engine of the Cobalt-M's endurance, proving that even in the disposable realm of reconnaissance satellites, second chances could redefine operational longevity.\n\nAs the Cobalt-M program drew to a close around 2015, questions lingered not only about the fate of its returned capsules—whether their intricate film mechanisms and structural components could be refurbished for subsequent missions or were destined as single-use relics of a bygone era—but also about the broader trajectory of Russian optical reconnaissance capabilities. The program's reliance on physically reentering film canisters underscored its heritage in Cold War-era technology, where high-resolution imagery demanded tangible media delivered back to Earth. This methodological anchor, while proven effective for capturing detailed panchromatic and spectral data over vast theaters, imposed inherent limitations: vulnerability to capsule recovery failures, delays in intelligence dissemination, and the logistical burdens of deorbit burns and parachute-assisted splashdowns in remote oceanic zones. It was against this backdrop that the Persona class of satellites emerged as the designated successor, inaugurating a new chapter in Russia's space-based intelligence architecture by transitioning from analog film retrieval to fully digital electro-optical transmission.\n\nThe Persona satellites represented a deliberate evolution from the Cobalt-M's film-centric paradigm. Where Cobalt-M vehicles, such as the Cobalt-M No. 4, maneuvered in low Earth orbits around 260-280 kilometers altitude to expose 35mm or larger film cassettes capturing resolutions down to the sub-meter level, Persona dispensed with such physical media altogether. Instead, it employed advanced charge-coupled device (CCD) arrays and pushbroom scanners to generate real-time digital imagery, downlinked via high-bandwidth S-band or X-band channels to ground stations. This shift eliminated the need for reentry vehicles, rendering moot the debates over capsule refurbishment that had characterized Cobalt-M operations. Persona’s imaging suite, optimized for both daylight and limited low-light conditions, prioritized stereo panchromatic mapping at around 1-meter ground sample distance, complemented by multispectral bands for enhanced target discrimination—capabilities that echoed Cobalt-M's strengths but with instantaneous data relay, slashing the intelligence cycle from days or weeks to hours.\n\nOperationally, the comparison highlights a profound maturation in mission profiles and resilience. Cobalt-M satellites, with their modular bus derived from the Yantar lineage, typically endured multi-year campaigns punctuated by periodic film ejections, achieving multiple returns per vehicle before orbital decay or retirement. Their sun-synchronous orbits facilitated repeatable coverage of high-priority areas like Europe, the Middle East, and Asia-Pacific hotspots, but weather dependency and film stock constraints often dictated imaging windows. Persona, by contrast, leveraged a more agile three-axis stabilized platform with onboard data processing and selective downlinking, allowing operators to task the satellite dynamically via uplink commands. This electro-optical approach proved its mettle, providing persistent surveillance without the attrition risk of capsule deployments. Subsequent iterations, including the upgraded Persona-R variant, further refined this model with improved signal processing and anti-jamming measures, addressing vulnerabilities exposed in Cobalt-M's era, such as susceptibility to electronic countermeasures during reentry tracking.\n\nTechnologically, the handover from Cobalt-M to Persona encapsulated Russia's push toward digital sovereignty in space reconnaissance amid evolving geopolitical demands. The older system's film-return methodology, while excelling in raw resolution and immunity to downlink disruptions—film could capture ultra-high-fidelity details impervious to bandwidth limitations—suffered from scalability issues as global threats proliferated. Persona countered this by integrating cryogenic coolers for infrared augmentation and onboard storage buffers holding gigabytes of compressed imagery, enabling burst-mode collection over denied areas. Cost-wise, though exact figures remain classified, the transition likely amortized development expenses through reusability; a single Persona could sustain operations far longer than a Cobalt-M's film-limited lifespan, obviating the manufacturing cadence of bespoke capsules. Moreover, Persona's ground segment evolved to ingest streaming data directly into analytic pipelines, fostering fusion with synthetic aperture radar feeds from complementary assets like Lotos-S1, a synergy absent in Cobalt-M's standalone returns.\n\nThis comparative lens reveals not just incremental upgrades but a strategic pivot: Cobalt-M perfected the art of physical delivery in an age of analog supremacy, bridging the post-Soviet reconnaissance drought with reliable, if archaic, performance. Persona, however, heralded the digital epoch, where speed and integration trumped tangibility. Challenges persisted—but the class's deployment signaled Russia's alignment with global peers like the U.S. KH-11 series or France's Pléiades, emphasizing real-time battlespace awareness. By 2015, as the last Cobalt-M faded from orbit, Persona had not only inherited its mantle but redefined it, ensuring continuity in Russia's orbital eyes while propelling the program into a future unbound by the pull of gravity on celluloid. This evolution underscores a broader narrative in space operations: the inexorable march from mechanical ingenuity to photonic precision, where yesterday's capsules pave the way for tomorrow's data streams.\n\nAs the Cobalt-M program reached its later iterations, the technological pivot toward electro-optical systems exemplified by the Persona class satellites not only promised enhanced resolution and flexibility but also ignited a broader debate on the economic underpinnings of reconnaissance architecture. This shift from analog film-return mechanisms to digital transmission constellations underscored a fundamental tension in space-based intelligence gathering: the trade-offs between proven, low-entry-barrier legacy systems and ambitious, capital-intensive modern alternatives. An economic analysis of the Cobalt-M initiative reveals a program that, while operationally robust, embodied the fiscal conservatism of post-Soviet Russian space ambitions, prioritizing incremental improvements over revolutionary overhauls amid chronic budget volatility.\n\nAt its core, the Cobalt-M series leveraged a film-return paradigm that minimized upfront development expenditures. Drawing from the Zenit and Yantar lineages, the program's architecture relied on reentry capsules to physically deliver exposed photographic film back to Earth, obviating the need for sophisticated onboard data processing or high-bandwidth downlink systems. This approach allowed for relatively modest satellite bus designs, with costs concentrated in reliable propulsion for deorbit maneuvers and robust thermal protection for capsule recovery. Launch vehicles like the Soyuz or Kosmos-3M, already staples in the Russian inventory, further streamlined expenses by enabling rapid integration and deployment cycles. Ground infrastructure, too, was repurposed from Cold War-era facilities at places like Plesetsk and Kheifiz, where film processing labs and parachute recovery teams operated with established efficiency. In an era of fluctuating ruble valuations and U.S. sanctions indirectly pressuring aerospace funding, this frugality ensured the program's longevity, sustaining a fleet capable of delivering high-fidelity panchromatic imagery across multiple spectral bands without the fiscal shock of a full digital redesign.\n\nYet, the cost-per-image metric for Cobalt-M painted a more nuanced picture, one marred by the inherent inefficiencies of physical return logistics. Each mission's imaging capacity was finite, dictated by the volume of film cassettes—typically yielding hundreds rather than thousands of frames per sortie—before the imperative to deorbit and recover. Recovery operations themselves imposed substantial recurring costs: specialized aircraft or ships stationed in remote oceanic zones, weather-dependent retrieval windows that often led to mission extensions, and the labor-intensive chemical development process prone to degradation from radiation exposure or handling errors. Delays in film return, sometimes spanning days or weeks, compounded opportunity costs, as time-sensitive intelligence lost urgency in fast-evolving geopolitical contexts like the 2008 Russo-Georgian conflict or Syrian theater monitoring. Moreover, the single-satellite deployment model left gaps in coverage during recovery downtimes, necessitating redundant launches that eroded per-mission economies of scale. While exact figures remain classified, the cumulative toll of these factors positioned Cobalt-M's cost-per-image as competitive only for niche, high-value targets where analog stereo-photogrammetry excelled, but less so against the voracious data appetites of contemporary warfare.\n\nIn stark contrast, the electro-optical revolution heralded by Persona demanded a seismic upfront investment, emblematic of the high-stakes gamble on digital constellations. Developing hyperspectral sensors, agile pointing gimbals, and resilient solid-state storage required billions in R&D, funneled through Roscosmos and military-industrial conglomerates like ISS Reshetnev. The constellation approach—multiple satellites in sun-synchronous orbits for persistent revisit rates—amplified launch cadence, relying on costlier Proton-M or Angara vehicles to loft heavier payloads. Ground segments expanded dramatically, incorporating secure laser communication networks, AI-driven image exploitation suites, and global data centers to handle petabytes of real-time downlink. This capital intensity strained Russia's federal space budget, already burdened by ISS commitments and GLONASS expansion, prompting phased rollouts and hybrid operations where Cobalt-M bridged gaps until Persona achieved initial operational capability around 2013.\n\nThe cost-effectiveness debate thus hinges on lifecycle amortization. Film-return systems like Cobalt-M offered a low barrier to entry, with per-unit production costs potentially a fraction of digital counterparts, enabling a \"pay-as-you-go\" model suited to austere fiscal environments. Over the program's decade-plus span from 2004 to 2015, this yielded a steady stream of actionable imagery for strategic reconnaissance, from Arctic border patrols to Central Asian infrastructure mapping, without the risk of technological obsolescence baked into massive sunk costs. Digital systems, however, promised exponential returns through scalability: once fielded, each satellite generated orders of magnitude more images per orbit, with near-instantaneous dissemination slashing downstream processing expenses and enabling automated analytics. The break-even point favored constellations in high-demand scenarios, where reduced latency translated to tactical multipliers—evident in Persona's role during Ukraine operations post-2014. Yet for Russia, constrained by export controls on key components like CCD arrays, the transition exposed vulnerabilities: overruns from import substitutions and integration delays inflated digital costs, prolonging reliance on film veterans.\n\nBroader programmatic economics further illuminated Cobalt-M's value proposition. International partnerships, though limited, occasionally offset burdens—shared launches with allies like Kazakhstan mitigated per-mission overheads—while dual-use civilian applications, such as mapping for Gazprom pipelines, generated ancillary revenues. The program's modularity facilitated upgrades, like enhanced film emulsions in later blocks, extending utility without full redesigns. Conversely, digital pursuits incurred non-recurring expenses for software hardening against cyber threats and orbital debris mitigation, alongside the imperative for frequent replenishment to counter rapid sensor commoditization globally. In a comparative lens, Cobalt-M exemplified \"good enough\" economics for a peer competitor facing U.S. KH-11/12 dominance, where film persistence outperformed digital in jammed or denied environments, albeit at the expense of volume.\n\nUltimately, the Cobalt-M era encapsulated a pragmatic calculus: film-return's cost-per-image, burdened by logistics yet anchored in affordability, deferred the digital leap until economic maturation allowed. As Russian space budgets stabilized post-2010, bolstered by oil windfalls and state consolidation, the pivot to Persona validated this sequencing—harnessing legacy efficiencies to underwrite future scalability. This evolution not only sustained reconnaissance primacy amid fiscal headwinds but also underscored a timeless axiom in space economics: the most cost-effective system is the one that endures, adapting incrementally until paradigm shifts align with strategic solvency. The program's ledger, therefore, closes not as a relic of analog austerity, but as a testament to resilient fiscal engineering in the unforgiving arena of orbital intelligence.\n\nThe operational tempo of the Cobalt-M Reconnaissance Satellite Program, as reflected in its launch cadence from 2004 to 2015, offers a vivid counterpoint to the economic debates surrounding film-return systems and digital constellations. While cost-per-image analyses often dominated budgetary deliberations, the rhythm of launches revealed the program's relentless drive to maintain persistent surveillance capabilities amid evolving global threats. Spanning over a decade, the Cobalt-M effort saw a deliberate buildup of orbital assets, with launches paced to replenish aging satellites, incorporate incremental technological upgrades, and respond to intelligence community priorities. This cadence was not uniform but pulsed with strategic intensity, marked by distinct peaks that underscored periods of heightened operational urgency.\n\nThe inaugural phase, beginning in 2004, established a foundational rhythm of roughly annual deployments, allowing engineers and operators to refine deployment techniques, orbital insertion profiles, and ground station integrations. These early missions focused on proving the Cobalt-M's hybrid electro-optical and synthetic aperture radar payloads, which balanced the reliability of film cassettes with emerging digital downlink experiments. By mid-decade, however, the program accelerated noticeably, culminating in the pronounced peak of 2007. That year represented a watershed, driven by post-Iraq War reconnaissance demands and the need to offset constellation attrition from micrometeorite impacts and nominal de-orbiting. Multiple launches in quick succession—clustered around key windows to minimize launch vehicle bottlenecks—bolstered the program's mid-inclination orbits, ensuring overlapping coverage over high-interest regions in the Middle East and Asia-Pacific. This surge not only doubled the typical yearly output but also tested the National Reconnaissance Office's supply chain resilience, from Kodak film production ramps to Raytheon sensor calibrations.\n\nFollowing this intensity, the cadence moderated into a steady sustainment pattern through 2008-2010, with launches spaced to align with predictable satellite lifespans of five to seven years. This interlude allowed for data-driven refinements, such as enhanced attitude control systems to counter solar array degradation and improved reentry vehicle designs for secure film recovery over Pacific splashdown zones. Yet, geopolitical flashpoints reignited momentum, leading to the second major peak in 2011. Amid rising tensions in the South China Sea and Arab Spring upheavals, the program executed a flurry of deployments that refreshed nearly a quarter of the constellation in under eighteen months. These missions introduced subtle evolutionary tweaks, like hardened electronics against electronic warfare threats and auxiliary digital burst transmitters as a hedge against full film dependency. The 2011 peak exemplified the Cobalt-M's agility, leveraging Delta IV and Atlas V heavy-lift manifests to sidestep delays, while ground crews at Vandenberg and Cape Canaveral honed rapid turnaround procedures.\n\nAs the program entered its twilight years, a final, urgent push materialized in 2014-2015, capping the decade with another spike in launch frequency. This endgame acceleration was precipitated by accelerated battery failures in older birds and an intelligence surge requirement tied to emerging cyber-physical threats. Operators prioritized high-value orbits, stacking payloads to maximize per-launch yield and incorporating last-generation Cobalt-M variants with proto-real-time data relays. The 2014-2015 crescendo not only sustained coverage through the program's sunset but also facilitated a orderly transition to successor architectures, archiving petabytes of panchromatic and multispectral imagery in the process. Across these peaks—2007's foundational surge, 2011's responsive escalation, and the 2014-2015 valedictory drive—the launch cadence chronicled the Cobalt-M's evolution from experimental outlier to cornerstone of national technical means, adapting to fiscal constraints, technological maturation, and the inexorable demands of strategic reconnaissance. This operational frequency, in essence, mapped the heartbeat of a program that prioritized endurance over extravagance, ensuring America's overhead eyes remained unblinking.\n\nAs the Cobalt-M program's launch cadence reached its crescendo with the intensive final push of 2014-2015—capping off earlier peaks in 2007 and 2011—the constellation achieved a maturity that marked not just operational endurance but a profound evolutionary milestone in Russian space reconnaissance. Over more than a decade, from its inaugural deployment in 2004, the program had transformed a heritage deeply rooted in Soviet-era designs into a robust, adaptable network capable of meeting the multifaceted demands of 21st-century intelligence, surveillance, and reconnaissance (ISR) missions. This evolution was no mere incremental upgrade; it represented a deliberate bridge across a technological chasm, fusing the proven reliability of Cold War architectures with contemporary advancements in sensor technology, orbital mechanics, and ground integration.\n\nAt its inception, Cobalt-M inherited the modular bus design philosophy traceable to the Zenit and Yantar series of the 1970s and 1980s, which emphasized ruggedness, rapid reusability, and cost-effective production under the stringent constraints of a post-Soviet space industry. These early satellites, often masked under Kosmos designations, relied on film-return capsules and basic electro-optical systems that demanded physical recovery for data exploitation—a relic of an era when digital bandwidth was scarce and launch vehicles like the Soyuz or Zenit-2 were the workhorses of the Soviet military-industrial complex. Yet, by the mid-2000s, as Russia grappled with the atrophy of its space infrastructure following the USSR's dissolution, Cobalt-M engineers at organizations like TsSKB-Progress and NPO Lavochkin introduced pivotal modifications: the shift to digital imaging with high-resolution CCD arrays, enhanced onboard storage via solid-state recorders, and X-band downlink capabilities that obviated the need for risky reentry maneuvers. These changes were iteratively refined across dozens of missions, with each launch cycle yielding data on everything from terrain mapping in contested regions to real-time maritime surveillance in the Arctic and Pacific theaters.\n\nThe program's resilience in the face of systemic challenges further underscores its triumph. Economic turbulence in the late 2000s, coupled with the 2010-2011 delays stemming from Zenit-3SL launch vehicle adaptations at the Sea Launch platform, tested the program's mettle. Proton-M and Rokot boosters stepped in as reliable alternatives, demonstrating the flexibility inherent in Russia's vertically integrated launch ecosystem. By 2011's surge, Cobalt-M satellites boasted improved agility with reaction wheels for precise pointing, synthetic aperture radar (SAR) payloads for all-weather operations, and encrypted data links interoperable with the GLONASS navigation constellation—capabilities that Soviet predecessors could scarcely imagine. The 2014-2015 finale, with its accelerated replenishment of the low Earth orbit (LEO) constellation, ensured persistent coverage exceeding 70% global revisit rates for high-priority targets, a feat validated through declassified mission reports and third-party orbital tracking.\n\nStrategically, Cobalt-M's success recalibrated Russia's space posture amid geopolitical shifts. It filled critical voids left by the retirement of aging Mk-4 and Lotos systems, providing the Russian Armed Forces with independent, sovereign ISR assets unencumbered by foreign dependencies. This was particularly vital during operations in Syria and Ukraine, where Cobalt-M-derived intelligence informed precision strikes and border monitoring. Economically, the program revitalized domestic supply chains, sustaining thousands of jobs at ISS Reshetnev and Khrunichev while fostering spin-offs in civilian Earth observation via the Resurs-P series. Technologically, it laid the groundwork for successors like the Lotos-S and Razdan platforms, incorporating lessons in radiation-hardened electronics and autonomous maneuvering to counter emerging anti-satellite threats.\n\nIn retrospect, the Cobalt-M program stands as an unqualified success—a testament to Russian ingenuity in perpetuating and modernizing a legacy forged in the fires of superpower rivalry. By 2015, it had not only bridged the yawning gap between Soviet technological paradigms and the exigencies of a multipolar world but had elevated Russian space reconnaissance to a peer-competitive echelon. With over a decade of sustained operations, minimal on-orbit failures, and a constellation that outlasted initial projections by years, Cobalt-M ensured that Russia's gaze from the stars remained sharp, sovereign, and strategically decisive. As the program yielded to next-generation architectures, its chronicle endures as a cornerstone of national space heritage, illuminating the path from yesterday's triumphs to tomorrow's orbital dominion.\n\n### Appendix: Launch Site Specifics\n\nNestled in the dense taiga forests of northern Russia's Arkhangelsk Oblast, the Plesetsk Cosmodrome stands as a cornerstone of the Russian space program's military heritage, particularly for missions demanding high-inclination orbits ideal for reconnaissance satellites like those in the Cobalt-M series. Established in the late 1950s as a secretive launch facility during the height of the Cold War, Plesetsk was purpose-built to support polar and sun-synchronous trajectories inaccessible from more equatorial sites like Baikonur, making it the indispensable hub for the Soyuz/Cobalt-M stack throughout the program's 2004-2015 operational lifespan. Its remote location, some 800 kilometers north of Moscow, not only provided strategic isolation but also leveraged the Earth's rotational dynamics for efficient access to orbits between 62° and 98° inclination—perfect for persistent imaging over Russia's vast northern territories and beyond. For the Cobalt-M missions, Plesetsk's infrastructure evolved into a finely tuned ecosystem, where every pad, building, and procedure was optimized for the reliable deployment of these electro-optical and radar reconnaissance payloads atop Soyuz-2.1v or earlier Soyuz-U variants.\n\nAt the heart of Plesetsk's Soyuz/Cobalt-M operations lay Launch Complex 41 (LC-41), a veteran pad that became synonymous with the program's successes. Reconstructed in the early 2000s to accommodate the Soyuz-U configuration used in the initial Cobalt-M flights, LC-41 featured a robust umbilical tower rising over 50 meters, equipped with cryogenic fueling arms for the vehicle's liquid oxygen and kerosene stages, as well as electrical and telemetry interfaces critical for final countdown sequences. The pad's service tower, a gantry-style structure with multiple access levels, allowed technicians to perform late-access payload checks on the Cobalt-M satellite nestled within its composite fairing, ensuring the reconnaissance module's sensitive optics and antennas remained pristine amid the harsh subarctic climate. Rail-mounted service platforms enabled precise positioning around the 49-meter-tall stack, facilitating the integration of the Fregat upper stage when required for precise orbital insertions—a necessity for some Cobalt-M variants targeting Resurs-class imaging resolutions. Environmental controls, including heated enclosures and de-icing systems, mitigated the cosmodrome's frequent snowfalls and temperatures dipping below -40°C, preserving the Soyuz/Cobalt-M assembly's integrity from rollout to ignition.\n\nAdjacent to LC-41, the payload integration and fueling facilities at Building 130MI exemplified Plesetsk's tailored adaptations for reconnaissance missions. This sprawling horizontal integration hall, spanning several thousand square meters, served as the nerve center where Cobalt-M satellites—encased in their protective shrouds—were mated to the Soyuz third stage. Equipped with overhead cranes capable of handling up to 20-ton payloads, vibration test stands simulating launch dynamics, and cleanroom environments meeting ISO Class 8 standards, the building ensured the satellites' high-resolution cameras and synthetic aperture radars underwent rigorous pre-launch verification. Fueling bays for hypergolic propellants used in attitude control systems were isolated with blast-proof walls, a precautionary measure honed from decades of military satellite deployments. From here, the fully stacked vehicle traversed a 1.5-kilometer rail transporter to the pad, a slow procession under armed escort that underscored Plesetsk's status as a restricted military zone, with razor-wire perimeters and round-the-clock surveillance safeguarding sensitive reconnaissance hardware.\n\nPlesetsk's logistical backbone extended to its rail and road networks, which funneled Soyuz boosters and Cobalt-M payloads from distant factories—boosters from the Progress plant in Samara, satellites from ISS Reshetnev in Zheleznogorsk—directly into secure storage bunkers. These reinforced structures, buried partially underground to withstand potential threats, maintained controlled humidity and temperature for the stack components, preventing corrosion on the Soyuz's corrugated aluminum airframes or degradation of the Cobalt-M's infrared sensors. Propellant farms nearby stored vast quantities of RP-1 kerosene and LOX in spherical tanks, serviced by insulated pipelines that snaked across the tundra, with redundant pumping stations to counter the site's permafrost challenges. During the Cobalt-M era, these systems supported a cadence of up to four launches annually from Plesetsk, each sequence choreographed with military precision: from satellite arrival via An-124 transport aircraft at the on-site airstrip, through stack-up rehearsals, to T-minus ignition amid the glow of arc lamps piercing the polar night.\n\nBeyond the physical plant, Plesetsk's telemetry and tracking infrastructure was pivotal for Cobalt-M's post-launch phase. Ground stations arrayed around the cosmodrome, linked to the national GLONASS network, provided real-time data on separation events and initial orbit acquisition, confirming the satellites' deployment into their 650-700 km altitudes. Mobile command posts, deployable for range safety, monitored downrange trajectories over the Barents Sea, ensuring compliance with international overflight protocols while prioritizing Russian strategic interests. The site's evolution during the Cobalt-M program—incorporating digital flight control systems and automated checkout procedures—mirrored the broader transition from Soviet rigidity to modern efficiency, with upgrades funded by Roscosmos to handle the Soyuz-2.1v's enhanced avionics. This infrastructure not only enabled the flawless execution of 12 successful Cobalt-M launches from Plesetsk but also cemented the cosmodrome's role as the unsung enabler of Russia's reconnaissance renaissance, bridging analog-era reliability with digital-era precision in the unforgiving Arctic expanse.\n\nAppendix: Telemetry Standards\n\nThe robust ground infrastructure at Plesetsk Cosmodrome, meticulously adapted for the Soyuz/Cobalt-M launch stack, relied intrinsically on standardized telemetry protocols to bridge the satellite's orbital operations with mission control. These telemetry standards formed the backbone of data downlink, ensuring that critical housekeeping information, payload reconnaissance imagery, and mission status updates flowed seamlessly from the Cobalt-M satellites to receiving stations during their operational lifespan from 2004 to 2015. Designed with the rigors of reconnaissance missions in mind—where latency, reliability, and data integrity could mean the difference between mission success and failure—these standards encompassed precise radio frequency allocations, modulation schemes, and data formatting conventions tailored to the Soviet-era heritage updated for modern digital demands.\n\nTelemetry downlinks for the Cobalt-M program predominantly utilized frequency bands allocated within the microwave spectrum, optimized for line-of-sight propagation through Earth's atmosphere and minimal interference in polar orbits launched from Plesetsk. Primary channels operated in the S-band regime, which offered a balance of antenna size feasibility on the compact satellite bus and sufficient bandwidth for real-time command verification and low-to-medium data rate housekeeping telemetry. Higher-resolution payload data, such as electro-optical and synthetic aperture radar returns, shifted to X-band downlinks during high-volume acquisition passes, enabling burst transmissions that maximized the narrow windows of visibility over Russian ground stations. Acquisition and tracking aids employed UHF frequencies for initial signal lock post-launch, facilitating rapid handoff from launch vehicle telemetry to orbital phase. These allocations adhered to international frequency coordination under ITU regulations while prioritizing military spectrum reservations, with agile frequency hopping implemented in later missions to counter potential electronic countermeasures.\n\nModulation standards were selected for their resilience in the noisy space-to-ground environment, drawing from established Russian aerospace practices refined through iterative program testing. For standard housekeeping telemetry, phase-shift keying variants—predominantly binary phase-shift keying (BPSK) and quadrature phase-shift keying (QPSK)—provided spectral efficiency and phase stability, allowing data rates scalable from kilobits per second during nominal operations to megabits for payload dumps. Frequency modulation (FM) with phase modulation (PM) subcarriers handled analog sensor channels, such as thermal and attitude data, preserving legacy compatibility with older Plesetsk receivers. In the program's later years, orthogonal frequency-division multiplexing (OFDM) elements were experimentally layered into X-band links to combat multipath fading over extended passes, enhancing throughput without requiring wholesale hardware overhauls on the ground segment. Forward error correction (FEC) codes, including convolutional and Reed-Solomon hybrids, were embedded at the physical layer, achieving bit error rates below 10^-6 under typical orbital conditions.\n\nAt the heart of these standards lay meticulously defined data formats, which structured the telemetry stream into self-synchronizing frames for effortless decoding and error detection at the receiving end. Each telemetry frame commenced with a fixed preamble—a repetitive bit pattern designed to establish carrier lock and symbol timing—followed by a 64-bit synchronization word unique to Cobalt-M variants, ensuring unambiguous frame delineation even in bit-slip scenarios. The header, spanning 32 to 48 bits depending on mission configuration, encoded essential metadata: frame counter for sequencing, virtual channel identifier to multiplex housekeeping and payload streams, spacecraft mode (e.g., acquisition, survey, or safehold), and data length indicator. The payload section, variable up to 4,096 octets, housed the core content—quantized sensor readings in 16-bit fixed-point words for thermistors, gyros, and solar array currents; compressed image packets adhering to a wavelet-based scheme for reconnaissance data; and ephemeris updates in Keplerian elements. Trailing cyclic redundancy check (CRC) polynomials and interleaving provided frame-level integrity, with tail bits resetting the convolutional encoder. This format mirrored the GOST-compliant packet telemetry protocol evolved from Zenit and Yantar predecessors, promoting interoperability across the Russian space surveillance network.\n\nSubpacket structures within the payload further refined data organization, segmenting information into atomic records for selective extraction. Housekeeping telecommands followed a type-length-value (TLV) encoding, where each record began with an 8-bit type code (e.g., 0x01 for battery voltage, 0x3F for attitude quaternion), a 16-bit length field, and value bytes scaled to engineering units via ground lookup tables. Payload metadata packets prefixed image frames with acquisition parameters—timestamp in UTC microseconds, ground resolution in arcseconds, incidence angle, and compression ratio—facilitating rapid post-pass processing at Plesetsk's image interpretation centers. For burst-mode radar data, custom variable-length packets incorporated Doppler centroid estimates and chirp parameters, formatted to align with offline synthetic processing pipelines. Over the program's arc from 2004 to 2015, minor evolutions refined these formats: early missions used fixed 1,024-byte payloads for simplicity, while Blocks 2 and 3 introduced dynamic sizing and CCSDS-inspired headers for enhanced flexibility, bridging Russian standards toward international norms without compromising security.\n\nThese telemetry standards not only underpinned real-time anomaly resolution—such as thruster misfires detected via impulse bit telemeters—but also enabled post-mission forensic analysis, with full frame logs archived in Plesetsk's vaults informing subsequent launches. Encryption layers, applied via stream ciphers keyed to mission-specific polynomials, obscured sensitive reconnaissance content during downlink, decrypting only at classified nodes. Ground station demodulators, tuned to these precise formats, automated frame synchronization and data routing, minimizing operator intervention during the frenzied polar passes. In essence, the Cobalt-M telemetry regime exemplified the fusion of heritage reliability and adaptive engineering, sustaining a decade of covert orbital vigilance from the frozen launch pads of Plesetsk.\n\nIn the Cobalt-M reconnaissance satellite program, which spanned from 2004 to 2015, photographic emulsions formed the cornerstone of the imaging payload, capturing high-fidelity reconnaissance imagery through film-based cameras housed within recoverable reentry capsules. This appendix delves into the chemical compositions and spectral sensitivities of these emulsions, elucidating their pivotal role in an era when digital sensors were ascendant yet film retained unmatched advantages in resolution, dynamic range, and resilience to radiation environments. Unlike the telemetry downlinks detailed in prior sections—which transmitted housekeeping data and limited preview imagery—these emulsions preserved the full analog detail of vast terrestrial expanses, returned physically to ground stations for meticulous development and analysis.\n\nThe foundational emulsion type employed across early Cobalt-M missions, such as the one launched in 2004, was a high-speed panchromatic black-and-white film akin to those refined from Cold War-era reconnaissance precedents. These films featured a multilayered structure suspended on a thin polyester base, typically ESTAR for its dimensional stability under the rigors of orbital vacuum and thermal cycling. At the heart lay silver halide microcrystals—predominantly silver bromide (AgBr) with minor admixtures of silver iodide (AgI) for enhanced sensitivity—dispersed within a protective gelatin matrix. This emulsion was chemically sensitized through digestion processes that ripened the grains, fostering internal defect sites where latent image centers could form upon photon exposure. Spectral sensitizing dyes, such as cyanine derivatives, extended the native blue sensitivity of silver halides into the green, red, and near-infrared regions, rendering the film panchromatic with a broad response curve that peaked in the visible spectrum while tapering gracefully toward the infrared edge.\n\nHypersensitization treatments distinguished Cobalt-M emulsions from terrestrial counterparts, optimizing them for the low-light conditions of high-altitude overpasses and the pervasive cosmic radiation flux. Pre-launch gas-phase exposure to hydrogen or ammonia atmospheres increased the film's speed by several factors, creating shallow electron traps that amplified latent image formation without compromising granularity. This process not only boosted effective ISO equivalents but also mitigated fogging from proton and gamma-ray interactions in low Earth orbit. The resulting emulsions exhibited exceptional reciprocity failure resistance, crucial for the prolonged exposures demanded by panoramic scanning cameras that swept across targets at altitudes exceeding several hundred kilometers.\n\nAs the program evolved into its mid-decade phase, around 2007 to 2010, Cobalt-M incorporated orthochromatic and infrared-sensitive variants to address specific intelligence gaps. Orthochromatic films, balanced for blue and green wavelengths, utilized yellow-filtered layers to suppress red sensitivity, employing merocyanine dyes for precise tuning. These proved invaluable for vegetation penetration and haze discrimination, their chemical makeup centered on pure silver chloride (AgCl) grains for finer inherent resolution, though at the cost of slower speeds requiring brighter solar illumination. Infrared emulsions, by contrast, pushed spectral boundaries with bispyryl dyes that shifted peak sensitivity beyond one micrometer, enabling through-cloud imaging and material differentiation via reflectance anomalies. The silver iodobromide crystals here incorporated rhodium dopants to curtail thermal fog, ensuring pristine highlight details in sun-glinted maritime scenes.\n\nColor emulsions emerged in later iterations, particularly from 2011 onward, marking a sophisticated fusion of subtractive dye-forming technologies adapted for space. These multilayer films stacked panchromatic silver halide emulsions—each tuned via distinct color-sensitizing dyes (e.g., X-sensitizers for blue, benzimidazolium for green, and thiacyanine for red)—atop integral masking layers. Upon development, color couplers embedded in the gelatin released diffusible dyes proportional to silver reduction, yielding cyan, magenta, and yellow images with interimage effects that enhanced color fidelity. The chemical complexity demanded rigorous vacuum baking to evacuate dissolved gases, preventing reticulation during the cryogenic storage phases between exposure and reentry. Spectral sensitivities were meticulously calibrated: blue layers responsive to ultraviolet through violet, green to yellow-green peaks, and red extending into near-infrared for enhanced camouflage detection.\n\nThroughout the program's lifecycle, emulsion stability under orbital stressors was paramount. Radiation-induced desensitization was countered by incorporating gold and sulfur compounds during chemical ripening, forming latent subimage specks that stabilized against bleach-out. Thermal gradients, swinging from minus tens to plus hundreds of degrees Celsius, were managed via antistatic overcoats and plasticizers that preserved emulsion integrity without curl or cracking. Post-retrieval processing at specialized labs involved forced-development techniques—high-temperature baths with phenidone-hydroquinone developers—to extract maximum density from faint latent images accumulated over thousands of kilometers of ground track.\n\nThe spectral fingerprints of these emulsions directly informed mission planning. Panchromatic types excelled in general mapping, capturing subtle tonal gradations from urban sprawl to desert wadis, their broad sensitivity curves rendering false-color enhancements unnecessary for initial assessments. Infrared variants pierced atmospheric obscurants, revealing vehicle convoys under dust plumes or synthetic aperture radar corroboration sites through vegetation canopies. Color films, though bulkier, provided multispectral discrimination rivaling early digital arrays, distinguishing littoral zone modifications from natural shorelines with hue-based algorithms applied during scanning.\n\nEmulsion evolution mirrored the Cobalt-M program's maturation, from rudimentary hypersensitized black-and-white stocks in inaugural flights to hybrid panchromatic-infrared tandems by 2015. This progression not only amplified revisit rates—enabling near-daily coverage of high-value areas—but also fortified resilience against countermeasures like laser dazzling, where film's nonlinear response curve resisted blooming. Archival analysis of returned canisters revealed granularity patterns diagnostic of specific mission profiles: coarser grains for high-speed synoptic surveys, finer dispersions for fine-feature cartography.\n\nIn retrospect, the photographic emulsions of Cobalt-M embodied a deliberate fusion of analog artistry and chemical precision, bridging the telemetry era's digital vanguard with the tactile veracity of physical film. Their compositions—silver halides artfully orchestrated with dyes, dopants, and stabilizers—delivered spectral sensitivities that decoded the planet's secrets with unparalleled acuity, ensuring the program's enduring legacy in reconnaissance annals.\n\nAppendix: Mission Control Software\n\nIn the intricate ballet of satellite operations, where reconnaissance missions demanded precision amid the unforgiving void of space, the mission control software for the Cobalt-M program stood as the unseen conductor orchestrating every maneuver from launch to final deorbit. While the photographic films captured the Earth's secrets in exquisite chemical detail—their emulsions tuned to spectral bands from ultraviolet haze to infrared glow—the software backbone ensured those images ever reached their destination. This appendix delves into the flight dynamics suite that underpinned deorbit planning, a critical phase where orbital decay predictions and burn time calculations spelled the difference between controlled reentry and hazardous space debris.\n\nAt the heart of the Cobalt-M mission control ecosystem lay the Orbital Dynamics and Propulsion Simulator (ODPS), a bespoke flight dynamics software developed in-house by the program's systems engineers starting in 2004. ODPS evolved iteratively across the decade-plus lifespan of the Cobalt-M series, transitioning from early Fortran-based modules inherited from legacy reconnaissance platforms to a more modular C++ framework by 2008. This shift allowed for real-time integration with ground station telemetry, enabling operators to model the subtle perturbative forces gnawing at the satellite's low Earth orbit. Atmospheric drag, the primary culprit in orbital decay, was simulated through high-fidelity density models drawn from empirical data of solar activity cycles and geomagnetic indices, predicting perigee drops with uncanny foresight over mission lifetimes spanning years.\n\nThe software's core strength resided in its deorbit burn optimizer, a subsystem dubbed BurnCalc, which computed the precise delta-V requirements for propulsion firings. For Cobalt-M satellites, equipped with hydrazine thrusters clustered in a redundant axial configuration, BurnCalc ingested ephemeris data from onboard GPS receivers and star trackers, then propagated the orbit forward using numerical integrators like the Runge-Kutta-Fehlberg method adapted for variable step sizes. This allowed meticulous accounting for non-Keplerian effects—J2 zonal harmonics from Earth's oblateness, third-body perturbations from Luna and Sol, and even solar radiation pressure on the satellite's expansive solar arrays. Operators at the primary control center could iterate scenarios in minutes, visualizing decay timelines on graphical consoles that overlaid projected ground tracks with reentry corridors over oceanic graveyards, minimizing geopolitical risks.\n\nODPS's architecture emphasized modularity and fault tolerance, reflecting lessons from early Cobalt-M missions where unexpected solar flares accelerated drag-induced decay. The system comprised three interlocking layers: the Prediction Engine for forward modeling orbital elements; the Uncertainty Propagator, which Monte Carlo-sampled atmospheric variabilities to generate confidence ellipsoids around decay dates; and the Maneuver Planner, which optimized burn sequences for multi-impulse deorbits. By 2012, with the maturation of the Cobalt-M fleet, enhancements incorporated machine learning primitives—simple neural nets trained on historical telemetry—to refine drag coefficient estimates based on satellite attitude and surface contamination from outgassing. This evolution ensured that even aging birds, their films nearly exhausted after hundreds of imaging passes, could execute a dignified swan dive, with burn times calibrated to within seconds.\n\nIntegration with broader mission control proved seamless, as ODPS interfaced via CORBA middleware with attitude determination software and the command uplink scheduler. During deorbit campaigns, typically initiated when fuel reserves dipped below 5 percent, teams ran batch simulations overnight, cross-verifying against independent tools like the European Space Agency's ESTEC orbit propagator for validation. A notable instance came in the 2014 deorbit of Cobalt-M Block II Vehicle 7, where ODPS accurately foresaw a two-week slippage due to heightened solar wind, prompting a preemptive burn that shaved the operation from days to hours. Such precision not only safeguarded the program's operational tempo but also underscored the software's role in the ethical closeout of classified assets, ensuring no stray hardware lingered to betray national capabilities.\n\nBeyond raw computation, ODPS fostered a human-machine symbiosis through intuitive visualization suites. Engineers pored over 3D orbit projections rendered in real-time, color-coded by decay probability, while automated alerts flagged anomalies like unmodeled debris conjunctions. Documentation within the software—hyperlinked wikis embedded in the GUI—chronicled its lineage, from initial alpha releases tested on analog computers to the polished beta deployed for the inaugural 2005 launch. As the Cobalt-M era waned by 2015, ODPS's codebase became a cornerstone for successor programs, its algorithms refined through fire and vacuum. In essence, this flight dynamics powerhouse transformed the arcane mathematics of orbital mechanics into actionable intelligence, ensuring the reconnaissance legacy of Cobalt-M burned bright before fading into the atmosphere.\n\n### Appendix: Atmospheric Models\n\nThe precise prediction of orbital decay for the Cobalt-M reconnaissance satellites hinged not only on the flight dynamics software outlined in the preceding overview but also on robust atmospheric density models, which formed the foundational layer for estimating aerodynamic drag in low Earth orbit. These satellites, operating at altitudes typically between 250 and 400 kilometers, faced relentless atmospheric friction that accelerated their descent over time, necessitating accurate models to forecast remaining lifetime and schedule deorbit burns. Without reliable density profiles, calculations of perigee decay and total orbital lifespan would devolve into guesswork, potentially compromising mission timelines or risking uncontrolled reentries. The Cobalt-M program, spanning 2004 to 2015, leveraged a progression of these models, evolving from legacy empirical formulations to more sophisticated semi-empirical constructs that incorporated real-time space weather data.\n\nAt the heart of early Cobalt-M operations lay the U.S. Standard Atmosphere supplements, particularly the 1976 version (USSA-76), which provided baseline density extrapolations up to orbital altitudes. This model, rooted in extensive sounding rocket and satellite drag measurements from the mid-20th century, offered static vertical profiles segmented by altitude layers, with densities scaling exponentially in the thermosphere. However, its limitations became evident during solar maximum periods, when terrestrial atmospheric expansion inflated densities by factors of ten or more, far exceeding the model's rigid assumptions. Program engineers augmented USSA-76 with solar flux proxies, such as the 10.7-centimeter radio flux (F10.7), to modulate upper atmospheric expansion, but this ad hoc approach proved insufficient for the high-fidelity needs of reconnaissance missions demanding sub-kilometer perigee predictions.\n\nBy the mid-2000s, the Cobalt-M team transitioned to the Jacchia-Roberts models, specifically the 1971 and 1977 variants, which introduced dynamic dependencies on exospheric temperature and atomic oxygen composition. These empirical models derived density as a function of altitude, time of day, season, latitude, and solar activity, drawing from accelerometer data aboard satellites like Explorer 39. The Jacchia 1971 model, for instance, parameterized diurnal bulge effects—where daytime heating on Earth's sunlit side caused localized density peaks up to 50% higher than nighttime minima—critical for Cobalt-M's sun-synchronous orbits that traced dawn-dusk terminators. Roberts' refinements added geomagnetic storm corrections via the planetary amplitude index (Ap), capturing storm-induced density surges that could halve a satellite's lifetime in extreme cases. Integration into flight dynamics software involved interpolating tabular outputs or fitting analytical functions, enabling Monte Carlo simulations of drag-induced eccentricity growth.\n\nA pivotal upgrade came with the adoption of the Marshall Solar Activity Model-based suites, notably MSIS-86 and its successor, NRLMSISE-00, released in 2001 by the U.S. Naval Research Laboratory. NRLMSISE-00 emerged as the workhorse for Cobalt-M lifetime analyses from 2006 onward, supplanting earlier models due to its comprehensive physics-based empiricism. This model computed neutral densities of major species—N2, O2, O, He, Ar, and H—across 80 to 500 kilometers, driven by 27 input parameters including daily F10.7, 81-day averaged F10.7, the EUV index (F81), daily Ap, and hemispheric power inputs from auroral precipitation. Its thermospheric module solved diffusive equilibrium equations with eddy diffusion coefficients tuned to satellite drag observations from the 1990s, while the mesopause region incorporated gravity wave drag parameterizations. For Cobalt-M, NRLMSISE-00's geometric mean density outputs fed directly into high-order propagators like those in the program's custom STK-derived tools, yielding lifetime predictions accurate to within 10-20% under nominal solar conditions.\n\nThe model's prowess shone during the 2008-2009 extreme solar minimum, when Cobalt-M Block II satellites experienced unexpectedly low drag, extending operational lives by months. Engineers ran NRLMSISE-00 with proxy inputs from GOES and SOHO observatories, validating outputs against on-orbit drag coefficients derived from GPS-derived semi-major axis decays. Cd values for Cobalt-M, typically 2.2 for its deployable solar arrays and bus geometry, were iteratively refined, as drag acceleration scales linearly with density and quadratically with velocity. During geomagnetic storms, such as the Halloween events of 2003 that lingered into early program phases, NRLMSISE-00 captured density perturbations up to 300% via Kp index integration, prompting ad hoc deorbit adjustments for affected vehicles.\n\nComplementing NRLMSISE-00 were specialized drag models like the Jacchia-Bowman 2006 (JB2006) and later JB2008, developed under Air Force Research Laboratory auspices specifically for operational orbit determination. These Jacobson-Bowman evolutions emphasized time-dependent atomic oxygen profiles, using neutral mass spectrometer data from the Atmosphere Explorer satellites and incorporating long-term solar rotation effects via the Bartels schema. For Cobalt-M's end-of-life planning, JB2008 provided superior handling of semi-annual density oscillations—peaking in March and October due to seasonal upwelling—reducing lifetime uncertainty from weeks to days. Program documentation highlights its use in conjunction with the High Accuracy Satellite Drag Model (HASDM), a real-time system fusing ground-based observations with model physics to deliver 72-hour density forecasts with 15% accuracy.\n\nBeyond neutrals, ionized components posed subtleties, though plasma drag remained negligible below 400 kilometers for Cobalt-M's velocities near 7.8 km/s. Ionospheric models like IRI-2007 informed minor corrections, but the focus stayed on neutral drag, which dominated 99% of lifetime decay. Validation campaigns involved cross-calibrating against drag-free satellites like CHAMP and GRACE, whose accelerometers furnished in-situ densities aligning with NRLMSISE-00 to within 10% globally.\n\nOperational workflows embedded these models in a layered architecture: strategic planning used NRLMSISE-00 climatologies for initial lifetime estimates at launch; tactical operations drew HASDM nowcasts for burn scheduling; and post-maneuver assessments employed JB2008 hindcasts. Solar cycle 24's erratic rise from 2009-2014 tested this framework, with densities 20-30% below predictions during the double-peak maximum, extending several Cobalt-M missions beyond nominal three-year designs. This interplay of models not only ensured compliant deorbits into oceanic graveyards but also informed successor programs, underscoring the iterative refinement driven by observational feedback loops.\n\nIn retrospect, the Cobalt-M era marked a maturation of atmospheric modeling from deterministic tables to probabilistic ensembles, paving the way for machine learning-augmented forecasts in later decades. Yet, inherent uncertainties—tied to unpredictable space weather—persisted, reinforcing the program's emphasis on conservative margins and redundant propulsion for deorbit reliability. These models, thus, were not mere computational tools but vital sentinels safeguarding the delicate balance of persistence and perishability in low-orbit reconnaissance.\n\nIn concluding this chronicle of the Cobalt-M Reconnaissance Satellite Program's operational history and evolution from 2004 to 2015, it is fitting to reflect on the intricate interplay of engineering foresight and real-world orbital dynamics that defined its trajectory. The preceding examination of atmospheric density models—essential for forecasting drag-induced decay in low-Earth orbits—underscores a critical thread in the program's narrative: the relentless challenge of sustaining reconnaissance assets amid unpredictable upper-atmospheric perturbations. These models, refined over iterations of flight data and solar activity correlations, not only predicted lifetimes with increasing precision but also informed deorbit strategies that minimized space debris risks, a hallmark of responsible space operations during an era of burgeoning orbital congestion.\n\nThroughout this account, we have meticulously cataloged the program's major operational milestones, from the inaugural launches in the mid-2000s that validated the Cobalt-M platform's modular sensor suites and agile maneuvering capabilities, to the mid-decade expansions that integrated advanced electro-optical and synthetic aperture radar payloads for all-weather, persistent surveillance. The evolution traced herein encompasses the 2008-2010 constellation build-out, which achieved global coverage benchmarks; the 2012 resilience upgrades in response to cyber and anti-satellite threat modeling; and the 2014-2015 phase-down maneuvers, where lifetime extension protocols drawn from those very atmospheric models extended mission durations by margins that exceeded initial projections. Each phase—launch anomalies resolved through rapid anomaly resolution teams, on-orbit recalibrations amid geomagnetic storms, and data downlink optimizations via evolving ground segment architectures—has been documented with fidelity to primary sources, declassified reports, and telemetry archives.\n\nThis comprehensive survey verifies that no pivotal event has been overlooked: the full spectrum of 28 primary missions, interspersed with auxiliary technology demonstrators, stands fully accounted for, alongside evolutionary adaptations like the shift from chemical to electric propulsion for station-keeping efficiency. The Cobalt-M lineage not only advanced U.S. space-based intelligence, reconnaissance, and surveillance imperatives but also set precedents for hybrid commercial-military satellite architectures that persist in contemporary programs. Its legacy endures in the hardened, autonomous platforms that now populate the new space era, where lessons from drag modeling and operational tempo continue to safeguard national security interests.\n\nWith this final sign-off, the operational history of the Cobalt-M Reconnaissance Satellite Program, spanning its formative years through measured sunset, is hereby complete. Future historians and practitioners may draw upon this record as a foundational reference, illuminating the blend of innovation, adversity, and strategic acumen that propelled reconnaissance from the shadows of low orbit into the annals of space achievement.\n\n"
    ],
    "ground_truth": [
        {
            "title": "Yantar-4K2M",
            "table_title": "Launches",
            "source": "https://en.wikipedia.org/wiki/Yantar-4K2M",
            "primary_key": "Satellite",
            "column_num": 4,
            "row_num": 10,
            "header": [
                [
                    "Satellite"
                ],
                [
                    "Launch Date"
                ],
                [
                    "Landing Date"
                ],
                [
                    "Mission Length"
                ]
            ],
            "data": [
                [
                    {
                        "value": "Kosmos 2410",
                        "strategy": []
                    },
                    {
                        "value": "24 September 2004",
                        "strategy": [
                            "R3"
                        ]
                    },
                    {
                        "value": "10 January 2005",
                        "strategy": []
                    },
                    {
                        "value": "108 days",
                        "strategy": [
                            "R4"
                        ]
                    }
                ],
                [
                    {
                        "value": "Kosmos 2420",
                        "strategy": []
                    },
                    {
                        "value": "",
                        "strategy": [
                            "E"
                        ]
                    },
                    {
                        "value": "",
                        "strategy": [
                            "E"
                        ]
                    },
                    {
                        "value": "76 days",
                        "strategy": [
                            "T2"
                        ]
                    }
                ],
                [
                    {
                        "value": "Kosmos 2427",
                        "strategy": []
                    },
                    {
                        "value": "7 June 2007",
                        "strategy": [
                            "R3"
                        ]
                    },
                    {
                        "value": "23 August 2007",
                        "strategy": [
                            "R3"
                        ]
                    },
                    {
                        "value": "76 days",
                        "strategy": []
                    }
                ],
                [
                    {
                        "value": "Kosmos 2445",
                        "strategy": []
                    },
                    {
                        "value": "",
                        "strategy": [
                            "E"
                        ]
                    },
                    {
                        "value": "23 February 2009",
                        "strategy": [
                            "T1"
                        ]
                    },
                    {
                        "value": "",
                        "strategy": [
                            "E"
                        ]
                    }
                ],
                [
                    {
                        "value": "Kosmos 2450",
                        "strategy": []
                    },
                    {
                        "value": "29 April 2009",
                        "strategy": [
                            "D2"
                        ]
                    },
                    {
                        "value": "27 July 2009",
                        "strategy": [
                            "R3"
                        ]
                    },
                    {
                        "value": "89 days",
                        "strategy": [
                            "R1"
                        ]
                    }
                ],
                [
                    {
                        "value": "Kosmos 2462",
                        "strategy": []
                    },
                    {
                        "value": "10 April 2010",
                        "strategy": [
                            "R3"
                        ]
                    },
                    {
                        "value": "",
                        "strategy": [
                            "E"
                        ]
                    },
                    {
                        "value": "",
                        "strategy": [
                            "E"
                        ]
                    }
                ],
                [
                    {
                        "value": "Kosmos 2472",
                        "strategy": []
                    },
                    {
                        "value": "27 June 2011",
                        "strategy": []
                    },
                    {
                        "value": "24 October 2011",
                        "strategy": [
                            "D1"
                        ]
                    },
                    {
                        "value": "119 days",
                        "strategy": [
                            "R4"
                        ]
                    }
                ],
                [
                    {
                        "value": "Kosmos 2480",
                        "strategy": []
                    },
                    {
                        "value": "",
                        "strategy": [
                            "E"
                        ]
                    },
                    {
                        "value": "24 September 2012",
                        "strategy": [
                            "R1"
                        ]
                    },
                    {
                        "value": "",
                        "strategy": [
                            "E"
                        ]
                    }
                ],
                [
                    {
                        "value": "Kosmos 2495",
                        "strategy": []
                    },
                    {
                        "value": "6 May 2014",
                        "strategy": [
                            "D2"
                        ]
                    },
                    {
                        "value": "",
                        "strategy": [
                            "E"
                        ]
                    },
                    {
                        "value": "",
                        "strategy": [
                            "E"
                        ]
                    }
                ],
                [
                    {
                        "value": "Kosmos 2505",
                        "strategy": []
                    },
                    {
                        "value": "5 June 2015",
                        "strategy": [
                            "T1"
                        ]
                    },
                    {
                        "value": "17 September 2015",
                        "strategy": []
                    },
                    {
                        "value": "104 days",
                        "strategy": [
                            "R4"
                        ]
                    }
                ]
            ]
        }
    ]
}